Workbook

Sheet VW+ANDES
A1: Sucursal | B1: Marca | C1: Versión | D1: Código Interno | E1: Año | F1: Numero Chasis | G1: Cliente | H1: Vendedor | I1: Tipo Vehiculo | J1: Forma de Pago | K1: Unidad Costo Factura (-) | L1: Gastos (-) | M1: Trámites (-) | N1: Costo Accesorios (-) | O1: Notas de Crédito (+) | P1: Venta Neta con tramites (+) | Q1: Acción Comercial Contado (Bruto) | R1: Acción Comercial Contado (Neto) (+) | S1: Acción Comercial Crèdito (Bruto) | T1: Acción Comercial Crédito Pagada (Neto) (+) | U1: Bono Crédito (Bruto) | V1: Bono Crédito (Neto) (+) | W1: Bono Volumen Bruto | X1: Bono Volumen Neto (+) | Y1: Margen Final | Z1: Margen con Bonos en Sistema | AA1: Diferencias | AB1: % MARGEN | AC1: Fecha Venta | AD1: Folio Venta | AE1: Rut | AF1: Digito | AG1: Dirección | AH1: Teléfono Fijo | AI1: Teléfono Móvil | AJ1: Teléfono Comercial | AK1: Comuna | AL1: Fecha Nacimiento | AM1: E-mail | AN1: Placa Patente | AO1: Tipo Vehículo | AP1: Modelo | AQ1: Codigo Version | AR1: Color | AS1: Numero VIN | AT1: Numero Serie | AU1: Condición | AV1: Estado Venta | AW1: Folio Facturación | AX1: Fecha Facturación | AY1: Tipo Documento | AZ1: Documento | BA1: Precio Compra | BB1: Vencimiento Factura | BC1: Vendedor Cotización | BD1: Folio | BE1: Medio Contacto | BF1: Vencimiento Documento | BG1: Tipo Venta | BH1: Moneda Venta | BI1: Patente Pago | BJ1: Días Stock | BK1: Precio Lista | BL1: Bono Lista Precio | BM1: Descuento Unidad | BN1: Unidad Venta | BO1: Unidad Costo | BP1: Unidad Margen | BQ1: % | BR1: Tramites Descuento/Recargo | BS1: Tramites Venta | BT1: Tramites Costo | BU1: Tramites Margen | BV1: %1 | BW1: Accesorios Descuento/Recargo | BX1: Accesorios Venta | BY1: Accesorios Costo | BZ1: Accesorios Margen | CA1: %2 | CB1: Contratos DR ML | CC1: Contratos Sub Total ML | CD1: Contratos Costo ML | CE1: Contratos Margen ML | CF1: Contratos Margen Pje | CG1: Total Lista Precio | CH1: SubTotal Venta | CI1: SubTotal Costo | CJ1: SubTotal Margen + Crédito + Seguro | CK1: %3 | CL1: Margen Sin Intereses | CM1: Sub Total Margen ML Sin Inter~s Pje | CN1: Total Interés | CO1: Total Retoma | CP1: Total Abono | CQ1: Total Saldo | CR1: Total Venta Trámite | CS1: Total Venta Accesorios | CT1: Total Venta | CU1: Venta Sin Creditos Y Seguros | CV1: Margen de Venta | CW1: Pje. Margen de Venta | CX1: Entidad Crédito | CY1: Margen Crédito | CZ1: Entidad Seguro | DA1: Margen Seguro | DB1: Bono | DC1: Gasto | DD1: Nacionalidad
A2: CASA MATRIZ NUEVOS | B2: VOLKSWAGEN | C2: Polo 1.6 MT Comfortline - 81 kW/101 CV | D2: AN-25-01-0004 | E2: 2025 | F2: 9BWAL5BZ5ST639230 | G2: ANDREA BETSABE REQUENA ORTIZ | H2: JUAN PABLO GONZALEZ ACUÑA | I2: N | J2: Forum | K2: =BA2 -> 13320731 | L2: 90000 | M2: =BT2 -> 564820 | P2: =CU2 -> 12312719 | Q2: =R2*1.19 -> 1199999.6 | R2: 1008403 | S2: =T2*1.19 -> 999999.84 | T2: 840336 | U2: 150000 | V2: =U2/1.19 -> 126050.42 | W2: =X2*1.19 -> 0 | Y2: =-K2-L2-M2-N2+O2+P2+R2+T2+V2+X2 -> 311957.42 | Z2: =VLOOKUP(D2,'Archivo con Bonos Ingresados '!V:CB,59,0) -> 311957 | AA2: =Z2-Y2 -> -0.42016807 | AB2: =Y2*100/CU2 -> 2.5336193 | AC2: 07-01-2025 11:16:30 | AD2: 5896 | AE2: 17833721 | AF2: 1 | AG2: PASAJE SANTA RAQUEL 0501 | AH2: 976670831 | AK2: PUENTE ALTO | AL2: 19/02/1991 | AM2: requenaortiz@gmail.com | AO2: AUTOMOVIL | AP2: POLO | AQ2: 782024 | AR2: BLANCO CANDY | AS2: 9BWAL5BZ5ST639230 | AT2: 9BWAL5BZ5ST639230 | AU2: NUEVO Y SIN USO | AV2: Facturada | AW2: 19841 | AX2: 09-01-2025 0:00:00 | AZ2: Guía de Despacho: 1 - Factura Electrónica: 1842500 | BA2: 13320731 | BB2: 08-02-2025 0:00:00 | BD2: 0 | BE2: SALON | BF2: 08-02-2025 0:00:00 | BG2: RETAIL | BH2: Peso | BJ2: 0 | BK2: 14277311 | BL2: -2100840 | BM2: -428571 | BN2: 11747899 | BO2: 13320731 | BP2: -1572832 | BQ2: -13.39 % | BR2: 0 | BS2: 564820 | BT2: 564820 | BU2: 0 | BV2: 0 % | BW2: 0 | BX2: 0 | BY2: 0 | BZ2: 0 | CA2: 0 % | CB2: 0 | CC2: 0 | CD2: 0 | CE2: 0 | CF2: 0 % | CG2: 12176471 | CH2: 12312719 | CI2: 13885551 | CJ2: -1572832 | CK2: -12.77 % | CL2: -1572832 | CM2: -12.77 % | CN2: 0 | CO2: 0 | CP2: 14544820 | CQ2: 0 | CR2: 564820 | CS2: 0 | CT2: 14544820 | CU2: 12312719 | CV2: -1572832 | CW2: -12.77 % | CY2: 0 | DA2: 0 | DB2: 0 | DC2: 0
A3: ANDES MOTOR | B3: MAXUS | C3: T60 4X2 GL MT E6 | D3: AN-24-08-0083 | E3: 2025 | F3: LSFAM11A4RA077914 | G3: ASCANIO OSORIO AVENDAÑO SER.ING.MEC.MOT.ASES.PINT.IND.Y GRALES .EIRL | H3: Manuel Rodrigo Hurtado Melo | I3: N | J3: Directo | K3: =BA3 -> 19586800 | L3: 235000 | M3: =BT3 -> 658602 | P3: =CU3 -> 19130902 | Q3: =R3*1.19 -> 2026808 | R3: 1703200 | S3: =T3*1.19 -> 0 | V3: =U3/1.19 -> 0 | W3: =X3*1.19 -> 0 | Y3: =-K3-L3-M3-N3+O3+P3+R3+T3+V3+X3 -> 353700 | Z3: =VLOOKUP(D3,'Archivo con Bonos Ingresados '!V:CB,59,0) -> 353700 | AA3: =Z3-Y3 -> 0 | AB3: =Y3*100/CU3 -> 1.8488412 | AC3: 10-01-2025 15:37:20 | AD3: 5911 | AE3: 76692680 | AF3: 0 | AG3: PETRONILA 149 50 | AI3: 985433201 | AK3: ANTOFAGASTA | AL3: 01/01/2022 | AM3: ascanio.osorioc@gmail.com | AP3: T60 | AQ3: T60 4X2 GL MT E6 | AR3: GRIS | AS3: LSFAM11A4RA077914 | AT3: LSFAM11A4RA077914 | AU3: NUEVO Y SIN USO | AV3: Parcial Facturada | AW3: 19862 | AX3: 14-01-2025 0:00:00 | AZ3: Guía de Despacho: 1 - Factura Electrónica: 186708 | BA3: 19586800 | BB3: 14-01-2025 0:00:00 | BD3: 0 | BE3: SITIO WEB | BF3: 14-01-2025 0:00:00 | BG3: FLOTA | BH3: Peso | BJ3: 109 | BK3: 21290000 | BL3: -2767700 | BM3: -50000 | BN3: 18472300 | BO3: 19586800 | BP3: -1114500 | BQ3: -6.03 % | BR3: 0 | BS3: 658602 | BT3: 658602 | BU3: 0 | BV3: 0 % | BW3: 0 | BX3: 0 | BY3: 0 | BZ3: 0 | CA3: 0 % | CB3: 0 | CC3: 0 | CD3: 0 | CE3: 0 | CF3: 0 % | CG3: 18522300 | CH3: 19130902 | CI3: 20245402 | CJ3: -1114500 | CK3: -5.83 % | CL3: -1114500 | CM3: -5.83 % | CN3: 0 | CO3: 0 | CP3: 22640639 | CQ3: 0 | CR3: 658602 | CS3: 0 | CT3: 22640639 | CU3: 19130902 | CV3: -1114500 | CW3: -5.83 % | CY3: 0 | DA3: 0 | DB3: 0 | DC3: 0
A4: CASA MATRIZ NUEVOS | B4: VOLKSWAGEN | C4: T-Cross 1.0 TSI AT Highline - 85 kW/116 CV | D4: AN-24-12-0036 | E4: 2025 | F4: 9BWBH6BF2S4053564 | G4: BERNARDITA MARIA SOLER LEON | H4: ROBERTO LOBOS GUTIERREZ | I4: N | J4: Directo | K4: =BA4 -> 17651815 | L4: 175000 | M4: =BT4 -> 977613 | P4: =CU4 -> 18338958 | Q4: =R4*1.19 -> 1449999.5 | R4: 1218487 | S4: =T4*1.19 -> 0 | V4: =U4/1.19 -> 0 | W4: =X4*1.19 -> 224900.48 | X4: 188992 | Y4: =-K4-L4-M4-N4+O4+P4+R4+T4+V4+X4 -> 942009 | Z4: =VLOOKUP(D4,'Archivo con Bonos Ingresados '!V:CB,59,0) -> 942009 | AA4: =Z4-Y4 -> 0 | AB4: =Y4*100/CU4 -> 5.136655 | AC4: 24-01-2025 17:04:54 | AD4: 5958 | AE4: 15313830 | AF4: 3 | AG4: VASCO DE GAMA 4596 DEPTO 17 | AI4: 961689307 | AK4: LAS CONDES | AL4: 01/01/1900 | AM4: bernarditasoler@gmail.com | AO4: STATION WAGON | AP4: T CROSS | AQ4: BF34K311 | AR4: PLATA PIRITA | AS4: 9BWBH6BF2S4053564 | AT4: 9BWBH6BF2S4053564 | AU4: NUEVO Y SIN USO | AV4: Parcial Facturada | AW4: 19918 | AX4: 27-01-2025 0:00:00 | AZ4: Guía de Despacho: 1 - Factura Electrónica: 1841782 | BA4: 17651815 | BB4: 27-01-2025 0:00:00 | BD4: 0 | BE4: WEB CONCESIONARIO | BF4: 27-01-2025 0:00:00 | BG4: CC | BH4: Peso | BJ4: 39 | BK4: 18899160 | BL4: -1218487 | BM4: -571429 | BN4: 17109244 | BO4: 17651815 | BP4: -542571 | BQ4: -3.17 % | BR4: 0 | BS4: 977613 | BT4: 977613 | BU4: 0 | BV4: 0 % | BW4: 55336 | BX4: 252101 | BY4: 0 | BZ4: 0 | CA4: 0 % | CB4: 0 | CC4: 0 | CD4: 0 | CE4: 0 | CF4: 0 % | CG4: 17680673 | CH4: 18338958 | CI4: 18629428 | CJ4: -290470 | CK4: -1.58 % | CL4: -290470 | CM4: -1.58 % | CN4: 0 | CO4: 0 | CP4: 21637613 | CQ4: 0 | CR4: 977613 | CS4: 252101 | CT4: 21637614 | CU4: 18338958 | CV4: -290470 | CW4: -1.58 % | CY4: 0 | DA4: 0 | DB4: 0 | DC4: 0
A5: CASA MATRIZ NUEVOS | B5: VOLKSWAGEN | C5: Saveiro 1.6 MT Cabina Simple Lite | D5: AN-24-11-0061 | E5: 2025 | F5: 9BWKL45UXSP031761 | G5: COMERCIAL OXIPROTEX LTDA. | H5: ROBERTO LOBOS GUTIERREZ | I5: N | J5: Directo | K5: =BA5 -> 11047360 | L5: 90000 | M5: =BT5 -> 0 | P5: =CU5 -> 11344538 | Q5: =R5*1.19 -> 1487500 | R5: 1250000 | S5: =T5*1.19 -> 0 | V5: =U5/1.19 -> 0 | W5: =X5*1.19 -> 0 | Y5: =-K5-L5-M5-N5+O5+P5+R5+T5+V5+X5 -> 1457178 | Z5: =VLOOKUP(D5,'Archivo con Bonos Ingresados '!V:CB,59,0) -> 1457178 | AA5: =Z5-Y5 -> 0 | AB5: =Y5*100/CU5 -> 12.844754 | AC5: 14-01-2025 14:19:05 | AD5: 5926 | AE5: 76937697 | AF5: 6 | AG5: FCO. BILBAO 1860 3 301 | AH5: 64 2644300 | AK5: OSORNO | AL5: 01/01/2000 | AM5: ABASTECIMIENTO@INTEGRA-CHILE.CL | AO5: CAMIONETA | AP5: SAVEIRO | AQ5: 5URTT412 | AR5: BLANCO CANDY | AS5: 9BWKL45UXSP031761 | AT5: 9BWKL45UXSP031761 | AU5: NUEVO Y SIN USO | AV5: Facturada | AW5: 19936 | AX5: 29-01-2025 0:00:00 | AZ5: Guía de Despacho: 1 - Factura Electrónica: 1840823 - Nota de Crédito Electrónica: 3062529 | BA5: 11047360 | BB5: 28-02-2025 0:00:00 | BD5: 0 | BE5: SALON | BF5: 28-02-2025 0:00:00 | BG5: CC | BH5: Peso | BJ5: 0 | BK5: 12640000 | BL5: -1295462 | BM5: 0 | BN5: 11344538 | BO5: 9797360 | BP5: 1547178 | BQ5: 13.64 % | BR5: 0 | BS5: 0 | BT5: 0 | BU5: 0 | BV5: 0 % | BW5: 0 | BX5: 0 | BY5: 0 | BZ5: 0 | CA5: 0 % | CB5: 0 | CC5: 0 | CD5: 0 | CE5: 0 | CF5: 0 % | CG5: 11344538 | CH5: 11344538 | CI5: 9797360 | CJ5: 1547178 | CK5: 13.64 % | CL5: 1547178 | CM5: 13.64 % | CN5: 0 | CO5: 0 | CP5: 13500000 | CQ5: 0 | CR5: 0 | CS5: 0 | CT5: 13500000 | CU5: 11344538 | CV5: 1547178 | CW5: 13.64 % | CY5: 0 | DA5: 0 | DB5: 1487500 | DC5: 0
A6: CASA MATRIZ NUEVOS | B6: VOLKSWAGEN | C6: Saveiro 1.6 MT Cabina Simple Lite | D6: AN-24-11-0062 | E6: 2025 | F6: 9BWKL45UXSP033087 | G6: CONSULTORA Y GESTION DEXTRA LIMITADA | H6: JUAN PABLO GONZALEZ ACUÑA | I6: N | J6: Forum | K6: =BA6 -> 11047360 | L6: 90000 | M6: =BT6 -> 299330 | P6: =CU6 -> 10075330 | Q6: =R6*1.19 -> 1487500 | R6: 1250000 | S6: =T6*1.19 -> 0 | U6: 150000 | V6: =U6/1.19 -> 126050.42 | W6: =X6*1.19 -> 499999.92 | X6: 420168 | Y6: =-K6-L6-M6-N6+O6+P6+R6+T6+V6+X6 -> 434858.42 | Z6: =VLOOKUP(D6,'Archivo con Bonos Ingresados '!V:CB,59,0) -> 14690 | AA6: =Z6-Y6 -> -420168.42 | AB6: =Y6*100/CU6 -> 4.3160712 | AC6: 08-01-2025 11:12:40 | AD6: 5898 | AE6: 76193982 | AF6: 3 | AG6: BADAJOZ 100 OF 1003 PISO 10 | AH6: 977092999 | AK6: LAS CONDES | AM6: roberto.alvarez@dextraltda.cl | AO6: CAMIONETA | AP6: SAVEIRO | AQ6: 5URTT412 | AR6: BLANCO CANDY | AS6: 9BWKL45UXSP033087 | AT6: 9BWKL45UXSP033087 | AU6: NUEVO Y SIN USO | AV6: Facturada | AW6: 19852 | AX6: 13-01-2025 0:00:00 | AZ6: Guía de Despacho: 1 - Factura Electrónica: 1840743 - Nota de Crédito Electrónica: 3062485 | BA6: 11047360 | BB6: 12-02-2025 0:00:00 | BD6: 0 | BE6: SALON | BF6: 12-02-2025 0:00:00 | BG6: RETAIL | BH6: Peso | BJ6: 0 | BK6: 12640000 | BL6: -2050000 | BM6: -814000 | BN6: 9776000 | BO6: 9797360 | BP6: -21360 | BQ6: -0.22 % | BR6: 0 | BS6: 299330 | BT6: 299330 | BU6: 0 | BV6: 0 % | BW6: 0 | BX6: 0 | BY6: 0 | BZ6: 0 | CA6: 0 % | CB6: 0 | CC6: 0 | CD6: 0 | CE6: 0 | CF6: 0 % | CG6: 10590000 | CH6: 10075330 | CI6: 10096690 | CJ6: -21360 | CK6: -0.21 % | CL6: -21360 | CM6: -0.21 % | CN6: 0 | CO6: 0 | CP6: 11932770 | CQ6: 0 | CR6: 299330 | CS6: 0 | CT6: 11932770 | CU6: 10075330 | CV6: -21360 | CW6: -0.21 % | CY6: 0 | DA6: 0 | DB6: 1487500 | DC6: 0
A7: CASA MATRIZ NUEVOS | B7: VOLKSWAGEN | C7: Saveiro 1.6 MT Cabina Simple Lite | D7: AN-24-11-0082 | E7: 2025 | F7: 9BWKL45UXSP007119 | G7: DANDILION INSPECCION LIMITADA | H7: JUAN PABLO GONZALEZ ACUÑA | I7: N | J7: Santander | K7: =BA7 -> 11047360 | L7: 90000 | M7: =BT7 -> 381560 | P7: =CU7 -> 10157560 | Q7: =R7*1.19 -> 1687499.7 | R7: 1418067 | S7: =T7*1.19 -> 0 | V7: =U7/1.19 -> 0 | W7: =X7*1.19 -> 499999.92 | X7: 420168 | Y7: =-K7-L7-M7-N7+O7+P7+R7+T7+V7+X7 -> 476875 | Z7: =VLOOKUP(D7,'Archivo con Bonos Ingresados '!V:CB,59,0) -> 56707 | AA7: =Z7-Y7 -> -420168 | AB7: =Y7*100/CU7 -> 4.6947791 | AC7: 07-01-2025 10:13:45 | AD7: 5894 | AE7: 76296875 | AF7: 4 | AG7: LAREDO 8357 OF 21 | AH7: 954061070 | AK7: LAS CONDES | AM7: eruz@dandilion.cl | AO7: CAMIONETA | AP7: SAVEIRO | AQ7: 5URTT412 | AR7: BLANCO CANDY | AS7: 9BWKL45UXSP007119 | AT7: 9BWKL45UXSP007119 | AU7: NUEVO Y SIN USO | AV7: Facturada | AW7: 19857 | AX7: 14-01-2025 0:00:00 | AZ7: Guía de Despacho: 1 - Factura Electrónica: 1840728 - Nota de Crédito Electrónica: 3062075 | BA7: 11047360 | BB7: 14-01-2025 0:00:00 | BD7: 0 | BE7: SALON | BF7: 14-01-2025 0:00:00 | BG7: RETAIL | BH7: Peso | BJ7: 0 | BK7: 12640000 | BL7: -2050000 | BM7: -814000 | BN7: 9776000 | BO7: 9629293 | BP7: 146707 | BQ7: 1.5 % | BR7: 0 | BS7: 381560 | BT7: 381560 | BU7: 0 | BV7: 0 % | BW7: 0 | BX7: 0 | BY7: 0 | BZ7: 0 | CA7: 0 % | CB7: 0 | CC7: 0 | CD7: 0 | CE7: 0 | CF7: 0 % | CG7: 10590000 | CH7: 10157560 | CI7: 10010853 | CJ7: 146707 | CK7: 1.44 % | CL7: 146707 | CM7: 1.44 % | CN7: 0 | CO7: 0 | CP7: 12015000 | CQ7: 0 | CR7: 381560 | CS7: 0 | CT7: 12015000 | CU7: 10157560 | CV7: 146707 | CW7: 1.44 % | CY7: 0 | DA7: 0 | DB7: 1687500 | DC7: 0
A8: CASA MATRIZ NUEVOS | B8: VOLKSWAGEN | C8: Saveiro 1.6 MT Cabina Simple Lite | D8: AN-24-11-0060 | E8: 2025 | F8: 9BWKL45U9SP015874 | G8: DANDILION INSPECCION LIMITADA | H8: JUAN PABLO GONZALEZ ACUÑA | I8: N | J8: Santander | K8: =BA8 -> 11047360 | L8: 90000 | M8: =BT8 -> 381560 | P8: =CU8 -> 10971560 | Q8: =R8*1.19 -> 1687499.7 | R8: 1418067 | S8: =T8*1.19 -> 0 | V8: =U8/1.19 -> 0 | W8: =X8*1.19 -> 0 | Y8: =-K8-L8-M8-N8+O8+P8+R8+T8+V8+X8 -> 870707 | Z8: =VLOOKUP(D8,'Archivo con Bonos Ingresados '!V:CB,59,0) -> 870707 | AA8: =Z8-Y8 -> 0 | AB8: =Y8*100/CU8 -> 7.9360364 | AC8: 07-01-2025 10:15:54 | AD8: 5895 | AE8: 76296875 | AF8: 4 | AG8: LAREDO 8357 OF 21 | AH8: 954061070 | AK8: LAS CONDES | AM8: eruz@dandilion.cl | AO8: CAMIONETA | AP8: SAVEIRO | AQ8: 5URTT412 | AR8: BLANCO CANDY | AS8: 9BWKL45U9SP015874 | AT8: 9BWKL45U9SP015874 | AU8: NUEVO Y SIN USO | AV8: Facturada | AW8: 19858 | AX8: 14-01-2025 0:00:00 | AZ8: Guía de Despacho: 1 - Factura Electrónica: 1840658 - Nota de Crédito Electrónica: 3062073 | BA8: 11047360 | BB8: 14-01-2025 0:00:00 | BD8: 0 | BE8: SALON | BF8: 14-01-2025 0:00:00 | BG8: FLOTA | BH8: Peso | BJ8: 0 | BK8: 12640000 | BL8: -2050000 | BM8: 0 | BN8: 10590000 | BO8: 9629293 | BP8: 960707 | BQ8: 9.07 % | BR8: 0 | BS8: 381560 | BT8: 381560 | BU8: 0 | BV8: 0 % | BW8: 0 | BX8: 0 | BY8: 0 | BZ8: 0 | CA8: 0 % | CB8: 0 | CC8: 0 | CD8: 0 | CE8: 0 | CF8: 0 % | CG8: 10590000 | CH8: 10971560 | CI8: 10010853 | CJ8: 960707 | CK8: 8.76 % | CL8: 960707 | CM8: 8.76 % | CN8: 0 | CO8: 0 | CP8: 14657464 | CQ8: -1673804 | CR8: 381560 | CS8: 0 | CT8: 12983660 | CU8: 10971560 | CV8: 960707 | CW8: 8.76 % | CY8: 0 | DA8: 0 | DB8: 1687500 | DC8: 0
A9: CASA MATRIZ NUEVOS | B9: VOLKSWAGEN | C9: Nivus 1.0 TSI AT Highline 85KW/116CV 5 p | D9: AN-25-01-0035 | E9: 2025 | F9: 9BWCH6CH8RP052805 | G9: DANIEL JACK BROOKS BRAVO | H9: ROBERTO LOBOS GUTIERREZ | I9: N | J9: Lucy | K9: =BA9 -> 18103335 | L9: 145000 | M9: =BT9 -> 784164 | P9: =CU9 -> 15910214 | Q9: =R9*1.19 -> 3150000.2 | R9: 2647059 | S9: =T9*1.19 -> 999999.84 | T9: 840336 | U9: 150000 | V9: =U9/1.19 -> 126050.42 | W9: =X9*1.19 -> 230900.46 | X9: 194034 | Y9: =-K9-L9-M9-N9+O9+P9+R9+T9+V9+X9 -> 685194.42 | Z9: =VLOOKUP(D9,'Archivo con Bonos Ingresados '!V:CB,59,0) -> 685194 | AA9: =Z9-Y9 -> -0.42016807 | AB9: =Y9*100/CU9 -> 4.3066323 | AC9: 23-01-2025 16:36:11 | AD9: 5954 | AE9: 19894192 | AF9: 1 | AG9: MONROE 6584 | AI9: 969160087 | AK9: LAS CONDES | AL9: 01/01/1900 | AM9: Djbrookssb@gmail.com | AO9: STATION WAGON | AP9: FAMILIA 1 | AQ9: CH14K311 | AR9: Gris Piedra de Luna | AS9: 9BWCH6CH8RP052805 | AT9: 9BWCH6CH8RP052805 | AU9: NUEVO Y SIN USO | AV9: Facturada | AW9: 19920 | AX9: 27-01-2025 0:00:00 | AZ9: Guía de Despacho: 1 - Factura Electrónica: 1864596 | BA9: 18103335 | BB9: 26-02-2025 0:00:00 | BD9: 0 | BE9: WEB CONCESIONARIO | BF9: 26-02-2025 0:00:00 | BG9: CI | BH9: Peso | BJ9: 0 | BK9: 19403361 | BL9: -3739496 | BM9: -537815 | BN9: 15126050 | BO9: 18103335 | BP9: -2977285 | BQ9: -19.68 % | BR9: 0 | BS9: 784164 | BT9: 784164 | BU9: 0 | BV9: 0 % | BW9: 0 | BX9: 0 | BY9: 0 | BZ9: 0 | CA9: 0 % | CB9: 0 | CC9: 0 | CD9: 0 | CE9: 0 | CF9: 0 % | CG9: 15663865 | CH9: 15910214 | CI9: 18887499 | CJ9: -2977285 | CK9: -18.71 % | CL9: -2977285 | CM9: -18.71 % | CN9: 0 | CO9: 0 | CP9: 18784164 | CQ9: 0 | CR9: 784164 | CS9: 0 | CT9: 18784164 | CU9: 15910214 | CV9: -2977285 | CW9: -18.71 % | CY9: 0 | DA9: 0 | DB9: 0 | DC9: 0
A10: ANDES MOTOR | B10: KAIYI | C10: KYE5 1.5T MT LUX | D10: AN-24-03-0009 | E10: 2025 | F10: LUYJA1G22RA003056 | G10: DIEGO ALEJANDRO JIMENEZ SILVA | H10: Marcos Ignacio Campos Zavala | I10: N | J10: Tanner | K10: =BA10 -> 11588907 | L10: 90000 | M10: =BT10 -> 669467 | P10: =CU10 -> 10987450 | Q10: 1200000 | R10: =Q10/1.19 -> 1008403.4 | S10: =T10*1.19 -> 0 | U10: 1000000 | V10: =U10/1.19 -> 840336.13 | W10: =X10*1.19 -> 0 | Y10: =-K10-L10-M10-N10+O10+P10+R10+T10+V10+X10 -> 487815.5 | Z10: =VLOOKUP(D10,'Archivo con Bonos Ingresados '!V:CB,59,0) -> 487815 | AA10: =Z10-Y10 -> -0.49579832 | AB10: =Y10*100/CU10 -> 4.4397517 | AC10: 11-01-2025 12:06:24 | AD10: 5915 | AE10: 16802706 | AF10: 0 | AG10: EJERCITO LIBERTADOR 2120 CASA 297 | AI10: 985658267 | AK10: PUENTE ALTO | AL10: 22/09/1987 | AM10: COMERCIALA07SPA@GMAIL.COM | AP10: KYE5 | AQ10: KYE5 1.5T MT LUX | AR10: GRIS | AS10: LUYJA1G22RA003056 | AT10: LUYJA1G22RA003056 | AU10: NUEVO Y SIN USO | AV10: Parcial Facturada | AW10: 19872 | AX10: 15-01-2025 0:00:00 | AZ10: Guía de Despacho Electrónica: 1 - Factura Electrónica: 168809 | BA10: 11588907 | BB10: 14-02-2025 0:00:00 | BD10: 0 | BE10: WEB CONCESIONARIO | BF10: 14-02-2025 0:00:00 | BG10: RETAIL | BH10: Peso | BJ10: 0 | BK10: 12596639 | BL10: -1848739 | BM10: -429916 | BN10: 10317983 | BO10: 11588907 | BP10: -1270924 | BQ10: -12.32 % | BR10: 0 | BS10: 669467 | BT10: 669467 | BU10: 0 | BV10: 0 % | BW10: 0 | BX10: 0 | BY10: 0 | BZ10: 0 | CA10: 0 % | CB10: 0 | CC10: 0 | CD10: 0 | CE10: 0 | CF10: 0 % | CG10: 10747900 | CH10: 10987450 | CI10: 12258374 | CJ10: -1270924 | CK10: -11.57 % | CL10: -1270924 | CM10: -11.57 % | CN10: 0 | CO10: 0 | CP10: 12947867 | CQ10: 0 | CR10: 669467 | CS10: 0 | CT10: 12947867 | CU10: 10987450 | CV10: -1270924 | CW10: -11.57 % | CY10: 0 | DA10: 0 | DB10: 0 | DC10: 0
A11: CASA MATRIZ NUEVOS | B11: VOLKSWAGEN | C11: T-Cross 1.0 TSI AT Highline - 85 kW/116 CV | D11: AN-24-12-0032 | E11: 2025 | F11: 9BWBH6BF0S4053238 | G11: DOBRA WALESKA LUSIC MORALES | H11: JUAN PABLO GONZALEZ ACUÑA | I11: N | J11: Directo | K11: =BA11 -> 17651815 | L11: 175000 | M11: =BT11 -> 973956 | P11: =CU11 -> 17898326 | Q11: =R11*1.19 -> 1449999.5 | R11: 1218487 | S11: =T11*1.19 -> 0 | V11: =U11/1.19 -> 0 | W11: =X11*1.19 -> 224900.48 | X11: 188992 | Y11: =-K11-L11-M11-N11+O11+P11+R11+T11+V11+X11 -> 505034 | Z11: =VLOOKUP(D11,'Archivo con Bonos Ingresados '!V:CB,59,0) -> 505034 | AA11: =Z11-Y11 -> 0 | AB11: =Y11*100/CU11 -> 2.8216829 | AC11: 09-01-2025 15:45:12 | AD11: 5905 | AE11: 16748913 | AF11: 3 | AG11: GENERAL JOFRE 202 DPTO 507 | AH11: 957148023 | AK11: SANTIAGO | AL11: 02/03/1988 | AM11: dobralusic@gmail.com | AO11: STATION WAGON | AP11: T CROSS | AQ11: BF34K311 | AR11: BLANCO PURO | AS11: 9BWBH6BF0S4053238 | AT11: 9BWBH6BF0S4053238 | AU11: NUEVO Y SIN USO | AV11: Facturada | AW11: 19859 | AX11: 14-01-2025 0:00:00 | AZ11: Guía de Despacho: 1 - Factura Electrónica: 1841780 | BA11: 17651815 | BB11: 14-01-2025 0:00:00 | BD11: 0 | BE11: SALON | BF11: 14-01-2025 0:00:00 | BG11: RETAIL | BH11: Peso | BJ11: 26 | BK11: 18899160 | BL11: -1218487 | BM11: -756303 | BN11: 16924370 | BO11: 17651815 | BP11: -727445 | BQ11: -4.3 % | BR11: 0 | BS11: 973956 | BT11: 973956 | BU11: 0 | BV11: 0 % | BW11: 0 | BX11: 0 | BY11: 0 | BZ11: 0 | CA11: 0 % | CB11: 0 | CC11: 0 | CD11: 0 | CE11: 0 | CF11: 0 % | CG11: 17680673 | CH11: 17898326 | CI11: 18625771 | CJ11: -727445 | CK11: -4.06 % | CL11: -727445 | CM11: -4.06 % | CN11: 0 | CO11: 0 | CP11: 21113956 | CQ11: 0 | CR11: 973956 | CS11: 0 | CT11: 21113956 | CU11: 17898326 | CV11: -727445 | CW11: -4.06 % | CY11: 0 | DA11: 0 | DB11: 0 | DC11: 0
A12: ANDES MOTOR | B12: MAXUS | C12: D60 4X2 LUX AT 7P | D12: AN-24-09-0044 | E12: 2025 | F12: LSKG4BC13SD040453 | G12: ENNIO MAURICIO GRBAC NUÑEZ | H12: SERGIO POBLETE CAMPOS | I12: N | J12: BK | K12: =BA12 -> 17773781 | L12: 235000 | M12: =BT12 -> 1000000 | P12: =CU12 -> 17798319 | Q12: =R12*1.19 -> 1000000 | R12: 840336.13 | S12: =T12*1.19 -> 0 | U12: =V12*1.19 -> 800000.11 | V12: =126050+546219 -> 672269 | W12: =X12*1.19 -> 0 | Y12: =-K12-L12-M12-N12+O12+P12+R12+T12+V12+X12 -> 302143.13 | Z12: =VLOOKUP(D12,'Archivo con Bonos Ingresados '!V:CB,59,0) -> 302143 | AA12: =Z12-Y12 -> -0.13445378 | AB12: =Y12*100/CU12 -> 1.6975937 | AC12: 21-01-2025 11:03:39 | AD12: 5943 | AE12: 7131041 | AF12: 8 | AG12: TONGOY 1157 | AH12: 67275763 | AI12: +569 67275763 | AK12: LAS CONDES | AL12: 20/12/1964 | AM12: enniogrbac@grbac.cl | AP12: D60 | AQ12: D60 4X2 LUX AT 7P | AR12: PLATA | AS12: LSKG4BC13SD040453 | AT12: LSKG4BC13SD040453 | AU12: NUEVO Y SIN USO | AV12: Parcial Facturada | AW12: 19907 | AX12: 23-01-2025 0:00:00 | AZ12: Guía de Despacho: 1 - Factura Electrónica: 205322 | BA12: 17773781 | BB12: 22-02-2025 0:00:00 | BD12: 0 | BE12: SALON | BF12: 22-02-2025 0:00:00 | BG12: CC | BH12: Peso | BI12: KBBL13 | BJ12: 115 | BK12: 19319328 | BL12: -1680672 | BM12: -840336 | BN12: 16798319 | BO12: 17773781 | BP12: -975462 | BQ12: -5.81 % | BR12: 0 | BS12: 1000000 | BT12: 1000000 | BU12: 0 | BV12: 0 % | BW12: 0 | BX12: 0 | BY12: 0 | BZ12: 0 | CA12: 0 % | CB12: 0 | CC12: 0 | CD12: 0 | CE12: 0 | CF12: 0 % | CG12: 17638656 | CH12: 17798319 | CI12: 18773781 | CJ12: -975462 | CK12: -5.48 % | CL12: -975462 | CM12: -5.48 % | CN12: 0 | CO12: 6300000 | CP12: 14690000 | CQ12: 0 | CR12: 1000000 | CS12: 0 | CT12: 20990000 | CU12: 17798319 | CV12: -975462 | CW12: -5.48 % | CY12: 0 | DA12: 0 | DB12: 0 | DC12: 0
A13: CASA MATRIZ NUEVOS | B13: VOLKSWAGEN | C13: NUEVO TIGUAN TSI AT COMFORTLINE 150HP | D13: AN-25-01-0008 | E13: 2025 | F13: 3VVHP65N7RM219894 | G13: ENRIQUE EDUARDO LATOJA OVIEDO | H13: JUAN PABLO GONZALEZ ACUÑA | I13: N | J13: Directo | K13: =BA13 -> 23804093 | L13: 175000 | M13: =BT13 -> 1581111 | P13: =CU13 -> 24160355 | Q13: =R13*1.19 -> 2900000.2 | R13: 2436975 | S13: =T13*1.19 -> 0 | V13: =U13/1.19 -> 0 | W13: =X13*1.19 -> 306899.81 | X13: 257899 | Y13: =-K13-L13-M13-N13+O13+P13+R13+T13+V13+X13 -> 1295025 | Z13: =VLOOKUP(D13,'Archivo con Bonos Ingresados '!V:CB,59,0) -> 1295025 | AA13: =Z13-Y13 -> 0 | AB13: =Y13*100/CU13 -> 5.3601241 | AC13: 13-01-2025 10:23:49 | AD13: 5917 | AE13: 7918183 | AF13: 8 | AG13: JANUARIO ESPINOZA 7205-A | AH13: 998213308 | AK13: LA REINA | AL13: 11/06/1959 | AM13: elatoja@entel.cl | AO13: STATION WAGON 01 | AP13: FAMILIA 1 | AQ13: BJ23N611 | AR13: PLATA PIRITA | AS13: 3VVHP65N7RM219894 | AU13: NUEVO Y SIN USO | AV13: Facturada | AW13: 19861 | AX13: 14-01-2025 0:00:00 | AZ13: Guía de Despacho: 1 - Factura Electrónica: 1864398 | BA13: 23804093 | BB13: 14-01-2025 0:00:00 | BD13: 0 | BE13: SALON | BF13: 14-01-2025 0:00:00 | BG13: RETAIL | BH13: Peso | BJ13: 0 | BK13: 25789916 | BL13: -2436975 | BM13: -773697 | BN13: 22579244 | BO13: 23804093 | BP13: -1224849 | BQ13: -5.42 % | BR13: 0 | BS13: 1581111 | BT13: 1581111 | BU13: 0 | BV13: 0 % | BW13: 0 | BX13: 0 | BY13: 0 | BZ13: 0 | CA13: 0 % | CB13: 0 | CC13: 0 | CD13: 0 | CE13: 0 | CF13: 0 % | CG13: 23352941 | CH13: 24160355 | CI13: 25385204 | CJ13: -1224849 | CK13: -5.07 % | CL13: -1224849 | CM13: -5.07 % | CN13: 0 | CO13: 0 | CP13: 28450411 | CQ13: 0 | CR13: 1581111 | CS13: 0 | CT13: 28450411 | CU13: 24160355 | CV13: -1224849 | CW13: -5.07 % | CY13: 0 | DA13: 0 | DB13: 0 | DC13: 0
A14: CASA MATRIZ NUEVOS | B14: VOLKSWAGEN | C14: T-Cross 1.0 TSI MT Comfortline - 74 kW/101 CV | D14: AN-24-08-0072 | E14: 2025 | F14: 9BWBH6BF7S4004618 | G14: FRANCESCA MARIA DE LOURDES CALVANESE HUIDOBRO | H14: JUAN PABLO GONZALEZ ACUÑA | I14: N | J14: Directo | K14: =BA14 -> 15795707 | L14: 175000 | M14: =BT14 -> 860724 | P14: =CU14 -> 15763497 | Q14: =R14*1.19 -> 1850000.2 | R14: 1554622 | S14: =T14*1.19 -> 0 | V14: =U14/1.19 -> 0 | W14: =X14*1.19 -> 201900.16 | X14: 169664 | Y14: =-K14-L14-M14-N14+O14+P14+R14+T14+V14+X14 -> 656352 | Z14: =VLOOKUP(D14,'Archivo con Bonos Ingresados '!V:CB,59,0) -> 656352 | AA14: =Z14-Y14 -> 0 | AB14: =Y14*100/CU14 -> 4.1637462 | AC14: 27-01-2025 18:15:38 | AD14: 5960 | AE14: 8545815 | AF14: 9 | AG14: HERNANDO DE MAGALLANES 1922 | AH14: 996897113 | AK14: LAS CONDES | AL14: 06/06/1959 | AM14: francescacalvanese@gmail.com | AO14: STATION WAGON | AP14: T CROSS | AQ14: BF33D411 | AR14: AZUL NORUEGA | AS14: 9BWBH6BF7S4004618 | AT14: 9BWBH6BF7S4004618 | AU14: NUEVO Y SIN USO | AV14: Facturada | AW14: 19926 | AX14: 28-01-2025 0:00:00 | AZ14: Guía de Despacho: 1 - Factura Electrónica: 1838082 | BA14: 15795707 | BB14: 28-01-2025 0:00:00 | BD14: 0 | BE14: SALON | BF14: 28-01-2025 0:00:00 | BG14: RETAIL | BH14: Peso | BJ14: 123 | BK14: 16966386 | BL14: -1554622 | BM14: -508992 | BN14: 14902773 | BO14: 15795707 | BP14: -892934 | BQ14: -5.99 % | BR14: 0 | BS14: 860724 | BT14: 860724 | BU14: 0 | BV14: 0 % | BW14: 0 | BX14: 0 | BY14: 0 | BZ14: 0 | CA14: 0 % | CB14: 0 | CC14: 0 | CD14: 0 | CE14: 0 | CF14: 0 % | CG14: 15411764 | CH14: 15763497 | CI14: 16656431 | CJ14: -892934 | CK14: -5.66 % | CL14: -892934 | CM14: -5.66 % | CN14: 0 | CO14: 0 | CP14: 18595024 | CQ14: 0 | CR14: 860724 | CS14: 0 | CT14: 18595024 | CU14: 15763497 | CV14: -892934 | CW14: -5.66 % | CY14: 0 | DA14: 0 | DB14: 0 | DC14: 0
A15: CASA MATRIZ NUEVOS | B15: VOLKSWAGEN | C15: NUEVO ATLAS 2.0 TSI AT LIMITED 4MOTION | D15: AN-24-12-0042 | E15: 2025 | F15: WVGZZZCA5RC601451 | G15: FRANCISCA ANDREA RIQUELME FENNER | H15: ROBERTO LOBOS GUTIERREZ | I15: N | J15: Directo | K15: =BA15 -> 43474588 | L15: 235000 | M15: =BT15 -> 2749605 | P15: =CU15 -> 44926495 | Q15: =R15*1.19 -> 2999999.5 | R15: 2521008 | S15: =T15*1.19 -> 0 | V15: =U15/1.19 -> 0 | W15: =X15*1.19 -> 559899.76 | X15: 470504 | Y15: =-K15-L15-M15-N15+O15+P15+R15+T15+V15+X15 -> 1458814 | Z15: =VLOOKUP(D15,'Archivo con Bonos Ingresados '!V:CB,59,0) -> 1458814 | AA15: =Z15-Y15 -> 0 | AB15: =Y15*100/CU15 -> 3.2471129 | AC15: 30-01-2025 17:47:56 | AD15: 5969 | AE15: 18142681 | AF15: 0 | AG15: ALONSO DE CAMARGO 5870 DEPTO 403 | AI15: 99179180 | AK15: LAS CONDES | AL15: 01/01/1900 | AM15: NICOLAS.C¿MACCLUR@INPEN.CL | AO15: STATION WAGON | AQ15: CA35PR11 | AR15: GRIS PLATINO | AS15: WVGZZZCA5RC601451 | AT15: WVGZZZCA5RC601451 | AU15: NUEVO Y SIN USO | AV15: Parcial Facturada | AW15: 19949 | AX15: 31-01-2025 0:00:00 | AZ15: Factura Electrónica: 1841778 | BA15: 43474588 | BB15: 31-01-2025 0:00:00 | BD15: 0 | BE15: SALON | BF15: 31-01-2025 0:00:00 | BG15: CC | BH15: Peso | BJ15: 31 | BK15: 47050420 | BL15: -2521008 | BM15: -2521008 | BN15: 42008403 | BO15: 43474588 | BP15: -1466185 | BQ15: -3.49 % | BR15: 0 | BS15: 2749605 | BT15: 2749605 | BU15: 0 | BV15: 0 % | BW15: 110500 | BX15: 168487 | BY15: 0 | BZ15: 0 | CA15: 0 % | CB15: 0 | CC15: 0 | CD15: 0 | CE15: 0 | CF15: 0 % | CG15: 44529412 | CH15: 44926495 | CI15: 46224193 | CJ15: -1297698 | CK15: -2.89 % | CL15: -1297698 | CM15: -2.89 % | CN15: 0 | CO15: 0 | CP15: 52940105 | CQ15: 0 | CR15: 2749605 | CS15: 168487 | CT15: 52940104 | CU15: 44926495 | CV15: -1297698 | CW15: -2.89 % | CY15: 0 | DA15: 0 | DB15: 0 | DC15: 0
A16: CASA MATRIZ NUEVOS | B16: VOLKSWAGEN | C16: Taos TSI AT Highline 110KW/150CV | D16: AN-25-01-0011 | E16: 2025 | F16: 8AWBJ6B25RA840847 | G16: FRANCISCO JAVIER URETA ESTRADA | H16: ROBERTO LOBOS GUTIERREZ | I16: N | J16: Forum | K16: =BA16 -> 22640647 | L16: 175000 | M16: =BT16 -> 1196428 | P16: =CU16 -> 21608193 | Q16: =R16*1.19 -> 2850000 | R16: 2394958 | S16: =T16*1.19 -> 949999.61 | T16: 798319 | U16: 150000 | V16: =U16/1.19 -> 126050.42 | W16: =X16*1.19 -> 291899.86 | X16: 245294 | Y16: =-K16-L16-M16-N16+O16+P16+R16+T16+V16+X16 -> 1160739.4 | Z16: =VLOOKUP(D16,'Archivo con Bonos Ingresados '!V:CB,59,0) -> 1160739 | AA16: =Z16-Y16 -> -0.42016807 | AB16: =Y16*100/CU16 -> 5.3717561 | AC16: 10-01-2025 15:46:14 | AD16: 5913 | AE16: 17408406 | AF16: 8 | AG16: LAS VERBENAS 8485 DEPTO 713 B | AI16: 984295679 | AK16: LAS CONDES | AL16: 28/05/1990 | AM16: F.URETA.ES@GMAIL.COM | AO16: STATION WAGON 01 | AP16: FAMILIA 1 | AQ16: CQ17LY11 | AR16: BLANCO PURO | AS16: 8AWBJ6B25RA840847 | AT16: 8AWBJ6B25RA840847 | AU16: NUEVO Y SIN USO | AV16: Parcial Facturada | AW16: 19908 | AX16: 24-01-2025 0:00:00 | AZ16: Guía de Despacho: 1 - Factura Electrónica: 1864513 | BA16: 22640647 | BB16: 23-02-2025 0:00:00 | BD16: 0 | BE16: SALON | BF16: 23-02-2025 0:00:00 | BG16: CC | BH16: Peso | BI16: SZRZ28 | BJ16: -6 | BK16: 24529412 | BL16: -3571429 | BM16: -840336 | BN16: 20117647 | BO16: 22640647 | BP16: -2523000 | BQ16: -12.54 % | BR16: 0 | BS16: 1196428 | BT16: 1196428 | BU16: 0 | BV16: 0 % | BW16: 73920 | BX16: 294118 | BY16: 0 | BZ16: 0 | CA16: 0 % | CB16: 0 | CC16: 0 | CD16: 0 | CE16: 0 | CF16: 0 % | CG16: 20957983 | CH16: 21608193 | CI16: 23837075 | CJ16: -2228882 | CK16: -10.31 % | CL16: -2228882 | CM16: -10.31 % | CN16: 0 | CO16: 21557299 | CP16: 17178644 | CQ16: -13249515 | CR16: 1196428 | CS16: 294118 | CT16: 25486428 | CU16: 21608193 | CV16: -2228882 | CW16: -10.31 % | CY16: 0 | DA16: 0 | DB16: 0 | DC16: 0
A17: ANDES MOTOR | B17: JETOUR | C17: X70 1.5T MT STD | D17: AN-24-07-0010 | E17: 2024 | F17: LVUDB11B4PF009299 | G17: GERARDO ACHA ZUÑIGA | H17: Matias Larrain Larrain | I17: N | J17: BK | K17: =BA17 -> 12362017 | L17: 175000 | M17: =BT17 -> 622830 | P17: =CU17 -> 10579832 | Q17: 2000000 | R17: =Q17/1.19 -> 1680672.3 | S17: =T17*1.19 -> 0 | U17: 600000 | V17: =U17/1.19 -> 504201.68 | W17: =X17*1.19 -> 249999.96 | X17: 210084 | Y17: =-K17-L17-M17-N17+O17+P17+R17+T17+V17+X17 -> -185057.05 | Z17: =VLOOKUP(D17,'Archivo con Bonos Ingresados '!V:CB,59,0) -> -185057 | AA17: =Z17-Y17 -> 0.050420168 | AB17: =Y17*100/CU17 -> -1.7491492 | AC17: 15-01-2025 10:53:16 | AD17: 5929 | AE17: 7697564 | AF17: 7 | AG17: LOS JORNALEROS 1718 | AI17: 982342462 | AK17: ÑUÑOA | AL17: 06/03/1961 | AM17: GERARDOACHA@GMAIL.COM | AP17: X70 | AQ17: X70 1.5T MT STD | AR17: BLANCO | AS17: LVUDB11B4PF009299 | AT17: LVUDB11B4PF009299 | AU17: NUEVO Y SIN USO | AV17: Facturada | AW17: 19887 | AX17: 20-01-2025 0:00:00 | AZ17: Guía de Despacho: 1 - Factura Electrónica: 176302 | BA17: 12362017 | BB17: 19-02-2025 0:00:00 | BD17: 0 | BE17: SITIO WEB | BF17: 19-02-2025 0:00:00 | BG17: CI | BH17: Peso | BJ17: 202 | BK17: 13436975 | BL17: -2394958 | BM17: -462185 | BN17: 10579832 | BO17: 12362017 | BP17: -1782185 | BQ17: -16.85 % | BR17: -622830 | BS17: 0 | BT17: 622830 | BU17: -622830 | BV17: -100 % | BW17: 0 | BX17: 0 | BY17: 0 | BZ17: 0 | CA17: 0 % | CB17: 0 | CC17: 0 | CD17: 0 | CE17: 0 | CF17: 0 % | CG17: 11042017 | CH17: 10579832 | CI17: 12984847 | CJ17: -2405015 | CK17: -22.73 % | CL17: -2405015 | CM17: -22.73 % | CN17: 0 | CO17: 0 | CP17: 12672230 | CQ17: -82230 | CR17: 0 | CS17: 0 | CT17: 12590000 | CU17: 10579832 | CV17: -2405015 | CW17: -22.73 % | CY17: 0 | DA17: 0 | DB17: 0 | DC17: 0
A18: ANDES MOTOR | B18: MAXUS | C18: C35 L CARROCERÍA PLANA | D18: AN-24-12-0004 | E18: 2023 | F18: LSH14B4C6PD900042 | G18: GLOBAL GROUP INGENIERIA SPA | H18: Marcos Ignacio Campos Zavala | I18: N | J18: Directo | K18: =BA18 -> 15190500 | L18: 235000 | M18: =BT18 -> 573980 | P18: =CU18 -> 17120198 | Q18: =R18*1.19 -> 0 | S18: =T18*1.19 -> 0 | V18: =U18/1.19 -> 0 | W18: =X18*1.19 -> 0 | Y18: =-K18-L18-M18-N18+O18+P18+R18+T18+V18+X18 -> 1120718 | Z18: =VLOOKUP(D18,'Archivo con Bonos Ingresados '!V:CB,59,0) -> 1120718 | AA18: =Z18-Y18 -> 0 | AB18: =Y18*100/CU18 -> 6.5461743 | AC18: 07-01-2025 13:16:04 | AD18: 5897 | AE18: 76235534 | AF18: 5 | AG18: BAQUEDANO 239 OF 414 | AH18: 6-919.3266 | AI18: 926281759 | AK18: ANTOFAGASTA | AM18: GERENCIA@GGINGENIERIA.CL | AP18: C35 L | AQ18: C35 L CARROCERÍA PLANA | AR18: BLANCO | AS18: LSH14B4C6PD900042 | AT18: LSH14B4C6PD900042 | AU18: NUEVO Y SIN USO | AV18: Parcial Facturada | AW18: 19844 | AX18: 10-01-2025 0:00:00 | AZ18: Guía de Despacho: 1 - Factura Electrónica: 284604 | BA18: 15190500 | BB18: 10-01-2025 0:00:00 | BD18: 0 | BE18: WEB CONCESIONARIO | BF18: 10-01-2025 0:00:00 | BG18: RETAIL | BH18: Peso | BJ18: 15 | BK18: 20990000 | BL18: 0 | BM18: -4443782 | BN18: 16546218 | BO18: 15190500 | BP18: 1355718 | BQ18: 8.19 % | BR18: 0 | BS18: 573980 | BT18: 573980 | BU18: 0 | BV18: 0 % | BW18: 0 | BX18: 0 | BY18: 0 | BZ18: 0 | CA18: 0 % | CB18: 0 | CC18: 0 | CD18: 0 | CE18: 0 | CF18: 0 % | CG18: 20990000 | CH18: 17120198 | CI18: 15764480 | CJ18: 1355718 | CK18: 7.92 % | CL18: 1355718 | CM18: 7.92 % | CN18: 0 | CO18: 0 | CP18: 20263980 | CQ18: 0 | CR18: 573980 | CS18: 0 | CT18: 20263979 | CU18: 17120198 | CV18: 1355718 | CW18: 7.92 % | CY18: 0 | DA18: 0 | DB18: 0 | DC18: 0
A19: ANDES MOTOR | B19: JETOUR | C19: X70 1.5T MT LUX | D19: AN-23-08-0059 | E19: 2024 | F19: LVUDB11B8PF018233 | G19: HERWIN ROLANDO BAHAMONDES HENRIQUEZ | H19: Manuel Rodrigo Hurtado Melo | I19: N | J19: BK | K19: =BA19 -> 12748571 | L19: 175000 | M19: =BT19 -> 699835 | P19: =CU19 -> 11195633 | Q19: 2000000 | R19: =Q19/1.19 -> 1680672.3 | S19: =T19*1.19 -> 0 | U19: 1000000 | V19: =U19/1.19 -> 840336.13 | W19: 250000 | X19: =W19/1.19 -> 210084.03 | Y19: =-K19-L19-M19-N19+O19+P19+R19+T19+V19+X19 -> 303319.44 | Z19: =VLOOKUP(D19,'Archivo con Bonos Ingresados '!V:CB,59,0) -> 303319 | AA19: =Z19-Y19 -> -0.43697479 | AB19: =Y19*100/CU19 -> 2.7092656 | AC19: 02-01-2025 17:00:38 | AD19: 5885 | AE19: 13161261 | AF19: 3 | AG19: PASAJE LA GROSSAL 02340 | AI19: 993401676 | AK19: SAN BERNARDO | AL19: 07/06/1977 | AM19: HEREBAHAM@HOTMAIL.COM | AP19: X70 | AQ19: X70 1.5T MT LUX | AR19: ROJO | AS19: LVUDB11B8PF018233 | AT19: LVUDB11B8PF018233 | AU19: NUEVO Y SIN USO | AV19: Parcial Facturada | AW19: 19886 | AX19: 17-01-2025 0:00:00 | AZ19: Guía de Despacho: 1 - Factura Electrónica: 145309 | BA19: 12748571 | BB19: 16-02-2025 0:00:00 | BD19: 0 | BE19: SITIO WEB | BF19: 16-02-2025 0:00:00 | BG19: CC | BH19: Peso | BI19: HLRT60 | BJ19: 506 | BK19: 14697479 | BL19: -2521008 | BM19: -1680672 | BN19: 10495798 | BO19: 12748571 | BP19: -2252773 | BQ19: -21.46 % | BR19: 0 | BS19: 699835 | BT19: 699835 | BU19: 0 | BV19: 0 % | BW19: 0 | BX19: 0 | BY19: 0 | BZ19: 0 | CA19: 0 % | CB19: 0 | CC19: 0 | CD19: 0 | CE19: 0 | CF19: 0 % | CG19: 12176471 | CH19: 11195633 | CI19: 13448406 | CJ19: -2252773 | CK19: -20.12 % | CL19: -2252773 | CM19: -20.12 % | CN19: 0 | CO19: 3500000 | CP19: 9738652 | CQ19: -48817 | CR19: 699835 | CS19: 0 | CT19: 13189835 | CU19: 11195633 | CV19: -2252773 | CW19: -20.12 % | CY19: 0 | DA19: 0 | DB19: 0 | DC19: 0
A20: CASA MATRIZ NUEVOS | B20: VOLKSWAGEN | C20: Saveiro 1.6 MT Cabina Doble Lite | D20: AN-24-10-0057 | E20: 2025 | F20: 9BWJL45U7SP006599 | G20: INTELCLIMA LIMITADA | H20: JUAN PABLO GONZALEZ ACUÑA | I20: N | J20: Lucy | K20: =BA20 -> 12096160 | L20: 90000 | M20: =BT20 -> 328487 | P20: =CU20 -> 11076386 | Q20: =R20*1.19 -> 1606500 | R20: 1350000 | S20: =T20*1.19 -> 0 | U20: 150000 | V20: =U20/1.19 -> 126050.42 | W20: 500000 | X20: =W20/1.19 -> 420168.07 | Y20: =-K20-L20-M20-N20+O20+P20+R20+T20+V20+X20 -> 457957.49 | Z20: =VLOOKUP(D20,'Archivo con Bonos Ingresados '!V:CB,59,0) -> 37789 | AA20: =Z20-Y20 -> -420168.49 | AB20: =Y20*100/CU20 -> 4.1345389 | AC20: 21-01-2025 15:24:14 | AD20: 5946 | AE20: 76431332 | AF20: 1 | AG20: FEDERICO ERRAZURIZ 1250 DPTO 31 EDIFICIO 6 | AH20: 955290099 | AK20: PUDAHUEL | AM20: s.ramireztorres@hotmail.com | AO20: CAMIONETA | AP20: SAVEIRO | AQ20: 5UKWT412 | AR20: BLANCO CANDY | AS20: 9BWJL45U7SP006599 | AT20: 9BWJL45U7SP006599 | AU20: NUEVO Y SIN USO | AV20: Facturada | AW20: 19943 | AX20: 30-01-2025 0:00:00 | AZ20: Guía de Despacho: 1 - Factura Electrónica: 1839953 - Nota de Crédito Electrónica: 3062524 | BA20: 12096160 | BB20: 01-03-2025 0:00:00 | BD20: 0 | BE20: SALON | BF20: 01-03-2025 0:00:00 | BG20: FLOTA | BH20: Peso | BI20: PGSY19 | BJ20: 98 | BK20: 13840000 | BL20: -2150000 | BM20: -942101 | BN20: 10747899 | BO20: 10746160 | BP20: 1739 | BQ20: 0.02 % | BR20: 0 | BS20: 328487 | BT20: 328487 | BU20: 0 | BV20: 0 % | BW20: 0 | BX20: 0 | BY20: 0 | BZ20: 0 | CA20: 0 % | CB20: 0 | CC20: 0 | CD20: 0 | CE20: 0 | CF20: 0 % | CG20: 11690000 | CH20: 11076386 | CI20: 11074647 | CJ20: 1739 | CK20: 0.02 % | CL20: 1739 | CM20: 0.02 % | CN20: 0 | CO20: 9000000 | CP20: 10709913 | CQ20: -6591426 | CR20: 328487 | CS20: 0 | CT20: 13118487 | CU20: 11076386 | CV20: 1739 | CW20: 0.02 % | CY20: 0 | DA20: 0 | DB20: 1606500 | DC20: 0
A21: CASA MATRIZ NUEVOS | B21: VOLKSWAGEN | C21: Saveiro 1.6 MT Cabina Simple Lite | D21: AN-25-01-0028 | E21: 2025 | F21: 9BWKL45U3SP047879 | G21: INTELCLIMA LIMITADA | H21: JUAN PABLO GONZALEZ ACUÑA | I21: G | J21: BK | K21: =BA21 -> 11287520 | L21: 90000 | M21: =BT21 -> 295713 | P21: =CU21 -> 9951175 | Q21: =R21*1.19 -> 1487500 | R21: 1250000 | S21: =T21*1.19 -> 0 | V21: =U21/1.19 -> 0 | W21: =X21*1.19 -> 0 | Y21: =-K21-L21-M21-N21+O21+P21+R21+T21+V21+X21 -> -472058 | Z21: =VLOOKUP(D21,'Archivo con Bonos Ingresados '!V:CB,59,0) -> -472058 | AA21: =Z21-Y21 -> 0 | AB21: =Y21*100/CU21 -> -4.7437413 | AC21: 21-01-2025 15:32:21 | AD21: 5947 | AE21: 76431332 | AF21: 1 | AG21: FEDERICO ERRAZURIZ 1250 DPTO 31 EDIFICIO 6 | AH21: 955290099 | AK21: PUDAHUEL | AM21: s.ramireztorres@hotmail.com | AO21: CAMIONETA | AP21: SAVEIRO | AQ21: 5URTT412 | AR21: BLANCO CANDY | AS21: 9BWKL45U3SP047879 | AT21: 9BWKL45U3SP047879 | AU21: NUEVO Y SIN USO | AV21: Facturada | AW21: 19944 | AX21: 30-01-2025 0:00:00 | AZ21: Guía de Despacho: 1 - Factura Electrónica: 1864567 - Nota de Crédito Electrónica: 3063712 | BA21: 11287520 | BB21: 01-03-2025 0:00:00 | BD21: 0 | BE21: SALON | BF21: 01-03-2025 0:00:00 | BG21: FLOTA | BH21: Peso | BJ21: 8 | BK21: 12640000 | BL21: -2050000 | BM21: -934538 | BN21: 9655462 | BO21: 11287520 | BP21: -1632058 | BQ21: -16.9 % | BR21: 0 | BS21: 295713 | BT21: 295713 | BU21: 0 | BV21: 0 % | BW21: 0 | BX21: 0 | BY21: 0 | BZ21: 0 | CA21: 0 % | CB21: 0 | CC21: 0 | CD21: 0 | CE21: 0 | CF21: 0 % | CG21: 10590000 | CH21: 9951175 | CI21: 11583233 | CJ21: -1632058 | CK21: -16.4 % | CL21: -1632058 | CM21: -16.4 % | CN21: 0 | CO21: 0 | CP21: 11785713 | CQ21: 0 | CR21: 295713 | CS21: 0 | CT21: 11785713 | CU21: 9951175 | CV21: -1632058 | CW21: -16.4 % | CY21: 0 | DA21: 0 | DB21: 0 | DC21: 0
A22: CASA MATRIZ NUEVOS | B22: VOLKSWAGEN | C22: Saveiro 1.6 MT Cabina Simple Lite | D22: AN-25-01-0026 | E22: 2025 | F22: 9BWKL45U1SP048416 | G22: INTELCLIMA LIMITADA | H22: JUAN PABLO GONZALEZ ACUÑA | I22: G | J22: Forum | K22: =BA22 -> 11287520 | L22: 90000 | M22: =BT22 -> 295713 | P22: =CU22 -> 9951175 | Q22: =R22*1.19 -> 1487500 | R22: 1250000 | S22: =T22*1.19 -> 651999.81 | T22: 547899 | U22: 150000 | V22: =U22/1.19 -> 126050.42 | W22: =X22*1.19 -> 0 | Y22: =-K22-L22-M22-N22+O22+P22+R22+T22+V22+X22 -> 201891.42 | Z22: =VLOOKUP(D22,'Archivo con Bonos Ingresados '!V:CB,59,0) -> 201891 | AA22: =Z22-Y22 -> -0.42016807 | AB22: =Y22*100/CU22 -> 2.0288199 | AC22: 21-01-2025 15:51:21 | AD22: 5948 | AE22: 76431332 | AF22: 1 | AG22: FEDERICO ERRAZURIZ 1250 DPTO 31 EDIFICIO 6 | AH22: 955290099 | AK22: PUDAHUEL | AM22: s.ramireztorres@hotmail.com | AO22: CAMIONETA | AP22: SAVEIRO | AQ22: 5URTT412 | AR22: BLANCO CANDY | AS22: 9BWKL45U1SP048416 | AT22: 9BWKL45U1SP048416 | AU22: NUEVO Y SIN USO | AV22: Facturada | AW22: 19945 | AX22: 30-01-2025 0:00:00 | AZ22: Guía de Despacho: 1 - Factura Electrónica: 1864566 - Nota de Crédito Electrónica: 3063693 | BA22: 11287520 | BB22: 01-03-2025 0:00:00 | BD22: 0 | BE22: SALON | BF22: 01-03-2025 0:00:00 | BG22: FLOTA | BH22: Peso | BJ22: 8 | BK22: 13840000 | BL22: -2050000 | BM22: -934538 | BN22: 9655462 | BO22: 9937520 | BP22: -282058 | BQ22: -2.92 % | BR22: 0 | BS22: 295713 | BT22: 295713 | BU22: 0 | BV22: 0 % | BW22: 0 | BX22: 0 | BY22: 0 | BZ22: 0 | CA22: 0 % | CB22: 0 | CC22: 0 | CD22: 0 | CE22: 0 | CF22: 0 % | CG22: 11790000 | CH22: 9951175 | CI22: 10233233 | CJ22: -282058 | CK22: -2.83 % | CL22: -282058 | CM22: -2.83 % | CN22: 0 | CO22: 0 | CP22: 11785713 | CQ22: 0 | CR22: 295713 | CS22: 0 | CT22: 11785713 | CU22: 9951175 | CV22: -282058 | CW22: -2.83 % | CY22: 0 | DA22: 0 | DB22: 1606500 | DC22: 0
A23: CASA MATRIZ NUEVOS | B23: VOLKSWAGEN | C23: Taos TSI AT Highline 110KW/150CV | D23: AN-25-01-0003 | E23: 2025 | F23: 8AWBJ6B28RA828840 | G23: JENNY PAOLA LLEWELLYN ROVEGNO | H23: JUAN PABLO GONZALEZ ACUÑA | I23: N | J23: Forum | K23: =BA23 -> 22640647 | L23: 175000 | M23: =BT23 -> 1186750 | P23: =CU23 -> 21163557 | Q23: =R23*1.19 -> 2850000 | R23: 2394958 | S23: =T23*1.19 -> 949999.61 | T23: 798319 | U23: 150000 | V23: =U23/1.19 -> 126050.42 | W23: =X23*1.19 -> 291899.86 | X23: 245294 | Y23: =-K23-L23-M23-N23+O23+P23+R23+T23+V23+X23 -> 725781.42 | Z23: =VLOOKUP(D23,'Archivo con Bonos Ingresados '!V:CB,59,0) -> 725781 | AA23: =Z23-Y23 -> -0.42016807 | AB23: =Y23*100/CU23 -> 3.4293924 | AC23: 06-01-2025 11:01:03 | AD23: 5891 | AE23: 10265209 | AF23: 6 | AG23: DOCTOR ROBERTO DEL RIO 1771 DPTO 401 | AH23: 997991954 | AK23: PROVIDENCIA | AL23: 07/05/1972 | AM23: jenny.llewelyn@gmail.com | AO23: STATION WAGON 01 | AP23: FAMILIA 1 | AQ23: CQ17LY11 | AR23: GRIS INDIO METALIZADO | AS23: 8AWBJ6B28RA828840 | AU23: NUEVO Y SIN USO | AV23: Facturada | AW23: 19823 | AX23: 06-01-2025 0:00:00 | AZ23: Guía de Despacho: 1 - Factura Electrónica: 1842389 | BA23: 22640647 | BB23: 06-01-2025 0:00:00 | BD23: 0 | BE23: SALON | BF23: 06-01-2025 0:00:00 | BG23: RETAIL | BH23: Peso | BI23: JVGP11 | BJ23: 0 | BK23: 24529412 | BL23: -3571429 | BM23: -981176 | BN23: 19976807 | BO23: 22640647 | BP23: -2663840 | BQ23: -13.33 % | BR23: 0 | BS23: 1186750 | BT23: 1186750 | BU23: 0 | BV23: 0 % | BW23: 0 | BX23: 0 | BY23: 0 | BZ23: 0 | CA23: 0 % | CB23: 0 | CC23: 0 | CD23: 0 | CE23: 0 | CF23: 0 % | CG23: 20957983 | CH23: 21163557 | CI23: 23827397 | CJ23: -2663840 | CK23: -12.59 % | CL23: -2663840 | CM23: -12.59 % | CN23: 0 | CO23: 11000000 | CP23: 13959150 | CQ23: 0 | CR23: 1186750 | CS23: 0 | CT23: 24959150 | CU23: 21163557 | CV23: -2663840 | CW23: -12.59 % | CY23: 0 | DA23: 0 | DB23: 0 | DC23: 0
A24: CASA MATRIZ NUEVOS | B24: VOLKSWAGEN | C24: Nivus 1.0 TSI AT Comfortline 85KW/116CV 5 p | D24: AN-24-10-0040 | E24: 2025 | F24: 9BWCH6CH5RP048825 | G24: JONNY KULKA FRAENKEL | H24: ROBERTO LOBOS GUTIERREZ | I24: N | J24: Directo | K24: =BA24 -> 16396017 | L24: 145000 | M24: =BT24 -> 844500 | P24: =CU24 -> 15672651 | Q24: =R24*1.19 -> 2199999.4 | R24: 1848739 | S24: =T24*1.19 -> 0 | V24: =U24/1.19 -> 0 | W24: =X24*1.19 -> 208899.74 | X24: 175546 | Y24: =-K24-L24-M24-N24+O24+P24+R24+T24+V24+X24 -> 311419 | Z24: =VLOOKUP(D24,'Archivo con Bonos Ingresados '!V:CB,59,0) -> 311419 | AA24: =Z24-Y24 -> 0 | AB24: =Y24*100/CU24 -> 1.9870219 | AC24: 22-01-2025 17:41:25 | AD24: 5951 | AE24: 4863497 | AF24: 4 | AG24: CAMINO OTOÑAL 1326 DPTO C2 | AH24: 993300005 | AK24: LAS CONDES | AL24: 21/04/1945 | AM24: MARCOS.KULKA@FCH.CL | AO24: STATION WAGON | AP24: FAMILIA 1 | AQ24: CH13K311 | AR24: BLANCO CANDY | AS24: 9BWCH6CH5RP048825 | AT24: 9BWCH6CH5RP048825 | AU24: NUEVO Y SIN USO | AV24: Facturada | AW24: 19924 | AX24: 27-01-2025 0:00:00 | AZ24: Guía de Despacho: 1 - Factura Electrónica: 1839682 | BA24: 16396017 | BB24: 27-01-2025 0:00:00 | BD24: 0 | BE24: WEB CONCESIONARIO | BF24: 27-01-2025 0:00:00 | BG24: CC | BH24: Peso | BJ24: 0 | BK24: 17134454 | BL24: -1848739 | BM24: -457563 | BN24: 14828151 | BO24: 16396017 | BP24: -1567866 | BQ24: -10.57 % | BR24: 0 | BS24: 844500 | BT24: 844500 | BU24: 0 | BV24: 0 % | BW24: 0 | BX24: 0 | BY24: 0 | BZ24: 0 | CA24: 0 % | CB24: 0 | CC24: 0 | CD24: 0 | CE24: 0 | CF24: 0 % | CG24: 15285715 | CH24: 15672651 | CI24: 17240517 | CJ24: -1567866 | CK24: -10 % | CL24: -1567866 | CM24: -10 % | CN24: 0 | CO24: 0 | CP24: 18490000 | CQ24: 0 | CR24: 844500 | CS24: 0 | CT24: 18490000 | CU24: 15672651 | CV24: -1567866 | CW24: -10 % | CY24: 0 | DA24: 0 | DB24: 0 | DC24: 0
A25: ANDES MOTOR | B25: KARRY | C25: Q22 C.B. Cargo Box 1.5cc | D25: AN-25-01-0036 | E25: 2023 | F25: LVM1A1A14NF048727 | G25: LION OPERATIONS SPA | H25: Marcos Ignacio Campos Zavala | I25: N | J25: Directo | K25: =BA25 -> 9380600 | L25: 75000 | M25: =BT25 -> 336980 | P25: =CU25 -> 7891602 | Q25: =R25*1.19 -> 2677500 | R25: 2250000 | S25: =T25*1.19 -> 0 | V25: =U25/1.19 -> 0 | W25: =X25*1.19 -> 0 | Y25: =-K25-L25-M25-N25+O25+P25+R25+T25+V25+X25 -> 349022 | Z25: =VLOOKUP(D25,'Archivo con Bonos Ingresados '!V:CB,59,0) -> 349022 | AA25: =Z25-Y25 -> 0 | AB25: =Y25*100/CU25 -> 4.4227015 | AC25: 24-01-2025 10:01:06 | AD25: 5956 | AE25: 78060017 | AF25: 9 | AG25: SEMINARIO 372 | AI25: 985290198 | AK25: PUERTO MONTT | AM25: gabriel.oberreuter@opciones.cl | AP25: Q22 | AQ25: Q22 C.B. Cargo Box 1.5cc | AR25: BLANCO | AS25: LVM1A1A14NF048727 | AT25: LVM1A1A14NF048727 | AU25: NUEVO Y SIN USO | AV25: Parcial Facturada | AW25: 19950 | AX25: 31-01-2025 0:00:00 | AZ25: Guía de Despacho: 1 - Factura Electrónica: 293476 | BA25: 9380600 | BB25: 31-01-2025 0:00:00 | BD25: 0 | BE25: WEB CONCESIONARIO | BF25: 31-01-2025 0:00:00 | BG25: FLOTA | BH25: Peso | BJ25: -6 | BK25: 10540000 | BL25: -2250000 | BM25: -735378 | BN25: 7554622 | BO25: 9380600 | BP25: -1825978 | BQ25: -24.17 % | BR25: 0 | BS25: 336980 | BT25: 336980 | BU25: 0 | BV25: 0 % | BW25: 0 | BX25: 0 | BY25: 0 | BZ25: 0 | CA25: 0 % | CB25: 0 | CC25: 0 | CD25: 0 | CE25: 0 | CF25: 0 % | CG25: 8290000 | CH25: 7891602 | CI25: 9717580 | CJ25: -1825978 | CK25: -23.14 % | CL25: -1825978 | CM25: -23.14 % | CN25: 0 | CO25: 0 | CP25: 9326980 | CQ25: 0 | CR25: 336980 | CS25: 0 | CT25: 9326980 | CU25: 7891602 | CV25: -1825978 | CW25: -23.14 % | CY25: 0 | DA25: 0 | DB25: 0 | DC25: 0
A26: CASA MATRIZ NUEVOS | B26: VOLKSWAGEN | C26: SAVEIRO 1.6 MT CABINA DOBLE 81 kW/110 CV | D26: AN-24-06-0030 | E26: 2025 | F26: 9BWJL45U1SP003018 | G26: LIQUI MOLY CHILE S.A | H26: JUAN PABLO GONZALEZ ACUÑA | I26: N | J26: Directo | K26: =BA26 -> 13054340 | L26: 90000 | M26: =BT26 -> 485138 | P26: =CU26 -> 13454738 | Q26: =R26*1.19 -> 1263708.6 | R26: 1061940 | S26: =T26*1.19 -> 164291.4 | T26: 138060 | V26: =U26/1.19 -> 0 | W26: =X26*1.19 -> 0 | Y26: =-K26-L26-M26-N26+O26+P26+R26+T26+V26+X26 -> 1025260 | Z26: =VLOOKUP(D26,'Archivo con Bonos Ingresados '!V:CB,59,0) -> 1025260 | AA26: =Z26-Y26 -> 0 | AB26: =Y26*100/CU26 -> 7.6200666 | AC26: 16-01-2025 10:16:04 | AD26: 5934 | AE26: 86868900 | AF26: 5 | AG26: ELIODORO YAÑEZ 1727 | AH26: 984188185 | AK26: PROVIDENCIA | AL26: 01/01/1900 | AM26: info@liqui-moly.cl | AO26: CAMIONETA | AP26: FAMILIA 1 | AQ26: 5UKWT413 | AR26: BLANCO CANDY | AS26: 9BWJL45U1SP003018 | AT26: 9BWJL45U1SP003018 | AU26: NUEVO Y SIN USO | AV26: Parcial Facturada | AW26: 19884 | AX26: 17-01-2025 0:00:00 | AZ26: Guía de Despacho: 1 - Factura Electrónica: 1791013 - Nota de Crédito Electrónica: 3060477 - Nota de Crédito Electrónica: 3060548 | BA26: 13054340 | BB26: 17-01-2025 0:00:00 | BD26: 0 | BE26: SALON | BF26: 17-01-2025 0:00:00 | BG26: FLOTA | BH26: Peso | BJ26: 0 | BK26: 15340000 | BL26: -1450000 | BM26: -920400 | BN26: 12969600 | BO26: 11854340 | BP26: 1115260 | BQ26: 8.6 % | BR26: 0 | BS26: 485138 | BT26: 485138 | BU26: 0 | BV26: 0 % | BW26: 0 | BX26: 0 | BY26: 0 | BZ26: 0 | CA26: 0 % | CB26: 0 | CC26: 0 | CD26: 0 | CE26: 0 | CF26: 0 % | CG26: 13890000 | CH26: 13454738 | CI26: 12339478 | CJ26: 1115260 | CK26: 8.29 % | CL26: 1115260 | CM26: 8.29 % | CN26: 0 | CO26: 0 | CP26: 15918962 | CQ26: 0 | CR26: 485138 | CS26: 0 | CT26: 15918962 | CU26: 13454738 | CV26: 1115260 | CW26: 8.29 % | CY26: 0 | DA26: 0 | DB26: 1428000 | DC26: 0
A27: CASA MATRIZ NUEVOS | B27: VOLKSWAGEN | C27: T-Cross 1.0 TSI AT Comfortline - 85 kW/116 CV | D27: AN-24-08-0075 | E27: 2025 | F27: 9BWBH6BF0S4003522 | G27: LUIS ALEJANDRO REINOSO MEDINELLI | H27: JUAN PABLO GONZALEZ ACUÑA | I27: N | J27: Directo | K27: =BA27 -> 16812766 | L27: 175000 | M27: =BT27 -> 921320 | P27: =CU27 -> 16877496 | Q27: =R27*1.19 -> 1749999.7 | R27: 1470588 | S27: =T27*1.19 -> 0 | V27: =U27/1.19 -> 0 | W27: =X27*1.19 -> 214899.72 | X27: 180588 | Y27: =-K27-L27-M27-N27+O27+P27+R27+T27+V27+X27 -> 619586 | Z27: =VLOOKUP(D27,'Archivo con Bonos Ingresados '!V:CB,59,0) -> 619586 | AA27: =Z27-Y27 -> 0 | AB27: =Y27*100/CU27 -> 3.6710777 | AC27: 02-01-2025 12:13:45 | AD27: 5884 | AE27: 8133978 | AF27: 3 | AG27: MARCEL DUHAUT 2977 DPTO 501 | AH27: 988993993 | AK27: PROVIDENCIA | AL27: 10/08/1967 | AM27: areinoso@uc.cl | AO27: STATION WAGON | AP27: T CROSS | AQ27: BF33K311 | AR27: AZUL NORUEGA | AS27: 9BWBH6BF0S4003522 | AT27: 9BWBH6BF0S4003522 | AU27: NUEVO Y SIN USO | AV27: Facturada | AW27: 19842 | AX27: 09-01-2025 0:00:00 | AZ27: Guía de Despacho: 1 - Factura Electrónica: 1838074 | BA27: 16812766 | BB27: 09-01-2025 0:00:00 | BD27: 0 | BE27: SALON | BF27: 09-01-2025 0:00:00 | BG27: RETAIL | BH27: Peso | BJ27: 0 | BK27: 18058824 | BL27: -1470588 | BM27: -632059 | BN27: 15956176 | BO27: 16812766 | BP27: -856590 | BQ27: -5.37 % | BR27: 0 | BS27: 921320 | BT27: 921320 | BU27: 0 | BV27: 0 % | BW27: 0 | BX27: 0 | BY27: 0 | BZ27: 0 | CA27: 0 % | CB27: 0 | CC27: 0 | CD27: 0 | CE27: 0 | CF27: 0 % | CG27: 16588236 | CH27: 16877496 | CI27: 17734086 | CJ27: -856590 | CK27: -5.08 % | CL27: -856590 | CM27: -5.08 % | CN27: 0 | CO27: 0 | CP27: 19909170 | CQ27: 0 | CR27: 921320 | CS27: 0 | CT27: 19909169 | CU27: 16877496 | CV27: -856590 | CW27: -5.08 % | CY27: 0 | DA27: 0 | DB27: 0 | DC27: 0
A28: ANDES MOTOR | B28: JETOUR | C28: T2 2.0T GDI AWD 7DCT LIMITED | D28: AN-24-08-0067 | E28: 2025 | F28: HJRPBGJBXSB200369 | G28: MANUELA SOLEDAD SALAS CAMPOS | H28: Marcos Ignacio Campos Zavala | I28: N | J28: BK | K28: =BA28 -> 23185546 | L28: 175000 | M28: =BT28 -> 1572888 | P28: =CU28 -> 24637090 | Q28: 400000 | R28: =Q28/1.19 -> 336134.45 | S28: =T28*1.19 -> 0 | U28: 1000000 | V28: =U28/1.19 -> 840336.13 | W28: =X28*1.19 -> 0 | Y28: =-K28-L28-M28-N28+O28+P28+R28+T28+V28+X28 -> 880126.59 | Z28: =VLOOKUP(D28,'Archivo con Bonos Ingresados '!V:CB,59,0) -> 880127 | AA28: =Z28-Y28 -> 0.41176471 | AB28: =Y28*100/CU28 -> 3.5723642 | AC28: 21-01-2025 14:49:46 | AD28: 5945 | AE28: 17958247 | AF28: 3 | AG28: JUAN DE DIOS VIAL CORREA 4220 DPTO 401 B | AH28: 95975802 | AI28: 951975802 | AK28: PEÑALOLEN | AL28: 10/06/1991 | AM28: manu_salas1991@hotmail.com | AP28: T2 | AQ28: T2 2.0T GDI AWD 7DCT LIMITED | AR28: GRIS ARENA | AS28: HJRPBGJBXSB200369 | AT28: HJRPBGJBXSB200369 | AU28: NUEVO Y SIN USO | AV28: Parcial Facturada | AW28: 19957 | AX28: 31-01-2025 0:00:00 | AZ28: Guía de Despacho: 1 - Factura Electrónica: 187112 | BA28: 23185546 | BB28: 02-03-2025 0:00:00 | BD28: 0 | BE28: WEB CONCESIONARIO | BF28: 02-03-2025 0:00:00 | BG28: RETAIL | BH28: Peso | BI28: SFXJ73 | BJ28: 158 | BK28: 25201681 | BL28: -1176471 | BM28: -961008 | BN28: 23064202 | BO28: 23185546 | BP28: -121344 | BQ28: -0.53 % | BR28: 0 | BS28: 1572888 | BT28: 1572888 | BU28: 0 | BV28: 0 % | BW28: 0 | BX28: 0 | BY28: 0 | BZ28: 0 | CA28: 0 % | CB28: 0 | CC28: 0 | CD28: 0 | CE28: 0 | CF28: 0 % | CG28: 24025210 | CH28: 24637090 | CI28: 24758434 | CJ28: -121344 | CK28: -0.49 % | CL28: -121344 | CM28: -0.49 % | CN28: 0 | CO28: 6700000 | CP28: 24798063 | CQ28: -2478775 | CR28: 1572888 | CS28: 0 | CT28: 29019288 | CU28: 24637090 | CV28: -121344 | CW28: -0.49 % | CY28: 0 | DA28: 0 | DB28: 0 | DC28: 0
A29: CASA MATRIZ NUEVOS | B29: VOLKSWAGEN | C29: SAVEIRO 1.6 MT CABINA SIMPLE | D29: AN-24-11-0083 | E29: 2025 | F29: 9BWKL45U5SP024555 | G29: MAQUINARIAS FABIAN GALLARDO, E.I.R.L | H29: ROBERTO LOBOS GUTIERREZ | I29: N | J29: Lucy | K29: =BA29 -> 12358360 | L29: 90000 | M29: =BT29 -> 338823 | P29: =CU29 -> 11431260 | Q29: =R29*1.19 -> 1963500 | R29: 1650000 | S29: =T29*1.19 -> 651999.81 | T29: 547899 | U29: 150000 | V29: =U29/1.19 -> 126050.42 | W29: =X29*1.19 -> 0 | Y29: =-K29-L29-M29-N29+O29+P29+R29+T29+V29+X29 -> 968026.42 | Z29: =VLOOKUP(D29,'Archivo con Bonos Ingresados '!V:CB,59,0) -> 968026 | AA29: =Z29-Y29 -> -0.42016807 | AB29: =Y29*100/CU29 -> 8.468239 | AC29: 09-01-2025 17:40:31 | AD29: 5906 | AE29: 76096975 | AF29: 3 | AG29: COSTANERA DEL ESTRECHO 01934 EL GOLF | AI29: 56977082136 | AK29: PUNTA ARENAS | AL29: 01/01/1900 | AM29: Fgallardo@fgmaq.cl | AO29: CAMIONETA | AP29: SAVEIRO | AQ29: 5URTT413 | AR29: PLATA SIRIUS | AS29: 9BWKL45U5SP024555 | AT29: 9BWKL45U5SP024555 | AU29: NUEVO Y SIN USO | AV29: Facturada | AW29: 19895 | AX29: 22-01-2025 0:00:00 | AZ29: Guía de Despacho: 1 - Factura Electrónica: 1840962 - Nota de Crédito Electrónica: 3062488 | BA29: 12358360 | BB29: 21-02-2025 0:00:00 | BD29: 0 | BE29: WEB CONCESIONARIO | BF29: 21-02-2025 0:00:00 | BG29: CI | BH29: Peso | BJ29: 0 | BK29: 0 | BL29: -2450000 | BM29: -597563 | BN29: 11092437 | BO29: 10708360 | BP29: 384077 | BQ29: 3.46 % | BR29: 0 | BS29: 338823 | BT29: 338823 | BU29: 0 | BV29: 0 % | BW29: 0 | BX29: 0 | BY29: 0 | BZ29: 0 | CA29: 0 % | CB29: 0 | CC29: 0 | CD29: 0 | CE29: 0 | CF29: 0 % | CG29: -2450000 | CH29: 11431260 | CI29: 11047183 | CJ29: 384077 | CK29: 3.36 % | CL29: 384077 | CM29: 3.36 % | CN29: 0 | CO29: 0 | CP29: 13538823 | CQ29: 0 | CR29: 338823 | CS29: 0 | CT29: 13538823 | CU29: 11431260 | CV29: 384077 | CW29: 3.36 % | CY29: 0 | DA29: 0 | DB29: 1963500 | DC29: 0
A30: CASA MATRIZ NUEVOS | B30: VOLKSWAGEN | C30: Nivus 1.0 TSI AT Comfortline 85KW/116CV 5 p | D30: AN-24-03-0040 | E30: 2024 | F30: 9BWCH6CH3PP006182 | G30: MARIA DE LOS ANGELES RENARD MERINO | H30: ROBERTO LOBOS GUTIERREZ | I30: V | J30: Directo | K30: =BA30 -> 15695160 | L30: 145000 | M30: =BT30 -> 491389 | P30: =CU30 -> 13928364 | Q30: =R30*1.19 -> 4673400.1 | R30: 3927227 | S30: =T30*1.19 -> 0 | V30: =U30/1.19 -> 0 | W30: =X30*1.19 -> 0 | Y30: =-K30-L30-M30-N30+O30+P30+R30+T30+V30+X30 -> 1524042 | Z30: =VLOOKUP(D30,'Archivo con Bonos Ingresados '!V:CB,59,0) -> 1524042 | AA30: =Z30-Y30 -> 0 | AB30: =Y30*100/CU30 -> 10.942003 | AC30: 11-01-2025 11:47:26 | AD30: 5914 | AE30: 8966208 | AF30: 7 | AG30: GENERAL BLANCHE 10226 | AI30: 998273729 | AK30: LAS CONDES | AL30: 01/01/1900 | AM30: MRENARD@YUKEN.CL | AO30: STATION WAGON | AP30: FAMILIA 1 | AQ30: CH13K311 | AR30: BLANCO CANDY | AS30: 9BWCH6CH3PP006182 | AT30: 9BWCH6CH3PP006182 | AU30: NUEVO Y SIN USO | AV30: Facturada | AW30: 19860 | AX30: 14-01-2025 0:00:00 | AZ30: Guía de Despacho Electrónica: 1 - Factura Electrónica: 1788757 - Nota de Crédito Electrónica: 3058060 | BA30: 15695160 | BB30: 14-01-2025 0:00:00 | BD30: 0 | BE30: SALON | BF30: 14-01-2025 0:00:00 | BG30: CC | BH30: Peso | BJ30: 0 | BK30: 17134454 | BL30: -3697479 | BM30: 0 | BN30: 13436975 | BO30: 15695160 | BP30: -2258185 | BQ30: -16.81 % | BR30: 0 | BS30: 491389 | BT30: 491389 | BU30: 0 | BV30: 0 % | BW30: 0 | BX30: 0 | BY30: 0 | BZ30: 0 | CA30: 0 % | CB30: 0 | CC30: 0 | CD30: 0 | CE30: 0 | CF30: 0 % | CG30: 13436975 | CH30: 13928364 | CI30: 16186549 | CJ30: -2258185 | CK30: -16.21 % | CL30: -2258185 | CM30: -16.21 % | CN30: 0 | CO30: 0 | CP30: 16481389 | CQ30: 0 | CR30: 491389 | CS30: 0 | CT30: 16481389 | CU30: 13928364 | CV30: -2258185 | CW30: -16.21 % | CY30: 0 | DA30: 0 | DB30: 0 | DC30: 0
A31: CASA MATRIZ NUEVOS | B31: VOLKSWAGEN | C31: POLO 1.0 TSI HIGHLINE AT | D31: AN-24-06-0015 | E31: 2024 | F31: 9BWAH5BZ8ST602190 | G31: MARIA JOSE VIELMA ZANDOVAL | H31: CLAUDIO ROBLEZ GALAZ | I31: V | J31: Directo | K31: =BA31 -> 14537722 | L31: 90000 | M31: =BT31 -> 489290 | P31: =CU31 -> 13523500 | Q31: =R31*1.19 -> 2239400.3 | R31: 1881849 | S31: =T31*1.19 -> 0 | V31: =U31/1.19 -> 0 | W31: =X31*1.19 -> 0 | Y31: =-K31-L31-M31-N31+O31+P31+R31+T31+V31+X31 -> 288337 | Z31: =VLOOKUP(D31,'Archivo con Bonos Ingresados '!V:CB,59,0) -> 288337 | AA31: =Z31-Y31 -> 0 | AB31: =Y31*100/CU31 -> 2.1321182 | AC31: 08-01-2025 13:23:44 | AD31: 5899 | AE31: 20465426 | AF31: 3 | AG31: CAMINO LAS CUMBRE 6838 CASA 36 | AH31: 950270639 | AI31: 950270639 | AK31: LA FLORIDA | AL31: 02/03/2000 | AM31: ALAN.MARTINEZ.ANTIL@GMAIL.COM | AO31: AUTOMOVIL | AP31: POLO | AQ31: BZ33D311 | AR31: GRIS PLATINO | AS31: 9BWAH5BZ8ST602190 | AT31: 9BWAH5BZ8ST602190 | AU31: NUEVO Y SIN USO | AV31: Facturada | AW31: 19853 | AX31: 13-01-2025 0:00:00 | AZ31: Guía de Despacho: 1 - Factura Electrónica: 1790936 | BA31: 14537722 | BB31: 13-01-2025 0:00:00 | BD31: 0 | BE31: AMIGO | BF31: 13-01-2025 0:00:00 | BG31: RETAIL | BH31: Peso | BJ31: 224 | BK31: 15957983 | BL31: -2923773 | BM31: 0 | BN31: 13034210 | BO31: 14537722 | BP31: -1503512 | BQ31: -11.54 % | BR31: 0 | BS31: 489290 | BT31: 489290 | BU31: 0 | BV31: 0 % | BW31: 0 | BX31: 0 | BY31: 0 | BZ31: 0 | CA31: 0 % | CB31: 0 | CC31: 0 | CD31: 0 | CE31: 0 | CF31: 0 % | CG31: 13034210 | CH31: 13523500 | CI31: 15027012 | CJ31: -1503512 | CK31: -11.12 % | CL31: -1503512 | CM31: -11.12 % | CN31: 0 | CO31: 0 | CP31: 16000000 | CQ31: 0 | CR31: 489290 | CS31: 0 | CT31: 16000000 | CU31: 13523500 | CV31: -1503512 | CW31: -11.12 % | CY31: 0 | DA31: 0 | DB31: 0 | DC31: 0
A32: ANDES MOTOR | B32: JETOUR | C32: T2 2.0T GDI AWD 7DCT LIMITED | D32: AN-25-01-0033 | E32: 2025 | F32: HJRPBGJB1SB203855 | G32: MATIAS AGLIATI GARRIDO | H32: Marcos Ignacio Campos Zavala | I32: N | J32: BK | K32: =BA32 -> 23185546 | L32: 175000 | M32: =BT32 -> 1460222 | P32: =CU32 -> 23717701 | Q32: 400000 | R32: =Q32/1.19 -> 336134.45 | S32: =T32*1.19 -> 0 | U32: 2000000 | V32: =U32/1.19 -> 1680672.3 | W32: =X32*1.19 -> 0 | Y32: =-K32-L32-M32-N32+O32+P32+R32+T32+V32+X32 -> 913739.72 | Z32: =VLOOKUP(D32,'Archivo con Bonos Ingresados '!V:CB,59,0) -> 913740 | AA32: =Z32-Y32 -> 0.27731092 | AB32: =Y32*100/CU32 -> 3.8525645 | AC32: 31-01-2025 10:48:39 | AD32: 5970 | AE32: 15959880 | AF32: 2 | AG32: LO CABAÑA 80 DPTO 804 | AH32: 93433346 | AI32: 993433346 | AK32: LAS CONDES | AL32: 27/11/1984 | AM32: MATIASAGLIATI@GMAIL.COM | AP32: T2 | AQ32: T2 2.0T GDI AWD 7DCT LIMITED | AR32: GRIS ARENA | AS32: HJRPBGJB1SB203855 | AT32: HJRPBGJB1SB203855 | AU32: NUEVO Y SIN USO | AV32: Parcial Facturada | AW32: 19958 | AX32: 31-01-2025 0:00:00 | AZ32: Guía de Despacho: 1 - Factura Electrónica: 206373 | BA32: 23185546 | BB32: 02-03-2025 0:00:00 | BD32: 0 | BE32: WEB CONCESIONARIO | BF32: 02-03-2025 0:00:00 | BG32: RETAIL | BH32: Peso | BI32: KZHK49 | BJ32: 9 | BK32: 25201681 | BL32: -2016807 | BM32: -927395 | BN32: 22257479 | BO32: 23185546 | BP32: -928067 | BQ32: -4.17 % | BR32: 0 | BS32: 1460222 | BT32: 1460222 | BU32: 0 | BV32: 0 % | BW32: 0 | BX32: 0 | BY32: 0 | BZ32: 0 | CA32: 0 % | CB32: 0 | CC32: 0 | CD32: 0 | CE32: 0 | CF32: 0 % | CG32: 23184874 | CH32: 23717701 | CI32: 24645768 | CJ32: -928067 | CK32: -3.91 % | CL32: -928067 | CM32: -3.91 % | CN32: 0 | CO32: 22500000 | CP32: 13268630 | CQ32: -7822008 | CR32: 1460222 | CS32: 0 | CT32: 27946622 | CU32: 23717701 | CV32: -928067 | CW32: -3.91 % | CY32: 0 | DA32: 0 | DB32: 0 | DC32: 0
A33: CASA MATRIZ NUEVOS | B33: VOLKSWAGEN | C33: T-Cross 1.0 TSI AT Comfortline - 85 kW/116 CV | D33: AN-24-08-0078 | E33: 2025 | F33: 9BWBH6BF1S4003030 | G33: MOISES ENRIQUE NUÑEZ ROMO | H33: ROBERTO LOBOS GUTIERREZ | I33: N | J33: Forum | K33: =BA33 -> 16812766 | L33: 175000 | M33: =BT33 -> 764231 | P33: =CU33 -> 15428097 | Q33: =R33*1.19 -> 1749999.7 | R33: 1470588 | S33: =T33*1.19 -> 1249999.8 | T33: 1050420 | U33: 150000 | V33: =U33/1.19 -> 126050.42 | W33: =X33*1.19 -> 214899.72 | X33: 180588 | Y33: =-K33-L33-M33-N33+O33+P33+R33+T33+V33+X33 -> 503746.42 | Z33: =VLOOKUP(D33,'Archivo con Bonos Ingresados '!V:CB,59,0) -> 503746 | AA33: =Z33-Y33 -> -0.42016807 | AB33: =Y33*100/CU33 -> 3.2651235 | AC33: 14-01-2025 18:10:14 | AD33: 5927 | AE33: 8669391 | AF33: 7 | AG33: REVERENDO FRANCISCO ANABALON ROSALES 131 | AI33: 972162219 | AK33: MAIPU | AL33: 01/01/1900 | AM33: MNUNEZROMO@GMAIL.COM | AO33: STATION WAGON | AP33: T CROSS | AQ33: BF33K311 | AR33: ROJO METALICO | AS33: 9BWBH6BF1S4003030 | AT33: 9BWBH6BF1S4003030 | AU33: NUEVO Y SIN USO | AV33: Facturada | AW33: 19879 | AX33: 16-01-2025 0:00:00 | AZ33: Guía de Despacho: 1 - Factura Electrónica: 1838075 | BA33: 16812766 | BB33: 15-02-2025 0:00:00 | BD33: 0 | BE33: WEB CONCESIONARIO | BF33: 15-02-2025 0:00:00 | BG33: CI | BH33: Peso | BJ33: 111 | BK33: 18058824 | BL33: -2773109 | BM33: -621849 | BN33: 14663866 | BO33: 16812766 | BP33: -2148900 | BQ33: -14.65 % | BR33: 0 | BS33: 764231 | BT33: 764231 | BU33: 0 | BV33: 0 % | BW33: 0 | BX33: 0 | BY33: 0 | BZ33: 0 | CA33: 0 % | CB33: 0 | CC33: 0 | CD33: 0 | CE33: 0 | CF33: 0 % | CG33: 15285715 | CH33: 15428097 | CI33: 17576997 | CJ33: -2148900 | CK33: -13.93 % | CL33: -2148900 | CM33: -13.93 % | CN33: 0 | CO33: 0 | CP33: 18214231 | CQ33: 0 | CR33: 764231 | CS33: 0 | CT33: 18214232 | CU33: 15428097 | CV33: -2148900 | CW33: -13.93 % | CY33: 0 | DA33: 0 | DB33: 0 | DC33: 0
A34: CASA MATRIZ NUEVOS | B34: VOLKSWAGEN | C34: Nivus 1.0 TSI AT Comfortline 85KW/116CV 5 p | D34: AN-24-10-0012 | E34: 2025 | F34: 9BWCH6CH5RP054012 | G34: NADIM HASAN MASRI CIOCCA | H34: ROBERTO LOBOS GUTIERREZ | I34: N | J34: Forum | K34: =BA34 -> 15342740 | L34: 145000 | M34: =BT34 -> 717696 | N34: 5000 | P34: =CU34 -> 14549629 | Q34: =R34*1.19 -> 2200000 | R34: 1848739.5 | S34: =T34*1.19 -> 0 | U34: 150000 | V34: =U34/1.19 -> 126050.42 | W34: =X34*1.19 -> 0 | Y34: =-K34-L34-M34-N34+O34+P34+R34+T34+V34+X34 -> 313982.92 | Z34: =VLOOKUP(D34,'Archivo con Bonos Ingresados '!V:CB,59,0) -> 313983 | AA34: =Z34-Y34 -> 0.079831933 | AB34: =Y34*100/CU34 -> 2.1580132 | AC34: 06-01-2025 16:34:36 | AD34: 5892 | AE34: 10324690 | AF34: 3 | AG34: SIMON BOLIVAR 6242 PARCELA LOTE H EL NOVICIADO | AI34: 956578629 | AK34: PUDAHUEL | AL34: 01/01/1900 | AM34: NADIM.MASRI@BICE.CL | AO34: STATION WAGON | AP34: FAMILIA 1 | AQ34: CH13K316 | AR34: GRIS PLATINO | AS34: 9BWCH6CH5RP054012 | AU34: NUEVO Y SIN USO | AV34: Facturada | AW34: 19846 | AX34: 10-01-2025 0:00:00 | AZ34: Guía de Despacho: 0 - Factura Electrónica: 1839314 - Nota de Crédito Electrónica: 3061669 | BA34: 15342740 | BB34: 09-02-2025 0:00:00 | BD34: 0 | BE34: SALON | BF34: 09-02-2025 0:00:00 | BG34: CC | BH34: Peso | BJ34: 71 | BK34: 0 | BL34: -3109244 | BM34: -613445 | BN34: 13831933 | BO34: 13494000 | BP34: 337933 | BQ34: 2.44 % | BR34: 0 | BS34: 717696 | BT34: 717696 | BU34: 0 | BV34: 0 % | BW34: 0 | BX34: 0 | BY34: 0 | BZ34: 0 | CA34: 0 % | CB34: 0 | CC34: 0 | CD34: 0 | CE34: 0 | CF34: 0 % | CG34: -3109244 | CH34: 14549629 | CI34: 14216696 | CJ34: 332933 | CK34: 2.29 % | CL34: 332933 | CM34: 2.29 % | CN34: 0 | CO34: 0 | CP34: 17177696 | CQ34: 0 | CR34: 717696 | CS34: 0 | CT34: 17177696 | CU34: 14549629 | CV34: 332933 | CW34: 2.29 % | CY34: 0 | DA34: 0 | DB34: 2200000 | DC34: 5000
A35: CASA MATRIZ NUEVOS | B35: VOLKSWAGEN | C35: Taos TSI AT Comfortline 110KW/150CV | D35: AN-24-10-0061 | E35: 2025 | F35: 8AWBJ6B26RA830005 | G35: NATALIE ANDREE BORDACHAR URRUTIA | H35: JUAN PABLO GONZALEZ ACUÑA | I35: N | J35: Lucy | K35: =BA35 -> 20025176 | L35: 175000 | M35: =BT35 -> 1024400 | P35: =CU35 -> 18594484 | Q35: =R35*1.19 -> 2950000.5 | R35: 2478992 | S35: =T35*1.19 -> 449999.69 | T35: 378151 | U35: 300000 | V35: =U35/1.19 -> 252100.84 | W35: =X35*1.19 -> 257900.37 | X35: 216723 | Y35: =-K35-L35-M35-N35+O35+P35+R35+T35+V35+X35 -> 695874.84 | Z35: =VLOOKUP(D35,'Archivo con Bonos Ingresados '!V:CB,59,0) -> 695875 | AA35: =Z35-Y35 -> 0.15966387 | AB35: =Y35*100/CU35 -> 3.7423724 | AC35: 29-01-2025 9:57:23 | AD35: 5963 | AE35: 15934220 | AF35: 4 | AG35: VEINTITRES DE FEBRERO 8916 CASA A | AH35: 998484576 | AK35: LA REINA | AL35: 31/07/1984 | AM35: nataliebordachar@gmail.com | AO35: STATION WAGON 01 | AP35: FAMILIA 1 | AQ35: CQ16LY11 | AR35: BLANCO PURO | AS35: 8AWBJ6B26RA830005 | AT35: 8AWBJ6B26RA830005 | AU35: NUEVO Y SIN USO | AV35: Facturada | AW35: 19942 | AX35: 29-01-2025 0:00:00 | AZ35: Guía de Despacho: 1 - Factura Electrónica: 1839961 | BA35: 20025176 | BB35: 28-02-2025 0:00:00 | BD35: 0 | BE35: SALON | BF35: 28-02-2025 0:00:00 | BG35: RETAIL | BH35: Peso | BJ35: 97 | BK35: 21672269 | BL35: -3235294 | BM35: -866891 | BN35: 17570084 | BO35: 20025176 | BP35: -2455092 | BQ35: -13.97 % | BR35: 0 | BS35: 1024400 | BT35: 1024400 | BU35: 0 | BV35: 0 % | BW35: 0 | BX35: 0 | BY35: 0 | BZ35: 0 | CA35: 0 % | CB35: 0 | CC35: 0 | CD35: 0 | CE35: 0 | CF35: 0 % | CG35: 18436975 | CH35: 18594484 | CI35: 21049576 | CJ35: -2455092 | CK35: -13.2 % | CL35: -2455092 | CM35: -13.2 % | CN35: 0 | CO35: 0 | CP35: 21932800 | CQ35: 0 | CR35: 1024400 | CS35: 0 | CT35: 21932800 | CU35: 18594484 | CV35: -2455092 | CW35: -13.2 % | CY35: 0 | DA35: 0 | DB35: 0 | DC35: 0
A36: CASA MATRIZ NUEVOS | B36: VOLKSWAGEN | C36: T-Cross 1.0 TSI AT Highline Sport - 85 kW/116 CV | D36: AN-25-01-0002 | E36: 2025 | F36: 9BWBH6BF6S4051090 | G36: NICOLLE CARLA CASAGRANDE ARO | H36: RAIMUNDO GAZITUA SAAVEDRA | I36: N | J36: Forum | K36: =BA36 -> 18024933 | L36: 175000 | M36: =BT36 -> 924879 | P36: =CU36 -> 17017316 | Q36: =R36*1.19 -> 1389070.3 | R36: 1167286 | S36: =T36*1.19 -> 1249999.8 | T36: 1050420 | U36: 150000 | V36: =U36/1.19 -> 126050.42 | W36: =X36*1.19 -> 229899.67 | X36: 193193 | Y36: =-K36-L36-M36-N36+O36+P36+R36+T36+V36+X36 -> 429453.42 | Z36: =VLOOKUP(D36,'Archivo con Bonos Ingresados '!V:CB,59,0) -> 429453 | AA36: =Z36-Y36 -> -0.42016807 | AB36: =Y36*100/CU36 -> 2.5236261 | AC36: 02-01-2025 18:09:17 | AD36: 5886 | AE36: 17467115 | AF36: K | AG36: TIAHUANACO 1077 DPTO 408B | AI36: 996998621 | AK36: VITACURA | AL36: 01/12/2024 | AM36: NICOLLECASAGRANDE@YAHOO.ES | AO36: STATION WAGON | AP36: T CROSS | AQ36: BF34K312 | AR36: Gris Ascot/Negro | AS36: 9BWBH6BF6S4051090 | AU36: NUEVO Y SIN USO | AV36: Facturada | AW36: 19831 | AX36: 08-01-2025 0:00:00 | AZ36: Guía de Despacho: 1 - Factura Electrónica: 1842454 | BA36: 18024933 | BB36: 07-02-2025 0:00:00 | BD36: 0 | BF36: 07-02-2025 0:00:00 | BG36: [OTRO] | BH36: Peso | BJ36: 0 | BK36: 19319328 | BL36: -2605042 | BM36: -621849 | BN36: 16092437 | BO36: 18024933 | BP36: -1932496 | BQ36: -12.01 % | BR36: 0 | BS36: 924879 | BT36: 924879 | BU36: 0 | BV36: 0 % | BW36: 0 | BX36: 0 | BY36: 0 | BZ36: 0 | CA36: 0 % | CB36: 0 | CC36: 0 | CD36: 0 | CE36: 0 | CF36: 0 % | CG36: 16714286 | CH36: 17017316 | CI36: 18949812 | CJ36: -1932496 | CK36: -11.36 % | CL36: -1932496 | CM36: -11.36 % | CN36: 0 | CO36: 0 | CP36: 20074879 | CQ36: 0 | CR36: 924879 | CS36: 0 | CT36: 20074879 | CU36: 17017316 | CV36: -1932496 | CW36: -11.36 % | CY36: 0 | DA36: 0 | DB36: 0 | DC36: 0
A37: ANDES MOTOR | B37: MAXUS | C37: T60 4X4 GLX AT E6 | D37: AN-24-11-0035 | E37: 2025 | F37: LSFAM11A5SA041445 | G37: PATAGONIA BIOTECNICNOLOGIA SPA | H37: Manuel Rodrigo Hurtado Melo | I37: N | J37: Directo | K37: =BA37 -> 24554800 | L37: 235000 | M37: =BT37 -> 929310 | P37: =CU37 -> 25619310 | Q37: =R37*1.19 -> 1785000 | R37: 1500000 | S37: =T37*1.19 -> 0 | V37: =U37/1.19 -> 0 | W37: =X37*1.19 -> 0 | Y37: =-K37-L37-M37-N37+O37+P37+R37+T37+V37+X37 -> 1400200 | Z37: =VLOOKUP(D37,'Archivo con Bonos Ingresados '!V:CB,59,0) -> 1400200 | AA37: =Z37-Y37 -> 0 | AB37: =Y37*100/CU37 -> 5.4654087 | AC37: 23-01-2025 11:04:10 | AD37: 5952 | AE37: 76321115 | AF37: 0 | AG37: RUTA V-065 KM 5 0 RIO CHICO | AI37: 994341528 | AK37: PUERTO MONTT | AL37: 28/05/2024 | AM37: TJOQUE@PATBIO.COM | AP37: T60 | AQ37: T60 4X4 GLX AT E6 | AR37: GRIS | AS37: LSFAM11A5SA041445 | AT37: LSFAM11A5SA041445 | AU37: NUEVO Y SIN USO | AV37: Parcial Facturada | AW37: 19913 | AX37: 24-01-2025 0:00:00 | AZ37: Guía de Despacho: 1 - Factura Electrónica: 206185 | BA37: 24554800 | BB37: 24-01-2025 0:00:00 | BD37: 0 | BE37: SITIO WEB | BF37: 24-01-2025 0:00:00 | BG37: RETAIL | BH37: Peso | BJ37: 0 | BK37: 26690000 | BL37: -1500000 | BM37: -500000 | BN37: 24690000 | BO37: 24554800 | BP37: 135200 | BQ37: 0.55 % | BR37: 0 | BS37: 929310 | BT37: 929310 | BU37: 0 | BV37: 0 % | BW37: 0 | BX37: 0 | BY37: 0 | BZ37: 0 | CA37: 0 % | CB37: 0 | CC37: 0 | CD37: 0 | CE37: 0 | CF37: 0 % | CG37: 25190000 | CH37: 25619310 | CI37: 25484110 | CJ37: 135200 | CK37: 0.53 % | CL37: 135200 | CM37: 0.53 % | CN37: 0 | CO37: 0 | CP37: 30310410 | CQ37: 0 | CR37: 929310 | CS37: 0 | CT37: 30310410 | CU37: 25619310 | CV37: 135200 | CW37: 0.53 % | CY37: 0 | DA37: 0 | DB37: 0 | DC37: 0
A38: CASA MATRIZ NUEVOS | B38: VOLKSWAGEN | C38: NUEVO TIGUAN TSI AT R-LINE 220HP 2.0 | D38: AN-24-10-0051 | E38: 2025 | F38: 3VVDE65N8RM149262 | G38: PATRICIA EBEL FERNANDEZ | H38: JUAN PABLO GONZALEZ ACUÑA | I38: N | J38: Directo | K38: =BA38 -> 30123832 | L38: 175000 | M38: =BT38 -> 2240615 | P38: =CU38 -> 34593556 | Q38: =R38*1.19 -> 1999999.7 | R38: 1680672 | S38: =T38*1.19 -> 0 | V38: =U38/1.19 -> 0 | W38: =X38*1.19 -> 0 | Y38: =-K38-L38-M38-N38+O38+P38+R38+T38+V38+X38 -> 3734781 | Z38: =VLOOKUP(D38,'Archivo con Bonos Ingresados '!V:CB,59,0) -> 3734781 | AA38: =Z38-Y38 -> 0 | AB38: =Y38*100/CU38 -> 10.796175 | AC38: 10-01-2025 11:50:25 | AD38: 5907 | AE38: 10888067 | AF38: 8 | AG38: COSTANERA SUR 12033 DPTO 504 | AH38: 968477239 | AK38: VITACURA | AL38: 19/11/1969 | AM38: pebelf@gmail.com | AO38: STATION WAGON 01 | AP38: FAMILIA 1 | AQ38: BJ25TT11 | AR38: GRIS PLATINO | AS38: 3VVDE65N8RM149262 | AT38: 3VVDE65N8RM149262 | AU38: NUEVO Y SIN USO | AV38: Facturada | AW38: 19845 | AX38: 10-01-2025 0:00:00 | AZ38: Guía de Despacho: 1 - Factura Electrónica: 1839727 - Nota de Crédito Electrónica: 3062523 | BA38: 30123832 | BB38: 10-01-2025 0:00:00 | BD38: 0 | BE38: SALON | BF38: 10-01-2025 0:00:00 | BG38: RETAIL | BH38: Peso | BI38: JBPP80 | BJ38: 0 | BK38: 34865546 | BL38: -1680672 | BM38: -831933 | BN38: 32352941 | BO38: 28443160 | BP38: 3909781 | BQ38: 12.08 % | BR38: 0 | BS38: 2240615 | BT38: 2240615 | BU38: 0 | BV38: 0 % | BW38: 0 | BX38: 0 | BY38: 0 | BZ38: 0 | CA38: 0 % | CB38: 0 | CC38: 0 | CD38: 0 | CE38: 0 | CF38: 0 % | CG38: 33184874 | CH38: 34593556 | CI38: 30683775 | CJ38: 3909781 | CK38: 11.3 % | CL38: 3909781 | CM38: 11.3 % | CN38: 0 | CO38: 29000000 | CP38: 11740615 | CQ38: 0 | CR38: 2240615 | CS38: 0 | CT38: 40740615 | CU38: 34593556 | CV38: 3909781 | CW38: 11.3 % | CY38: 0 | DA38: 0 | DB38: 2000000 | DC38: 0
A39: CASA MATRIZ NUEVOS | B39: VOLKSWAGEN | C39: NUEVO TIGUAN TSI AT COMFORTLINE 150HP | D39: AN-25-01-0010 | E39: 2025 | F39: 3VVHP65N9RM207455 | G39: PILAR DEL CARMEN RODRIGUEZ PEREZ | H39: JUAN PABLO GONZALEZ ACUÑA | I39: N | J39: Directo | K39: =BA39 -> 23804093 | L39: 175000 | M39: =BT39 -> 1592887 | P39: =CU39 -> 24441627 | Q39: =R39*1.19 -> 2900000.2 | R39: 2436975 | S39: =T39*1.19 -> 0 | V39: =U39/1.19 -> 0 | W39: =X39*1.19 -> 306899.81 | X39: 257899 | Y39: =-K39-L39-M39-N39+O39+P39+R39+T39+V39+X39 -> 1564521 | Z39: =VLOOKUP(D39,'Archivo con Bonos Ingresados '!V:CB,59,0) -> 1564521 | AA39: =Z39-Y39 -> 0 | AB39: =Y39*100/CU39 -> 6.401051 | AC39: 15-01-2025 12:52:36 | AD39: 5931 | AE39: 6506064 | AF39: 7 | AG39: AVDA LUIS PASTEUR 5626 DEPTO 402 | AH39: 982594676 | AK39: VITACURA | AL39: 09/01/1959 | AM39: pirope@gmail.com | AO39: STATION WAGON 01 | AP39: FAMILIA 1 | AQ39: BJ23N611 | AR39: GRIS PLATINO | AS39: 3VVHP65N9RM207455 | AU39: NUEVO Y SIN USO | AV39: Facturada | AW39: 19883 | AX39: 17-01-2025 0:00:00 | AZ39: Guía de Despacho: 1 - Factura Electrónica: 1864440 | BA39: 23804093 | BB39: 17-01-2025 0:00:00 | BD39: 0 | BE39: SALON | BF39: 17-01-2025 0:00:00 | BG39: RETAIL | BH39: Peso | BJ39: 0 | BK39: 25789916 | BL39: -2436975 | BM39: -504202 | BN39: 22848740 | BO39: 23804093 | BP39: -955353 | BQ39: -4.18 % | BR39: 0 | BS39: 1592887 | BT39: 1592887 | BU39: 0 | BV39: 0 % | BW39: 0 | BX39: 0 | BY39: 0 | BZ39: 0 | CA39: 0 % | CB39: 0 | CC39: 0 | CD39: 0 | CE39: 0 | CF39: 0 % | CG39: 23352941 | CH39: 24441627 | CI39: 25396980 | CJ39: -955353 | CK39: -3.91 % | CL39: -955353 | CM39: -3.91 % | CN39: 0 | CO39: 0 | CP39: 28782887 | CQ39: 0 | CR39: 1592887 | CS39: 0 | CT39: 28782888 | CU39: 24441627 | CV39: -955353 | CW39: -3.91 % | CY39: 0 | DA39: 0 | DB39: 0 | DC39: 0
A40: CASA MATRIZ NUEVOS | B40: VOLKSWAGEN | C40: T-Cross 1.0 TSI AT Comfortline - 85 kW/116 CV | D40: AN-24-12-0049 | E40: 2025 | F40: 9BWBH6BF6S4053356 | G40: RODRIGO ALFONSO HEREDIA PEÑA | H40: ROBERTO LOBOS GUTIERREZ | I40: N | J40: Directo | K40: =BA40 -> 16848883 | L40: 175000 | M40: =BT40 -> 889892 | P40: =CU40 -> 16394598 | Q40: =R40*1.19 -> 1749999.7 | R40: 1470588 | S40: =T40*1.19 -> 0 | V40: =U40/1.19 -> 0 | W40: =X40*1.19 -> 214899.72 | X40: 180588 | Y40: =-K40-L40-M40-N40+O40+P40+R40+T40+V40+X40 -> 131999 | Z40: =VLOOKUP(D40,'Archivo con Bonos Ingresados '!V:CB,59,0) -> 131999 | AA40: =Z40-Y40 -> 0 | AB40: =Y40*100/CU40 -> 0.80513716 | AC40: 21-01-2025 18:00:21 | AD40: 5949 | AE40: 10653803 | AF40: 4 | AG40: CAMINO LOS PEUMOS 10200 CASA 27 | AH40: 979667938 | AK40: LO BARNECHEA | AL40: 18/01/1973 | AM40: RODRIGOHEREDI@GMAIL.COM | AO40: STATION WAGON | AP40: T CROSS | AQ40: BF33K311 | AR40: PLATA PIRITA | AS40: 9BWBH6BF6S4053356 | AT40: 9BWBH6BF6S4053356 | AU40: NUEVO Y SIN USO | AV40: Facturada | AW40: 19925 | AX40: 27-01-2025 0:00:00 | AZ40: Guía de Despacho: 1 - Factura Electrónica: 1864428 | BA40: 16848883 | BB40: 27-01-2025 0:00:00 | BD40: 0 | BE40: SALON | BF40: 27-01-2025 0:00:00 | BG40: CC | BH40: Peso | BJ40: 32 | BK40: 18058824 | BL40: -1470588 | BM40: -1083529 | BN40: 15504706 | BO40: 16848883 | BP40: -1344177 | BQ40: -8.67 % | BR40: 0 | BS40: 889892 | BT40: 889892 | BU40: 0 | BV40: 0 % | BW40: 0 | BX40: 0 | BY40: 0 | BZ40: 0 | CA40: 0 % | CB40: 0 | CC40: 0 | CD40: 0 | CE40: 0 | CF40: 0 % | CG40: 16588236 | CH40: 16394598 | CI40: 17738775 | CJ40: -1344177 | CK40: -8.2 % | CL40: -1344177 | CM40: -8.2 % | CN40: 0 | CO40: 0 | CP40: 19340492 | CQ40: 0 | CR40: 889892 | CS40: 0 | CT40: 19340492 | CU40: 16394598 | CV40: -1344177 | CW40: -8.2 % | CY40: 0 | DA40: 0 | DB40: 0 | DC40: 0
A41: ANDES MOTOR | B41: MAXUS | C41: T60 BLACK EDITION 4X4 GLX AT E6 | D41: AN-25-01-0009 | E41: 2024 | F41: LSFAM11A3PA075696 | G41: RUCO SPA | H41: Matias Larrain Larrain | I41: N | J41: Directo | K41: =BA41 -> 21298620 | L41: 235000 | M41: =BT41 -> 721264 | P41: =CU41 -> 23140864 | Q41: =R41*1.19 -> 0 | S41: =T41*1.19 -> 0 | V41: =U41/1.19 -> 0 | W41: =X41*1.19 -> 0 | Y41: =-K41-L41-M41-N41+O41+P41+R41+T41+V41+X41 -> 885980 | Z41: =VLOOKUP(D41,'Archivo con Bonos Ingresados '!V:CB,59,0) -> 885980 | AA41: =Z41-Y41 -> 0 | AB41: =Y41*100/CU41 -> 3.8286384 | AC41: 10-01-2025 15:45:47 | AD41: 5912 | AE41: 77423111 | AF41: 0 | AG41: RAFAEL CASANOVA 213, 309 | AI41: 953274041 | AK41: SANTA CRUZ | AL41: 25/07/2022 | AM41: AGUSTIN@RUCOCONSULTING.CL | AP41: T60 | AQ41: T60 BLACK EDITION 4X4 GLX AT E6 | AR41: PLATA | AS41: LSFAM11A3PA075696 | AT41: LSFAM11A3PA075696 | AU41: NUEVO Y SIN USO | AV41: Parcial Facturada | AW41: 19889 | AX41: 20-01-2025 0:00:00 | AZ41: Guía de Despacho: 1 - Factura Electrónica: 206024 | BA41: 21298620 | BB41: 19-02-2025 0:00:00 | BD41: 0 | BE41: AMIGO | BF41: 19-02-2025 0:00:00 | BG41: CC | BH41: Peso | BI41: FRTD28 | BJ41: 6 | BK41: 26690000 | BL41: -4270400 | BM41: 0 | BN41: 22419600 | BO41: 21298620 | BP41: 1120980 | BQ41: 5 % | BR41: 0 | BS41: 721264 | BT41: 721264 | BU41: 0 | BV41: 0 % | BW41: 0 | BX41: 0 | BY41: 0 | BZ41: 0 | CA41: 0 % | CB41: 0 | CC41: 0 | CD41: 0 | CE41: 0 | CF41: 0 % | CG41: 22419600 | CH41: 23140864 | CI41: 22019884 | CJ41: 1120980 | CK41: 4.84 % | CL41: 1120980 | CM41: 4.84 % | CN41: 0 | CO41: 2000000 | CP41: 25400588 | CQ41: 0 | CR41: 721264 | CS41: 0 | CT41: 27400588 | CU41: 23140864 | CV41: 1120980 | CW41: 4.84 % | CY41: 0 | DA41: 0 | DB41: 0 | DC41: 0
A42: CASA MATRIZ NUEVOS | B42: VOLKSWAGEN | C42: Saveiro 1.6 MT Cabina Simple Lite | D42: AN-24-11-0057 | E42: 2025 | F42: 9BWKL45U7SP024783 | G42: SOCIEDAD COMERCIAL ELECTROPOWER S.A. | H42: ROBERTO LOBOS GUTIERREZ | I42: N | J42: Directo | K42: =BA42 -> 11047360 | L42: 90000 | M42: =BT42 -> 412733 | P42: =CU42 -> 11227859 | Q42: =R42*1.19 -> 1487500 | R42: 1250000 | S42: =T42*1.19 -> 0 | V42: =U42/1.19 -> 0 | W42: =X42*1.19 -> 0 | Y42: =-K42-L42-M42-N42+O42+P42+R42+T42+V42+X42 -> 927766 | Z42: =VLOOKUP(D42,'Archivo con Bonos Ingresados '!V:CB,59,0) -> 927766 | AA42: =Z42-Y42 -> 0 | AB42: =Y42*100/CU42 -> 8.2630713 | AC42: 08-01-2025 15:37:55 | AD42: 5900 | AE42: 76257832 | AF42: 8 | AG42: CARRETERA GENERAL SAN MARTIN 8250 BODEGA 29B | AI42: 998185621 | AK42: QUILICURA | AL42: 01/01/1900 | AM42: cosorio@electropower.cl | AO42: CAMIONETA | AP42: SAVEIRO | AQ42: 5URTT412 | AR42: BLANCO CANDY | AS42: 9BWKL45U7SP024783 | AT42: 9BWKL45U7SP024783 | AU42: NUEVO Y SIN USO | AV42: Facturada | AW42: 19843 | AX42: 10-01-2025 0:00:00 | AZ42: Guía de Despacho: 1 - Factura Electrónica: 1840741 - Nota de Crédito Electrónica: 3062484 | BA42: 11047360 | BB42: 10-01-2025 0:00:00 | BD42: 0 | BE42: SITIO WEB | BF42: 10-01-2025 0:00:00 | BG42: CC | BH42: Peso | BJ42: 0 | BK42: 12640000 | BL42: -1250000 | BM42: -574874 | BN42: 10815126 | BO42: 11047360 | BP42: -232234 | BQ42: -2.15 % | BR42: 0 | BS42: 412733 | BT42: 412733 | BU42: 0 | BV42: 0 % | BW42: 0 | BX42: 0 | BY42: 0 | BZ42: 0 | CA42: 0 % | CB42: 0 | CC42: 0 | CD42: 0 | CE42: 0 | CF42: 0 % | CG42: 11390000 | CH42: 11227859 | CI42: 11460093 | CJ42: -232234 | CK42: -2.07 % | CL42: -232234 | CM42: -2.07 % | CN42: 0 | CO42: 0 | CP42: 13282733 | CQ42: 0 | CR42: 412733 | CS42: 0 | CT42: 13282733 | CU42: 11227859 | CV42: -232234 | CW42: -2.07 % | CY42: 0 | DA42: 0 | DB42: 0 | DC42: 0
A43: CASA MATRIZ NUEVOS | B43: VOLKSWAGEN | C43: Saveiro 1.6 MT Cabina Simple Lite | D43: AN-24-10-0032 | E43: 2025 | F43: 9BWKL45U2SP015005 | G43: SOCIEDAD COMERCIAL ELECTROPOWER S.A. | H43: ROBERTO LOBOS GUTIERREZ | I43: N | J43: Directo | K43: =BA43 -> 11047360 | L43: 90000 | M43: =BT43 -> 407238 | P43: =CU43 -> 11039171 | Q43: =R43*1.19 -> 1487500 | R43: 1250000 | S43: =T43*1.19 -> 0 | V43: =U43/1.19 -> 0 | W43: =X43*1.19 -> 0 | Y43: =-K43-L43-M43-N43+O43+P43+R43+T43+V43+X43 -> 744573 | Z43: =VLOOKUP(D43,'Archivo con Bonos Ingresados '!V:CB,59,0) -> 744573 | AA43: =Z43-Y43 -> 0 | AB43: =Y43*100/CU43 -> 6.7448271 | AC43: 17-01-2025 17:31:36 | AD43: 5938 | AE43: 76257832 | AF43: 8 | AG43: CARRETERA GENERAL SAN MARTIN 8250 BODEGA 29B | AI43: 998185621 | AK43: QUILICURA | AL43: 01/01/1900 | AM43: cosorio@electropower.cl | AO43: CAMIONETA | AP43: SAVEIRO | AQ43: 5URTT412 | AR43: BLANCO CANDY | AS43: 9BWKL45U2SP015005 | AT43: 9BWKL45U2SP015005 | AU43: NUEVO Y SIN USO | AV43: Parcial Facturada | AW43: 19906 | AX43: 23-01-2025 0:00:00 | AZ43: Guía de Despacho: 1 - Factura Electrónica: 1839691 - Nota de Crédito Electrónica: 3061194 - Nota de Débito Electrónica: 3906658 - Nota de Crédito Electrónica: 3062483 | BA43: 11047360 | BB43: 23-01-2025 0:00:00 | BD43: 0 | BE43: SALON | BF43: 23-01-2025 0:00:00 | BG43: CC | BH43: Peso | BJ43: 98 | BK43: 12640000 | BL43: -1250000 | BM43: -758067 | BN43: 10631933 | BO43: 11047360 | BP43: -415427 | BQ43: -3.91 % | BR43: 0 | BS43: 407238 | BT43: 407238 | BU43: 0 | BV43: 0 % | BW43: 0 | BX43: 0 | BY43: 0 | BZ43: 0 | CA43: 0 % | CB43: 0 | CC43: 0 | CD43: 0 | CE43: 0 | CF43: 0 % | CG43: 11390000 | CH43: 11039171 | CI43: 11454598 | CJ43: -415427 | CK43: -3.76 % | CL43: -415427 | CM43: -3.76 % | CN43: 0 | CO43: 0 | CP43: 13059238 | CQ43: 0 | CR43: 407238 | CS43: 0 | CT43: 13059238 | CU43: 11039171 | CV43: -415427 | CW43: -3.76 % | CY43: 0 | DA43: 0 | DB43: 0 | DC43: 0
A44: ANDES MOTOR | B44: MAXUS | C44: T60 4X2 GL AT E6 | D44: AN-25-01-0007 | E44: 2025 | F44: LSFAM11A6SA041342 | G44: SOCIEDAD DE PROFESIONALES ASESORIAS GARREAUD FERNANDEZ LIMITADA | H44: Matias Larrain Larrain | I44: N | J44: Directo | K44: =BA44 -> 19862800 | L44: 235000 | M44: =BT44 -> 633536 | P44: =CU44 -> 20859936 | Q44: =R44*1.19 -> 595000 | R44: 500000 | S44: =T44*1.19 -> 0 | V44: =U44/1.19 -> 0 | W44: =X44*1.19 -> 0 | Y44: =-K44-L44-M44-N44+O44+P44+R44+T44+V44+X44 -> 628600 | Z44: =VLOOKUP(D44,'Archivo con Bonos Ingresados '!V:CB,59,0) -> 628600 | AA44: =Z44-Y44 -> 0 | AB44: =Y44*100/CU44 -> 3.0134321 | AC44: 08-01-2025 17:53:51 | AD44: 5901 | AE44: 77722252 | AF44: K | AG44: LO FONTECILLA 101 OFI 903 LC | AI44: +56 9 8428 0282 | AK44: LAS CONDES | AL44: 03/03/2023 | AM44: fgarreaud@pkgabogados.cl | AP44: T60 | AQ44: T60 4X2 GL AT E6 | AR44: PLATA | AS44: LSFAM11A6SA041342 | AT44: LSFAM11A6SA041342 | AU44: NUEVO Y SIN USO | AV44: Parcial Facturada | AW44: 19891 | AX44: 21-01-2025 0:00:00 | AZ44: Guía de Despacho: 1 - Factura Electrónica: 206075 | BA44: 19862800 | BB44: 20-02-2025 0:00:00 | BD44: 0 | BE44: SITIO WEB | BF44: 20-02-2025 0:00:00 | BG44: CC | BH44: Peso | BJ44: 16 | BK44: 21290000 | BL44: -500000 | BM44: -863600 | BN44: 20226400 | BO44: 19862800 | BP44: 363600 | BQ44: 1.8 % | BR44: 0 | BS44: 633536 | BT44: 633536 | BU44: 0 | BV44: 0 % | BW44: 0 | BX44: 0 | BY44: 0 | BZ44: 0 | CA44: 0 % | CB44: 0 | CC44: 0 | CD44: 0 | CE44: 0 | CF44: 0 % | CG44: 20790000 | CH44: 20859936 | CI44: 20496336 | CJ44: 363600 | CK44: 1.74 % | CL44: 363600 | CM44: 1.74 % | CN44: 0 | CO44: 0 | CP44: 24702952 | CQ44: 0 | CR44: 633536 | CS44: 0 | CT44: 24702952 | CU44: 20859936 | CV44: 363600 | CW44: 1.74 % | CY44: 0 | DA44: 0 | DB44: 0 | DC44: 0
A45: CASA MATRIZ NUEVOS | B45: VOLKSWAGEN | C45: VIRTUS 1.0 TSI COMFORTLINE AT | D45: AN-23-12-0036 | E45: 2024 | F45: 9BWDH6BZ4RP012042 | G45: TERESA INES DE LA CRUZ MILLAN KLUSSE | H45: CLAUDIO ROBLEZ GALAZ | I45: V | J45: Directo | K45: =BA45 -> 14445294 | L45: 75000 | M45: =BT45 -> 326936 | P45: =CU45 -> 11808502 | Q45: =R45*1.19 -> 1133400 | R45: 952437 | S45: =T45*1.19 -> 0 | V45: =U45/1.19 -> 0 | W45: =X45*1.19 -> 0 | Y45: =-K45-L45-M45-N45+O45+P45+R45+T45+V45+X45 -> -2086291 | Z45: =VLOOKUP(D45,'Archivo con Bonos Ingresados '!V:CB,59,0) -> -2086291 | AA45: =Z45-Y45 -> 0 | AB45: =Y45*100/CU45 -> -17.667702 | AC45: 17-01-2025 14:40:20 | AD45: 5937 | AE45: 5388894 | AF45: 1 | AG45: SANTA RITA 498 | AH45: 3565136/091318341 | AK45: LA REINA | AL45: 07/04/1951 | AM45: tmillan@med.uchile.cl | AO45: AUTOMOVIL | AP45: VIRTUS | AQ45: BZ43D311 | AR45: GRIS PLATINO | AS45: 9BWDH6BZ4RP012042 | AT45: 9BWDH6BZ4RP012042 | AU45: NUEVO Y SIN USO | AV45: Facturada | AW45: 19888 | AX45: 20-01-2025 0:00:00 | AZ45: Guía de Despacho: 1 - Factura Electrónica: 1753763 | BA45: 14445294 | BB45: 20-01-2025 0:00:00 | BD45: 0 | BE45: AMIGO | BF45: 20-01-2025 0:00:00 | BG45: RETAIL | BH45: Peso | BI45: CJFV96 | BJ45: 414 | BK45: 15873950 | BL45: -4117647 | BM45: -274736 | BN45: 11481566 | BO45: 14445294 | BP45: -2963728 | BQ45: -25.81 % | BR45: 0 | BS45: 326936 | BT45: 326936 | BU45: 0 | BV45: 0 % | BW45: 0 | BX45: 0 | BY45: 0 | BZ45: 0 | CA45: 0 % | CB45: 0 | CC45: 0 | CD45: 0 | CE45: 0 | CF45: 0 % | CG45: 11756303 | CH45: 11808502 | CI45: 14772230 | CJ45: -2963728 | CK45: -25.1 % | CL45: -2963728 | CM45: -25.1 % | CN45: 0 | CO45: 2200000 | CP45: 11790000 | CQ45: 0 | CR45: 326936 | CS45: 0 | CT45: 13990000 | CU45: 11808502 | CV45: -2963728 | CW45: -25.1 % | CY45: 0 | DA45: 0 | DB45: 0 | DC45: 0
A46: CASA MATRIZ NUEVOS | B46: VOLKSWAGEN | C46: Saveiro 1.6 MT Cabina Doble Lite | D46: AN-24-10-0077 | E46: 2025 | F46: 9BWJL45UXSP024658 | G46: TRANSPORTES DONOSTIA LTDA | H46: JUAN PABLO GONZALEZ ACUÑA | I46: N | J46: Directo | K46: =BA46 -> 12096160 | L46: 90000 | M46: =BT46 -> 441686 | P46: =CU46 -> 12931686 | Q46: =R46*1.19 -> 1606500 | R46: 1350000 | S46: =T46*1.19 -> 0 | V46: =U46/1.19 -> 0 | W46: =X46*1.19 -> 0 | Y46: =-K46-L46-M46-N46+O46+P46+R46+T46+V46+X46 -> 1653840 | Z46: =VLOOKUP(D46,'Archivo con Bonos Ingresados '!V:CB,59,0) -> 1653840 | AA46: =Z46-Y46 -> 0 | AB46: =Y46*100/CU46 -> 12.789052 | AC46: 13-01-2025 17:13:25 | AD46: 5922 | AE46: 76101208 | AF46: 8 | AG46: LOS OLIVOS 1253, PARQUE IND. ENEA, PUDAHUEL | AI46: 998175879 | AJ46: 998175879 | AK46: PUDAHUEL | AL46: 12/11/2000 | AM46: fernanda.iturriaga@proingas.cl | AO46: CAMIONETA | AP46: SAVEIRO | AQ46: 5UKWT412 | AR46: BLANCO PURO | AS46: 9BWJL45UXSP024658 | AT46: 9BWJL45UXSP024658 | AU46: NUEVO Y SIN USO | AV46: Facturada | AW46: 19856 | AX46: 14-01-2025 0:00:00 | AZ46: Guía de Despacho: 1 - Factura Electrónica: 1840268 - Nota de Crédito Electrónica: 3062528 | BA46: 12096160 | BB46: 14-01-2025 0:00:00 | BD46: 0 | BE46: SALON | BF46: 14-01-2025 0:00:00 | BG46: FLOTA | BH46: Peso | BJ46: 0 | BK46: 13840000 | BL46: -1350000 | BM46: 0 | BN46: 12490000 | BO46: 10746160 | BP46: 1743840 | BQ46: 13.96 % | BR46: 0 | BS46: 441686 | BT46: 441686 | BU46: 0 | BV46: 0 % | BW46: 0 | BX46: 0 | BY46: 0 | BZ46: 0 | CA46: 0 % | CB46: 0 | CC46: 0 | CD46: 0 | CE46: 0 | CF46: 0 % | CG46: 12490000 | CH46: 12931686 | CI46: 11187846 | CJ46: 1743840 | CK46: 13.49 % | CL46: 1743840 | CM46: 13.49 % | CN46: 0 | CO46: 0 | CP46: 15304786 | CQ46: 0 | CR46: 441686 | CS46: 0 | CT46: 15304786 | CU46: 12931686 | CV46: 1743840 | CW46: 13.49 % | CY46: 0 | DA46: 0 | DB46: 1606500 | DC46: 0
A47: ANDES MOTOR | B47: MAXUS | C47: T60 4X2 DX MT E6 | D47: AN-24-12-0001 | E47: 2025 | F47: LSFAM11A2SA041144 | G47: TRIPLE C INTERNATIONAL SPA | H47: CLAUDIO ROBLEZ GALAZ | I47: N | J47: Directo | K47: =BA47 -> 18978600 | L47: 235000 | M47: =BT47 -> 0 | P47: =CU47 -> 18170966 | Q47: =R47*1.19 -> 1801957.5 | R47: 1514250 | S47: =T47*1.19 -> 0 | V47: =U47/1.19 -> 0 | W47: =X47*1.19 -> 0 | Y47: =-K47-L47-M47-N47+O47+P47+R47+T47+V47+X47 -> 471616 | Z47: =VLOOKUP(D47,'Archivo con Bonos Ingresados '!V:CB,59,0) -> 471616 | AA47: =Z47-Y47 -> 0 | AB47: =Y47*100/CU47 -> 2.5954371 | AC47: 10-12-2024 16:36:57 | AD47: 5810 | AE47: 76009782 | AF47: 9 | AG47: EL ALFALFAL N°471 | AH47: 932399384 | AI47: 957897580 | AK47: LAMPA | AL47: 20/07/2010 | AM47: CGODOY@TRIPLECINTERNATIONAL.COM | AP47: T60 | AQ47: T60 4X2 DX MT E6 | AR47: BLANCO | AS47: LSFAM11A2SA041144 | AT47: LSFAM11A2SA041144 | AU47: NUEVO Y SIN USO | AV47: Facturada | AW47: 19896 | AX47: 22-01-2025 0:00:00 | AZ47: Guía de Despacho: 1 - Factura Electrónica: 205710 | BA47: 18978600 | BB47: 21-02-2025 0:00:00 | BD47: 0 | BF47: 21-02-2025 0:00:00 | BG47: [OTRO] | BH47: Peso | BJ47: 52 | BK47: 20190000 | BL47: -2019034 | BM47: 0 | BN47: 18170966 | BO47: 17464350 | BP47: 706616 | BQ47: 3.89 % | BR47: 0 | BS47: 0 | BT47: 0 | BU47: 0 | BV47: 0 % | BW47: 0 | BX47: 0 | BY47: 0 | BZ47: 0 | CA47: 0 % | CB47: 0 | CC47: 0 | CD47: 0 | CE47: 0 | CF47: 0 % | CG47: 18170966 | CH47: 18170966 | CI47: 17699350 | CJ47: 471616 | CK47: 2.6 % | CL47: 471616 | CM47: 2.6 % | CN47: 0 | CO47: 0 | CP47: 21623450 | CQ47: 0 | CR47: 0 | CS47: 0 | CT47: 21623450 | CU47: 18170966 | CV47: 471616 | CW47: 2.6 % | CY47: 0 | DA47: 0 | DB47: 1801958 | DC47: 235000
A48: CASA MATRIZ NUEVOS | B48: VOLKSWAGEN | C48: Nivus TSI MT Comfortline - 70 kW/95 CV | D48: AN-25-01-0013 | E48: 2025 | F48: 9BWCH6CHXRP079584 | G48: VANESSA INES MALDONADO ALARCON | H48: ROBERTO LOBOS GUTIERREZ | I48: N | J48: Directo | K48: =BA48 -> 14888798 | L48: 145000 | M48: =BT48 -> 784550 | P48: =CU48 -> 14469802 | Q48: =R48*1.19 -> 2700000.5 | R48: =1554622+714286 -> 2268908 | S48: =T48*1.19 -> 0 | V48: =U48/1.19 -> 0 | W48: =X48*1.19 -> 189900.2 | X48: 159580 | Y48: =-K48-L48-M48-N48+O48+P48+R48+T48+V48+X48 -> 1079942 | Z48: =VLOOKUP(D48,'Archivo con Bonos Ingresados '!V:CB,59,0) -> 365656 | AA48: =Z48-Y48 -> -714286 | AB48: =Y48*100/CU48 -> 7.4634193 | AC48: 21-01-2025 18:15:01 | AD48: 5950 | AE48: 17166024 | AF48: 6 | AG48: COLOMBIA 7800 DEPTO 704 | AI48: 956003735 | AK48: LA FLORIDA | AL48: 01/01/1900 | AM48: VANE.M.ALARCON@GMAIL.COM | AO48: STATION WAGON 01 | AP48: NIVUS | AQ48: CH13L411 | AR48: GRIS PLATINO | AS48: 9BWCH6CHXRP079584 | AU48: NUEVO Y SIN USO | AV48: Facturada | AW48: 19921 | AX48: 27-01-2025 0:00:00 | AZ48: Guía de Despacho: 1 - Factura Electrónica: 1864536 | BA48: 14888798 | BB48: 27-01-2025 0:00:00 | BD48: 0 | BE48: WEB CONCESIONARIO | BF48: 27-01-2025 0:00:00 | BG48: CC | BH48: Peso | BJ48: 0 | BK48: 15537815 | BL48: -1554622 | BM48: -718109 | BN48: 13685252 | BO48: 14888798 | BP48: -1203546 | BQ48: -8.79 % | BR48: 0 | BS48: 784550 | BT48: 784550 | BU48: 0 | BV48: 0 % | BW48: 0 | BX48: 0 | BY48: 0 | BZ48: 0 | CA48: 0 % | CB48: 0 | CC48: 0 | CD48: 0 | CE48: 0 | CF48: 0 % | CG48: 13983193 | CH48: 14469802 | CI48: 15673348 | CJ48: -1203546 | CK48: -8.32 % | CL48: -1203546 | CM48: -8.32 % | CN48: 0 | CO48: 0 | CP48: 17070000 | CQ48: 0 | CR48: 784550 | CS48: 0 | CT48: 17070000 | CU48: 14469802 | CV48: -1203546 | CW48: -8.32 % | CY48: 0 | DA48: 0 | DB48: 0 | DC48: 0
Y49: =SUM(Y2:Y48) -> 33511098 | AA49: =Z49-Y49 -> -33511098
V51: Promedio | W51: Total
T52: Pasajeros | V52: =Hoja4!H56 -> 752916.91 | W52: =Hoja4!H57 -> 25599175
T53: LNF
T54: Andes Motors | V54: =Hoja4!B51 -> 608609.49 | W54: =Hoja4!B52 -> 7911923.3
T55: Total Autos | V55: =COUNTA(Y2:Y48) -> 47
W56: =SUM(W52:W54) -> 33511098

Sheet VW
A1: Sucursal | B1: Vendedor | C1: Fecha Venta | D1: Folio Venta | E1: Cliente | F1: Rut | G1: Digito | H1: Dirección | I1: Teléfono Fijo | J1: Teléfono Móvil | K1: Teléfono Comercial | L1: Comuna | M1: Fecha Nacimiento | N1: E-mail | O1: Placa Patente | P1: Tipo Vehículo | Q1: Marca | R1: Modelo | S1: Versión | T1: Codigo Version | U1: Color | V1: Código Interno | W1: Numero Chasis | X1: Numero VIN | Y1: Numero Serie | Z1: Condición | AA1: Año | AB1: Estado Venta | AC1: Folio Facturación | AD1: Fecha Facturación | AE1: Tipo Documento | AF1: Documento | AG1: Precio Compra | AH1: Vencimiento Factura | AI1: Vendedor Cotización | AJ1: Folio | AK1: Medio Contacto | AL1: Vencimiento Documento | AM1: Tipo Venta | AN1: Moneda Venta | AO1: Patente Pago | AP1: Días Stock | AQ1: Precio Lista | AR1: Bono Lista Precio | AS1: Descuento Unidad | AT1: Unidad Venta | AU1: Unidad Costo | AV1: Unidad Margen | AW1: % | AX1: Tramites Descuento/Recargo | AY1: Tramites Venta | AZ1: Tramites Costo | BA1: Tramites Margen | BB1: %1 | BC1: Accesorios Descuento/Recargo | BD1: Accesorios Venta | BE1: Accesorios Costo | BF1: Accesorios Margen | BG1: %2 | BH1: Contratos DR ML | BI1: Contratos Sub Total ML | BJ1: Contratos Costo ML | BK1: Contratos Margen ML | BL1: Contratos Margen Pje | BM1: Total Lista Precio | BN1: SubTotal Venta | BO1: SubTotal Costo | BP1: SubTotal Margen + Crédito + Seguro | BQ1: %3 | BR1: Margen Sin Intereses | BS1: Sub Total Margen ML Sin Inter~s Pje | BT1: Total Interés | BU1: Total Retoma | BV1: Total Abono | BW1: Total Saldo | BX1: Total Venta Trámite | BY1: Total Venta Accesorios | BZ1: Total Venta | CA1: Venta Sin Creditos Y Seguros | CB1: Margen de Venta | CC1: Pje. Margen de Venta | CD1: Entidad Crédito | CE1: Margen Crédito | CF1: Entidad Seguro | CG1: Margen Seguro | CH1: Bono | CI1: Gasto | CJ1: Nacionalidad
A2: CASA MATRIZ NUEVOS | B2: JUAN PABLO GONZALEZ ACUÑA | C2: 02-01-2025 12:13:45 | D2: 5884 | E2: LUIS ALEJANDRO REINOSO MEDINELLI | F2: 8133978 | G2: 3 | H2: MARCEL DUHAUT 2977 DPTO 501 | I2: 988993993 | L2: PROVIDENCIA | M2: 10/08/1967 | N2: areinoso@uc.cl | P2: STATION WAGON | Q2: VOLKSWAGEN | R2: T CROSS | S2: T-Cross 1.0 TSI AT Comfortline - 85 kW/116 CV | T2: BF33K311 | U2: AZUL NORUEGA | V2: AN-24-08-0075 | W2: 9BWBH6BF0S4003522 | X2: 9BWBH6BF0S4003522 | Y2: 9BWBH6BF0S4003522 | Z2: NUEVO Y SIN USO | AA2: 2025 | AB2: Facturada | AC2: 19842 | AD2: 09-01-2025 0:00:00 | AF2: Guía de Despacho: 1 - Factura Electrónica: 1838074 | AG2: 16812766 | AH2: 09-01-2025 0:00:00 | AJ2: 0 | AK2: SALON | AL2: 09-01-2025 0:00:00 | AM2: RETAIL | AN2: Peso | AP2: 0 | AQ2: 18058824 | AR2: -1470588 | AS2: -632059 | AT2: 15956176 | AU2: 16812766 | AV2: -856590 | AW2: -5.37 % | AX2: 0 | AY2: 921320 | AZ2: 921320 | BA2: 0 | BB2: 0 % | BC2: 0 | BD2: 0 | BE2: 0 | BF2: 0 | BG2: 0 % | BH2: 0 | BI2: 0 | BJ2: 0 | BK2: 0 | BL2: 0 % | BM2: 16588236 | BN2: 16877496 | BO2: 17734086 | BP2: -856590 | BQ2: -5.08 % | BR2: -856590 | BS2: -5.08 % | BT2: 0 | BU2: 0 | BV2: 19909170 | BW2: 0 | BX2: 921320 | BY2: 0 | BZ2: 19909169 | CA2: 16877496 | CB2: -856590 | CC2: -5.08 % | CE2: 0 | CG2: 0 | CH2: 0 | CI2: 0
A3: CASA MATRIZ NUEVOS | B3: RAIMUNDO GAZITUA SAAVEDRA | C3: 02-01-2025 18:09:17 | D3: 5886 | E3: NICOLLE CARLA CASAGRANDE ARO | F3: 17467115 | G3: K | H3: TIAHUANACO 1077 DPTO 408B | J3: 996998621 | L3: VITACURA | M3: 01/12/2024 | N3: NICOLLECASAGRANDE@YAHOO.ES | P3: STATION WAGON | Q3: VOLKSWAGEN | R3: T CROSS | S3: T-Cross 1.0 TSI AT Highline Sport - 85 kW/116 CV | T3: BF34K312 | U3: Gris Ascot/Negro | V3: AN-25-01-0002 | W3: 9BWBH6BF6S4051090 | X3: 9BWBH6BF6S4051090 | Z3: NUEVO Y SIN USO | AA3: 2025 | AB3: Facturada | AC3: 19831 | AD3: 08-01-2025 0:00:00 | AF3: Guía de Despacho: 1 - Factura Electrónica: 1842454 | AG3: 18024933 | AH3: 07-02-2025 0:00:00 | AJ3: 0 | AL3: 07-02-2025 0:00:00 | AM3: [OTRO] | AN3: Peso | AP3: 0 | AQ3: 19319328 | AR3: -2605042 | AS3: -621849 | AT3: 16092437 | AU3: 18024933 | AV3: -1932496 | AW3: -12.01 % | AX3: 0 | AY3: 924879 | AZ3: 924879 | BA3: 0 | BB3: 0 % | BC3: 0 | BD3: 0 | BE3: 0 | BF3: 0 | BG3: 0 % | BH3: 0 | BI3: 0 | BJ3: 0 | BK3: 0 | BL3: 0 % | BM3: 16714286 | BN3: 17017316 | BO3: 18949812 | BP3: -1932496 | BQ3: -11.36 % | BR3: -1932496 | BS3: -11.36 % | BT3: 0 | BU3: 0 | BV3: 20074879 | BW3: 0 | BX3: 924879 | BY3: 0 | BZ3: 20074879 | CA3: 17017316 | CB3: -1932496 | CC3: -11.36 % | CE3: 0 | CG3: 0 | CH3: 0 | CI3: 0
A4: CASA MATRIZ NUEVOS | B4: JUAN PABLO GONZALEZ ACUÑA | C4: 06-01-2025 11:01:03 | D4: 5891 | E4: JENNY PAOLA LLEWELLYN ROVEGNO | F4: 10265209 | G4: 6 | H4: DOCTOR ROBERTO DEL RIO 1771 DPTO 401 | I4: 997991954 | L4: PROVIDENCIA | M4: 07/05/1972 | N4: jenny.llewelyn@gmail.com | P4: STATION WAGON 01 | Q4: VOLKSWAGEN | R4: FAMILIA 1 | S4: Taos TSI AT Highline 110KW/150CV | T4: CQ17LY11 | U4: GRIS INDIO METALIZADO | V4: AN-25-01-0003 | W4: 8AWBJ6B28RA828840 | X4: 8AWBJ6B28RA828840 | Z4: NUEVO Y SIN USO | AA4: 2025 | AB4: Facturada | AC4: 19823 | AD4: 06-01-2025 0:00:00 | AF4: Guía de Despacho: 1 - Factura Electrónica: 1842389 | AG4: 22640647 | AH4: 06-01-2025 0:00:00 | AJ4: 0 | AK4: SALON | AL4: 06-01-2025 0:00:00 | AM4: RETAIL | AN4: Peso | AO4: JVGP11 | AP4: 0 | AQ4: 24529412 | AR4: -3571429 | AS4: -981176 | AT4: 19976807 | AU4: 22640647 | AV4: -2663840 | AW4: -13.33 % | AX4: 0 | AY4: 1186750 | AZ4: 1186750 | BA4: 0 | BB4: 0 % | BC4: 0 | BD4: 0 | BE4: 0 | BF4: 0 | BG4: 0 % | BH4: 0 | BI4: 0 | BJ4: 0 | BK4: 0 | BL4: 0 % | BM4: 20957983 | BN4: 21163557 | BO4: 23827397 | BP4: -2663840 | BQ4: -12.59 % | BR4: -2663840 | BS4: -12.59 % | BT4: 0 | BU4: 11000000 | BV4: 13959150 | BW4: 0 | BX4: 1186750 | BY4: 0 | BZ4: 24959150 | CA4: 21163557 | CB4: -2663840 | CC4: -12.59 % | CE4: 0 | CG4: 0 | CH4: 0 | CI4: 0
A5: CASA MATRIZ NUEVOS | B5: ROBERTO LOBOS GUTIERREZ | C5: 06-01-2025 16:34:36 | D5: 5892 | E5: NADIM HASAN MASRI CIOCCA | F5: 10324690 | G5: 3 | H5: SIMON BOLIVAR 6242 PARCELA LOTE H EL NOVICIADO | J5: 956578629 | L5: PUDAHUEL | M5: 01/01/1900 | N5: NADIM.MASRI@BICE.CL | P5: STATION WAGON | Q5: VOLKSWAGEN | R5: FAMILIA 1 | S5: Nivus 1.0 TSI AT Comfortline 85KW/116CV 5 p | T5: CH13K316 | U5: GRIS PLATINO | V5: AN-24-10-0012 | W5: 9BWCH6CH5RP054012 | X5: 9BWCH6CH5RP054012 | Z5: NUEVO Y SIN USO | AA5: 2025 | AB5: Facturada | AC5: 19846 | AD5: 10-01-2025 0:00:00 | AF5: Guía de Despacho: 0 - Factura Electrónica: 1839314 - Nota de Crédito Electrónica: 3061669 | AG5: 15342740 | AH5: 09-02-2025 0:00:00 | AJ5: 0 | AK5: SALON | AL5: 09-02-2025 0:00:00 | AM5: CC | AN5: Peso | AP5: 71 | AQ5: 0 | AR5: -3109244 | AS5: -613445 | AT5: 13831933 | AU5: 13494000 | AV5: 337933 | AW5: 2.44 % | AX5: 0 | AY5: 717696 | AZ5: 717696 | BA5: 0 | BB5: 0 % | BC5: 0 | BD5: 0 | BE5: 0 | BF5: 0 | BG5: 0 % | BH5: 0 | BI5: 0 | BJ5: 0 | BK5: 0 | BL5: 0 % | BM5: -3109244 | BN5: 14549629 | BO5: 14216696 | BP5: 332933 | BQ5: 2.29 % | BR5: 332933 | BS5: 2.29 % | BT5: 0 | BU5: 0 | BV5: 17177696 | BW5: 0 | BX5: 717696 | BY5: 0 | BZ5: 17177696 | CA5: 14549629 | CB5: 332933 | CC5: 2.29 % | CE5: 0 | CG5: 0 | CH5: 2200000 | CI5: 5000
A6: CASA MATRIZ NUEVOS | B6: JUAN PABLO GONZALEZ ACUÑA | C6: 07-01-2025 10:13:45 | D6: 5894 | E6: DANDILION INSPECCION LIMITADA | F6: 76296875 | G6: 4 | H6: LAREDO 8357 OF 21 | I6: 954061070 | L6: LAS CONDES | N6: eruz@dandilion.cl | P6: CAMIONETA | Q6: VOLKSWAGEN | R6: SAVEIRO | S6: Saveiro 1.6 MT Cabina Simple Lite | T6: 5URTT412 | U6: BLANCO CANDY | V6: AN-24-11-0082 | W6: 9BWKL45UXSP007119 | X6: 9BWKL45UXSP007119 | Y6: 9BWKL45UXSP007119 | Z6: NUEVO Y SIN USO | AA6: 2025 | AB6: Facturada | AC6: 19857 | AD6: 14-01-2025 0:00:00 | AF6: Guía de Despacho: 1 - Factura Electrónica: 1840728 - Nota de Crédito Electrónica: 3062075 | AG6: 11047360 | AH6: 14-01-2025 0:00:00 | AJ6: 0 | AK6: SALON | AL6: 14-01-2025 0:00:00 | AM6: RETAIL | AN6: Peso | AP6: 0 | AQ6: 12640000 | AR6: -2050000 | AS6: -814000 | AT6: 9776000 | AU6: 9629293 | AV6: 146707 | AW6: 1.5 % | AX6: 0 | AY6: 381560 | AZ6: 381560 | BA6: 0 | BB6: 0 % | BC6: 0 | BD6: 0 | BE6: 0 | BF6: 0 | BG6: 0 % | BH6: 0 | BI6: 0 | BJ6: 0 | BK6: 0 | BL6: 0 % | BM6: 10590000 | BN6: 10157560 | BO6: 10010853 | BP6: 146707 | BQ6: 1.44 % | BR6: 146707 | BS6: 1.44 % | BT6: 0 | BU6: 0 | BV6: 12015000 | BW6: 0 | BX6: 381560 | BY6: 0 | BZ6: 12015000 | CA6: 10157560 | CB6: 146707 | CC6: 1.44 % | CE6: 0 | CG6: 0 | CH6: 1687500 | CI6: 0
A7: CASA MATRIZ NUEVOS | B7: JUAN PABLO GONZALEZ ACUÑA | C7: 07-01-2025 10:15:54 | D7: 5895 | E7: DANDILION INSPECCION LIMITADA | F7: 76296875 | G7: 4 | H7: LAREDO 8357 OF 21 | I7: 954061070 | L7: LAS CONDES | N7: eruz@dandilion.cl | P7: CAMIONETA | Q7: VOLKSWAGEN | R7: SAVEIRO | S7: Saveiro 1.6 MT Cabina Simple Lite | T7: 5URTT412 | U7: BLANCO CANDY | V7: AN-24-11-0060 | W7: 9BWKL45U9SP015874 | X7: 9BWKL45U9SP015874 | Y7: 9BWKL45U9SP015874 | Z7: NUEVO Y SIN USO | AA7: 2025 | AB7: Facturada | AC7: 19858 | AD7: 14-01-2025 0:00:00 | AF7: Guía de Despacho: 1 - Factura Electrónica: 1840658 - Nota de Crédito Electrónica: 3062073 | AG7: 11047360 | AH7: 14-01-2025 0:00:00 | AJ7: 0 | AK7: SALON | AL7: 14-01-2025 0:00:00 | AM7: FLOTA | AN7: Peso | AP7: 0 | AQ7: 12640000 | AR7: -2050000 | AS7: 0 | AT7: 10590000 | AU7: 9629293 | AV7: 960707 | AW7: 9.07 % | AX7: 0 | AY7: 381560 | AZ7: 381560 | BA7: 0 | BB7: 0 % | BC7: 0 | BD7: 0 | BE7: 0 | BF7: 0 | BG7: 0 % | BH7: 0 | BI7: 0 | BJ7: 0 | BK7: 0 | BL7: 0 % | BM7: 10590000 | BN7: 10971560 | BO7: 10010853 | BP7: 960707 | BQ7: 8.76 % | BR7: 960707 | BS7: 8.76 % | BT7: 0 | BU7: 0 | BV7: 14657464 | BW7: -1673804 | BX7: 381560 | BY7: 0 | BZ7: 12983660 | CA7: 10971560 | CB7: 960707 | CC7: 8.76 % | CE7: 0 | CG7: 0 | CH7: 1687500 | CI7: 0
A8: CASA MATRIZ NUEVOS | B8: JUAN PABLO GONZALEZ ACUÑA | C8: 07-01-2025 11:16:30 | D8: 5896 | E8: ANDREA BETSABE REQUENA ORTIZ | F8: 17833721 | G8: 1 | H8: PASAJE SANTA RAQUEL 0501 | I8: 976670831 | L8: PUENTE ALTO | M8: 19/02/1991 | N8: requenaortiz@gmail.com | P8: AUTOMOVIL | Q8: VOLKSWAGEN | R8: POLO | S8: Polo 1.6 MT Comfortline - 81 kW/101 CV | T8: 782024 | U8: BLANCO CANDY | V8: AN-25-01-0004 | W8: 9BWAL5BZ5ST639230 | X8: 9BWAL5BZ5ST639230 | Y8: 9BWAL5BZ5ST639230 | Z8: NUEVO Y SIN USO | AA8: 2025 | AB8: Facturada | AC8: 19841 | AD8: 09-01-2025 0:00:00 | AF8: Guía de Despacho: 1 - Factura Electrónica: 1842500 | AG8: 13320731 | AH8: 08-02-2025 0:00:00 | AJ8: 0 | AK8: SALON | AL8: 08-02-2025 0:00:00 | AM8: RETAIL | AN8: Peso | AP8: 0 | AQ8: 14277311 | AR8: -2100840 | AS8: -428571 | AT8: 11747899 | AU8: 13320731 | AV8: -1572832 | AW8: -13.39 % | AX8: 0 | AY8: 564820 | AZ8: 564820 | BA8: 0 | BB8: 0 % | BC8: 0 | BD8: 0 | BE8: 0 | BF8: 0 | BG8: 0 % | BH8: 0 | BI8: 0 | BJ8: 0 | BK8: 0 | BL8: 0 % | BM8: 12176471 | BN8: 12312719 | BO8: 13885551 | BP8: -1572832 | BQ8: -12.77 % | BR8: -1572832 | BS8: -12.77 % | BT8: 0 | BU8: 0 | BV8: 14544820 | BW8: 0 | BX8: 564820 | BY8: 0 | BZ8: 14544820 | CA8: 12312719 | CB8: -1572832 | CC8: -12.77 % | CE8: 0 | CG8: 0 | CH8: 0 | CI8: 0
A9: CASA MATRIZ NUEVOS | B9: JUAN PABLO GONZALEZ ACUÑA | C9: 08-01-2025 11:12:40 | D9: 5898 | E9: CONSULTORA Y GESTION DEXTRA LIMITADA | F9: 76193982 | G9: 3 | H9: BADAJOZ 100 OF 1003 PISO 10 | I9: 977092999 | L9: LAS CONDES | N9: roberto.alvarez@dextraltda.cl | P9: CAMIONETA | Q9: VOLKSWAGEN | R9: SAVEIRO | S9: Saveiro 1.6 MT Cabina Simple Lite | T9: 5URTT412 | U9: BLANCO CANDY | V9: AN-24-11-0062 | W9: 9BWKL45UXSP033087 | X9: 9BWKL45UXSP033087 | Y9: 9BWKL45UXSP033087 | Z9: NUEVO Y SIN USO | AA9: 2025 | AB9: Facturada | AC9: 19852 | AD9: 13-01-2025 0:00:00 | AF9: Guía de Despacho: 1 - Factura Electrónica: 1840743 - Nota de Crédito Electrónica: 3062485 | AG9: 11047360 | AH9: 12-02-2025 0:00:00 | AJ9: 0 | AK9: SALON | AL9: 12-02-2025 0:00:00 | AM9: RETAIL | AN9: Peso | AP9: 0 | AQ9: 12640000 | AR9: -2050000 | AS9: -814000 | AT9: 9776000 | AU9: 9797360 | AV9: -21360 | AW9: -0.22 % | AX9: 0 | AY9: 299330 | AZ9: 299330 | BA9: 0 | BB9: 0 % | BC9: 0 | BD9: 0 | BE9: 0 | BF9: 0 | BG9: 0 % | BH9: 0 | BI9: 0 | BJ9: 0 | BK9: 0 | BL9: 0 % | BM9: 10590000 | BN9: 10075330 | BO9: 10096690 | BP9: -21360 | BQ9: -0.21 % | BR9: -21360 | BS9: -0.21 % | BT9: 0 | BU9: 0 | BV9: 11932770 | BW9: 0 | BX9: 299330 | BY9: 0 | BZ9: 11932770 | CA9: 10075330 | CB9: -21360 | CC9: -0.21 % | CE9: 0 | CG9: 0 | CH9: 1487500 | CI9: 0
A10: CASA MATRIZ NUEVOS | B10: CLAUDIO ROBLEZ GALAZ | C10: 08-01-2025 13:23:44 | D10: 5899 | E10: MARIA JOSE VIELMA ZANDOVAL | F10: 20465426 | G10: 3 | H10: CAMINO LAS CUMBRE 6838 CASA 36 | I10: 950270639 | J10: 950270639 | L10: LA FLORIDA | M10: 02/03/2000 | N10: ALAN.MARTINEZ.ANTIL@GMAIL.COM | P10: AUTOMOVIL | Q10: VOLKSWAGEN | R10: POLO | S10: POLO 1.0 TSI HIGHLINE AT | T10: BZ33D311 | U10: GRIS PLATINO | V10: AN-24-06-0015 | W10: 9BWAH5BZ8ST602190 | X10: 9BWAH5BZ8ST602190 | Y10: 9BWAH5BZ8ST602190 | Z10: NUEVO Y SIN USO | AA10: 2024 | AB10: Facturada | AC10: 19853 | AD10: 13-01-2025 0:00:00 | AF10: Guía de Despacho: 1 - Factura Electrónica: 1790936 | AG10: 14537722 | AH10: 13-01-2025 0:00:00 | AJ10: 0 | AK10: AMIGO | AL10: 13-01-2025 0:00:00 | AM10: RETAIL | AN10: Peso | AP10: 224 | AQ10: 15957983 | AR10: -2923773 | AS10: 0 | AT10: 13034210 | AU10: 14537722 | AV10: -1503512 | AW10: -11.54 % | AX10: 0 | AY10: 489290 | AZ10: 489290 | BA10: 0 | BB10: 0 % | BC10: 0 | BD10: 0 | BE10: 0 | BF10: 0 | BG10: 0 % | BH10: 0 | BI10: 0 | BJ10: 0 | BK10: 0 | BL10: 0 % | BM10: 13034210 | BN10: 13523500 | BO10: 15027012 | BP10: -1503512 | BQ10: -11.12 % | BR10: -1503512 | BS10: -11.12 % | BT10: 0 | BU10: 0 | BV10: 16000000 | BW10: 0 | BX10: 489290 | BY10: 0 | BZ10: 16000000 | CA10: 13523500 | CB10: -1503512 | CC10: -11.12 % | CE10: 0 | CG10: 0 | CH10: 0 | CI10: 0
A11: CASA MATRIZ NUEVOS | B11: ROBERTO LOBOS GUTIERREZ | C11: 08-01-2025 15:37:55 | D11: 5900 | E11: SOCIEDAD COMERCIAL ELECTROPOWER S.A. | F11: 76257832 | G11: 8 | H11: CARRETERA GENERAL SAN MARTIN 8250 BODEGA 29B | J11: 998185621 | L11: QUILICURA | M11: 01/01/1900 | N11: cosorio@electropower.cl | P11: CAMIONETA | Q11: VOLKSWAGEN | R11: SAVEIRO | S11: Saveiro 1.6 MT Cabina Simple Lite | T11: 5URTT412 | U11: BLANCO CANDY | V11: AN-24-11-0057 | W11: 9BWKL45U7SP024783 | X11: 9BWKL45U7SP024783 | Y11: 9BWKL45U7SP024783 | Z11: NUEVO Y SIN USO | AA11: 2025 | AB11: Facturada | AC11: 19843 | AD11: 10-01-2025 0:00:00 | AF11: Guía de Despacho: 1 - Factura Electrónica: 1840741 - Nota de Crédito Electrónica: 3062484 | AG11: 11047360 | AH11: 10-01-2025 0:00:00 | AJ11: 0 | AK11: SITIO WEB | AL11: 10-01-2025 0:00:00 | AM11: CC | AN11: Peso | AP11: 0 | AQ11: 12640000 | AR11: -1250000 | AS11: -574874 | AT11: 10815126 | AU11: 11047360 | AV11: -232234 | AW11: -2.15 % | AX11: 0 | AY11: 412733 | AZ11: 412733 | BA11: 0 | BB11: 0 % | BC11: 0 | BD11: 0 | BE11: 0 | BF11: 0 | BG11: 0 % | BH11: 0 | BI11: 0 | BJ11: 0 | BK11: 0 | BL11: 0 % | BM11: 11390000 | BN11: 11227859 | BO11: 11460093 | BP11: -232234 | BQ11: -2.07 % | BR11: -232234 | BS11: -2.07 % | BT11: 0 | BU11: 0 | BV11: 13282733 | BW11: 0 | BX11: 412733 | BY11: 0 | BZ11: 13282733 | CA11: 11227859 | CB11: -232234 | CC11: -2.07 % | CE11: 0 | CG11: 0 | CH11: 0 | CI11: 0
A12: CASA MATRIZ NUEVOS | B12: JUAN PABLO GONZALEZ ACUÑA | C12: 09-01-2025 15:45:12 | D12: 5905 | E12: DOBRA WALESKA LUSIC MORALES | F12: 16748913 | G12: 3 | H12: GENERAL JOFRE 202 DPTO 507 | I12: 957148023 | L12: SANTIAGO | M12: 02/03/1988 | N12: dobralusic@gmail.com | P12: STATION WAGON | Q12: VOLKSWAGEN | R12: T CROSS | S12: T-Cross 1.0 TSI AT Highline - 85 kW/116 CV | T12: BF34K311 | U12: BLANCO PURO | V12: AN-24-12-0032 | W12: 9BWBH6BF0S4053238 | X12: 9BWBH6BF0S4053238 | Y12: 9BWBH6BF0S4053238 | Z12: NUEVO Y SIN USO | AA12: 2025 | AB12: Facturada | AC12: 19859 | AD12: 14-01-2025 0:00:00 | AF12: Guía de Despacho: 1 - Factura Electrónica: 1841780 | AG12: 17651815 | AH12: 14-01-2025 0:00:00 | AJ12: 0 | AK12: SALON | AL12: 14-01-2025 0:00:00 | AM12: RETAIL | AN12: Peso | AP12: 26 | AQ12: 18899160 | AR12: -1218487 | AS12: -756303 | AT12: 16924370 | AU12: 17651815 | AV12: -727445 | AW12: -4.3 % | AX12: 0 | AY12: 973956 | AZ12: 973956 | BA12: 0 | BB12: 0 % | BC12: 0 | BD12: 0 | BE12: 0 | BF12: 0 | BG12: 0 % | BH12: 0 | BI12: 0 | BJ12: 0 | BK12: 0 | BL12: 0 % | BM12: 17680673 | BN12: 17898326 | BO12: 18625771 | BP12: -727445 | BQ12: -4.06 % | BR12: -727445 | BS12: -4.06 % | BT12: 0 | BU12: 0 | BV12: 21113956 | BW12: 0 | BX12: 973956 | BY12: 0 | BZ12: 21113956 | CA12: 17898326 | CB12: -727445 | CC12: -4.06 % | CE12: 0 | CG12: 0 | CH12: 0 | CI12: 0
A13: CASA MATRIZ NUEVOS | B13: ROBERTO LOBOS GUTIERREZ | C13: 09-01-2025 17:40:31 | D13: 5906 | E13: MAQUINARIAS FABIAN GALLARDO, E.I.R.L | F13: 76096975 | G13: 3 | H13: COSTANERA DEL ESTRECHO 01934 EL GOLF | J13: 56977082136 | L13: PUNTA ARENAS | M13: 01/01/1900 | N13: Fgallardo@fgmaq.cl | P13: CAMIONETA | Q13: VOLKSWAGEN | R13: SAVEIRO | S13: SAVEIRO 1.6 MT CABINA SIMPLE | T13: 5URTT413 | U13: PLATA SIRIUS | V13: AN-24-11-0083 | W13: 9BWKL45U5SP024555 | X13: 9BWKL45U5SP024555 | Y13: 9BWKL45U5SP024555 | Z13: NUEVO Y SIN USO | AA13: 2025 | AB13: Facturada | AC13: 19895 | AD13: 22-01-2025 0:00:00 | AF13: Guía de Despacho: 1 - Factura Electrónica: 1840962 - Nota de Crédito Electrónica: 3062488 | AG13: 12358360 | AH13: 21-02-2025 0:00:00 | AJ13: 0 | AK13: WEB CONCESIONARIO | AL13: 21-02-2025 0:00:00 | AM13: CI | AN13: Peso | AP13: 0 | AQ13: 0 | AR13: -2450000 | AS13: -597563 | AT13: 11092437 | AU13: 10708360 | AV13: 384077 | AW13: 3.46 % | AX13: 0 | AY13: 338823 | AZ13: 338823 | BA13: 0 | BB13: 0 % | BC13: 0 | BD13: 0 | BE13: 0 | BF13: 0 | BG13: 0 % | BH13: 0 | BI13: 0 | BJ13: 0 | BK13: 0 | BL13: 0 % | BM13: -2450000 | BN13: 11431260 | BO13: 11047183 | BP13: 384077 | BQ13: 3.36 % | BR13: 384077 | BS13: 3.36 % | BT13: 0 | BU13: 0 | BV13: 13538823 | BW13: 0 | BX13: 338823 | BY13: 0 | BZ13: 13538823 | CA13: 11431260 | CB13: 384077 | CC13: 3.36 % | CE13: 0 | CG13: 0 | CH13: 1963500 | CI13: 0
A14: CASA MATRIZ NUEVOS | B14: JUAN PABLO GONZALEZ ACUÑA | C14: 10-01-2025 11:50:25 | D14: 5907 | E14: PATRICIA EBEL FERNANDEZ | F14: 10888067 | G14: 8 | H14: COSTANERA SUR 12033 DPTO 504 | I14: 968477239 | L14: VITACURA | M14: 19/11/1969 | N14: pebelf@gmail.com | P14: STATION WAGON 01 | Q14: VOLKSWAGEN | R14: FAMILIA 1 | S14: NUEVO TIGUAN TSI AT R-LINE 220HP 2.0 | T14: BJ25TT11 | U14: GRIS PLATINO | V14: AN-24-10-0051 | W14: 3VVDE65N8RM149262 | X14: 3VVDE65N8RM149262 | Y14: 3VVDE65N8RM149262 | Z14: NUEVO Y SIN USO | AA14: 2025 | AB14: Facturada | AC14: 19845 | AD14: 10-01-2025 0:00:00 | AF14: Guía de Despacho: 1 - Factura Electrónica: 1839727 - Nota de Crédito Electrónica: 3062523 | AG14: 30123832 | AH14: 10-01-2025 0:00:00 | AJ14: 0 | AK14: SALON | AL14: 10-01-2025 0:00:00 | AM14: RETAIL | AN14: Peso | AO14: JBPP80 | AP14: 0 | AQ14: 34865546 | AR14: -1680672 | AS14: -831933 | AT14: 32352941 | AU14: 28443160 | AV14: 3909781 | AW14: 12.08 % | AX14: 0 | AY14: 2240615 | AZ14: 2240615 | BA14: 0 | BB14: 0 % | BC14: 0 | BD14: 0 | BE14: 0 | BF14: 0 | BG14: 0 % | BH14: 0 | BI14: 0 | BJ14: 0 | BK14: 0 | BL14: 0 % | BM14: 33184874 | BN14: 34593556 | BO14: 30683775 | BP14: 3909781 | BQ14: 11.3 % | BR14: 3909781 | BS14: 11.3 % | BT14: 0 | BU14: 29000000 | BV14: 11740615 | BW14: 0 | BX14: 2240615 | BY14: 0 | BZ14: 40740615 | CA14: 34593556 | CB14: 3909781 | CC14: 11.3 % | CE14: 0 | CG14: 0 | CH14: 2000000 | CI14: 0
A15: CASA MATRIZ NUEVOS | B15: ROBERTO LOBOS GUTIERREZ | C15: 10-01-2025 15:46:14 | D15: 5913 | E15: FRANCISCO JAVIER URETA ESTRADA | F15: 17408406 | G15: 8 | H15: LAS VERBENAS 8485 DEPTO 713 B | J15: 984295679 | L15: LAS CONDES | M15: 28/05/1990 | N15: F.URETA.ES@GMAIL.COM | P15: STATION WAGON 01 | Q15: VOLKSWAGEN | R15: FAMILIA 1 | S15: Taos TSI AT Highline 110KW/150CV | T15: CQ17LY11 | U15: BLANCO PURO | V15: AN-25-01-0011 | W15: 8AWBJ6B25RA840847 | X15: 8AWBJ6B25RA840847 | Y15: 8AWBJ6B25RA840847 | Z15: NUEVO Y SIN USO | AA15: 2025 | AB15: Parcial Facturada | AC15: 19908 | AD15: 24-01-2025 0:00:00 | AF15: Guía de Despacho: 1 - Factura Electrónica: 1864513 | AG15: 22640647 | AH15: 23-02-2025 0:00:00 | AJ15: 0 | AK15: SALON | AL15: 23-02-2025 0:00:00 | AM15: CC | AN15: Peso | AO15: SZRZ28 | AP15: -6 | AQ15: 24529412 | AR15: -3571429 | AS15: -840336 | AT15: 20117647 | AU15: 22640647 | AV15: -2523000 | AW15: -12.54 % | AX15: 0 | AY15: 1196428 | AZ15: 1196428 | BA15: 0 | BB15: 0 % | BC15: 73920 | BD15: 294118 | BE15: 0 | BF15: 0 | BG15: 0 % | BH15: 0 | BI15: 0 | BJ15: 0 | BK15: 0 | BL15: 0 % | BM15: 20957983 | BN15: 21608193 | BO15: 23837075 | BP15: -2228882 | BQ15: -10.31 % | BR15: -2228882 | BS15: -10.31 % | BT15: 0 | BU15: 21557299 | BV15: 17178644 | BW15: -13249515 | BX15: 1196428 | BY15: 294118 | BZ15: 25486428 | CA15: 21608193 | CB15: -2228882 | CC15: -10.31 % | CE15: 0 | CG15: 0 | CH15: 0 | CI15: 0
A16: CASA MATRIZ NUEVOS | B16: ROBERTO LOBOS GUTIERREZ | C16: 11-01-2025 11:47:26 | D16: 5914 | E16: MARIA DE LOS ANGELES RENARD MERINO | F16: 8966208 | G16: 7 | H16: GENERAL BLANCHE 10226 | J16: 998273729 | L16: LAS CONDES | M16: 01/01/1900 | N16: MRENARD@YUKEN.CL | P16: STATION WAGON | Q16: VOLKSWAGEN | R16: FAMILIA 1 | S16: Nivus 1.0 TSI AT Comfortline 85KW/116CV 5 p | T16: CH13K311 | U16: BLANCO CANDY | V16: AN-24-03-0040 | W16: 9BWCH6CH3PP006182 | X16: 9BWCH6CH3PP006182 | Y16: 9BWCH6CH3PP006182 | Z16: NUEVO Y SIN USO | AA16: 2024 | AB16: Facturada | AC16: 19860 | AD16: 14-01-2025 0:00:00 | AF16: Guía de Despacho Electrónica: 1 - Factura Electrónica: 1788757 - Nota de Crédito Electrónica: 3058060 | AG16: 15695160 | AH16: 14-01-2025 0:00:00 | AJ16: 0 | AK16: SALON | AL16: 14-01-2025 0:00:00 | AM16: CC | AN16: Peso | AP16: 0 | AQ16: 17134454 | AR16: -3697479 | AS16: 0 | AT16: 13436975 | AU16: 15695160 | AV16: -2258185 | AW16: -16.81 % | AX16: 0 | AY16: 491389 | AZ16: 491389 | BA16: 0 | BB16: 0 % | BC16: 0 | BD16: 0 | BE16: 0 | BF16: 0 | BG16: 0 % | BH16: 0 | BI16: 0 | BJ16: 0 | BK16: 0 | BL16: 0 % | BM16: 13436975 | BN16: 13928364 | BO16: 16186549 | BP16: -2258185 | BQ16: -16.21 % | BR16: -2258185 | BS16: -16.21 % | BT16: 0 | BU16: 0 | BV16: 16481389 | BW16: 0 | BX16: 491389 | BY16: 0 | BZ16: 16481389 | CA16: 13928364 | CB16: -2258185 | CC16: -16.21 % | CE16: 0 | CG16: 0 | CH16: 0 | CI16: 0
A17: CASA MATRIZ NUEVOS | B17: JUAN PABLO GONZALEZ ACUÑA | C17: 13-01-2025 10:23:49 | D17: 5917 | E17: ENRIQUE EDUARDO LATOJA OVIEDO | F17: 7918183 | G17: 8 | H17: JANUARIO ESPINOZA 7205-A | I17: 998213308 | L17: LA REINA | M17: 11/06/1959 | N17: elatoja@entel.cl | P17: STATION WAGON 01 | Q17: VOLKSWAGEN | R17: FAMILIA 1 | S17: NUEVO TIGUAN TSI AT COMFORTLINE 150HP | T17: BJ23N611 | U17: PLATA PIRITA | V17: AN-25-01-0008 | W17: 3VVHP65N7RM219894 | X17: 3VVHP65N7RM219894 | Z17: NUEVO Y SIN USO | AA17: 2025 | AB17: Facturada | AC17: 19861 | AD17: 14-01-2025 0:00:00 | AF17: Guía de Despacho: 1 - Factura Electrónica: 1864398 | AG17: 23804093 | AH17: 14-01-2025 0:00:00 | AJ17: 0 | AK17: SALON | AL17: 14-01-2025 0:00:00 | AM17: RETAIL | AN17: Peso | AP17: 0 | AQ17: 25789916 | AR17: -2436975 | AS17: -773697 | AT17: 22579244 | AU17: 23804093 | AV17: -1224849 | AW17: -5.42 % | AX17: 0 | AY17: 1581111 | AZ17: 1581111 | BA17: 0 | BB17: 0 % | BC17: 0 | BD17: 0 | BE17: 0 | BF17: 0 | BG17: 0 % | BH17: 0 | BI17: 0 | BJ17: 0 | BK17: 0 | BL17: 0 % | BM17: 23352941 | BN17: 24160355 | BO17: 25385204 | BP17: -1224849 | BQ17: -5.07 % | BR17: -1224849 | BS17: -5.07 % | BT17: 0 | BU17: 0 | BV17: 28450411 | BW17: 0 | BX17: 1581111 | BY17: 0 | BZ17: 28450411 | CA17: 24160355 | CB17: -1224849 | CC17: -5.07 % | CE17: 0 | CG17: 0 | CH17: 0 | CI17: 0
A18: CASA MATRIZ NUEVOS | B18: JUAN PABLO GONZALEZ ACUÑA | C18: 13-01-2025 17:13:25 | D18: 5922 | E18: TRANSPORTES DONOSTIA LTDA | F18: 76101208 | G18: 8 | H18: LOS OLIVOS 1253, PARQUE IND. ENEA, PUDAHUEL | J18: 998175879 | K18: 998175879 | L18: PUDAHUEL | M18: 12/11/2000 | N18: fernanda.iturriaga@proingas.cl | P18: CAMIONETA | Q18: VOLKSWAGEN | R18: SAVEIRO | S18: Saveiro 1.6 MT Cabina Doble Lite | T18: 5UKWT412 | U18: BLANCO PURO | V18: AN-24-10-0077 | W18: 9BWJL45UXSP024658 | X18: 9BWJL45UXSP024658 | Y18: 9BWJL45UXSP024658 | Z18: NUEVO Y SIN USO | AA18: 2025 | AB18: Facturada | AC18: 19856 | AD18: 14-01-2025 0:00:00 | AF18: Guía de Despacho: 1 - Factura Electrónica: 1840268 - Nota de Crédito Electrónica: 3062528 | AG18: 12096160 | AH18: 14-01-2025 0:00:00 | AJ18: 0 | AK18: SALON | AL18: 14-01-2025 0:00:00 | AM18: FLOTA | AN18: Peso | AP18: 0 | AQ18: 13840000 | AR18: -1350000 | AS18: 0 | AT18: 12490000 | AU18: 10746160 | AV18: 1743840 | AW18: 13.96 % | AX18: 0 | AY18: 441686 | AZ18: 441686 | BA18: 0 | BB18: 0 % | BC18: 0 | BD18: 0 | BE18: 0 | BF18: 0 | BG18: 0 % | BH18: 0 | BI18: 0 | BJ18: 0 | BK18: 0 | BL18: 0 % | BM18: 12490000 | BN18: 12931686 | BO18: 11187846 | BP18: 1743840 | BQ18: 13.49 % | BR18: 1743840 | BS18: 13.49 % | BT18: 0 | BU18: 0 | BV18: 15304786 | BW18: 0 | BX18: 441686 | BY18: 0 | BZ18: 15304786 | CA18: 12931686 | CB18: 1743840 | CC18: 13.49 % | CE18: 0 | CG18: 0 | CH18: 1606500 | CI18: 0
A19: CASA MATRIZ NUEVOS | B19: ROBERTO LOBOS GUTIERREZ | C19: 14-01-2025 14:19:05 | D19: 5926 | E19: COMERCIAL OXIPROTEX LTDA. | F19: 76937697 | G19: 6 | H19: FCO. BILBAO 1860 3 301 | I19: 64 2644300 | L19: OSORNO | M19: 01/01/2000 | N19: ABASTECIMIENTO@INTEGRA-CHILE.CL | P19: CAMIONETA | Q19: VOLKSWAGEN | R19: SAVEIRO | S19: Saveiro 1.6 MT Cabina Simple Lite | T19: 5URTT412 | U19: BLANCO CANDY | V19: AN-24-11-0061 | W19: 9BWKL45UXSP031761 | X19: 9BWKL45UXSP031761 | Y19: 9BWKL45UXSP031761 | Z19: NUEVO Y SIN USO | AA19: 2025 | AB19: Facturada | AC19: 19936 | AD19: 29-01-2025 0:00:00 | AF19: Guía de Despacho: 1 - Factura Electrónica: 1840823 - Nota de Crédito Electrónica: 3062529 | AG19: 11047360 | AH19: 28-02-2025 0:00:00 | AJ19: 0 | AK19: SALON | AL19: 28-02-2025 0:00:00 | AM19: CC | AN19: Peso | AP19: 0 | AQ19: 12640000 | AR19: -1295462 | AS19: 0 | AT19: 11344538 | AU19: 9797360 | AV19: 1547178 | AW19: 13.64 % | AX19: 0 | AY19: 0 | AZ19: 0 | BA19: 0 | BB19: 0 % | BC19: 0 | BD19: 0 | BE19: 0 | BF19: 0 | BG19: 0 % | BH19: 0 | BI19: 0 | BJ19: 0 | BK19: 0 | BL19: 0 % | BM19: 11344538 | BN19: 11344538 | BO19: 9797360 | BP19: 1547178 | BQ19: 13.64 % | BR19: 1547178 | BS19: 13.64 % | BT19: 0 | BU19: 0 | BV19: 13500000 | BW19: 0 | BX19: 0 | BY19: 0 | BZ19: 13500000 | CA19: 11344538 | CB19: 1547178 | CC19: 13.64 % | CE19: 0 | CG19: 0 | CH19: 1487500 | CI19: 0
A20: CASA MATRIZ NUEVOS | B20: ROBERTO LOBOS GUTIERREZ | C20: 14-01-2025 18:10:14 | D20: 5927 | E20: MOISES ENRIQUE NUÑEZ ROMO | F20: 8669391 | G20: 7 | H20: REVERENDO FRANCISCO ANABALON ROSALES 131 | J20: 972162219 | L20: MAIPU | M20: 01/01/1900 | N20: MNUNEZROMO@GMAIL.COM | P20: STATION WAGON | Q20: VOLKSWAGEN | R20: T CROSS | S20: T-Cross 1.0 TSI AT Comfortline - 85 kW/116 CV | T20: BF33K311 | U20: ROJO METALICO | V20: AN-24-08-0078 | W20: 9BWBH6BF1S4003030 | X20: 9BWBH6BF1S4003030 | Y20: 9BWBH6BF1S4003030 | Z20: NUEVO Y SIN USO | AA20: 2025 | AB20: Facturada | AC20: 19879 | AD20: 16-01-2025 0:00:00 | AF20: Guía de Despacho: 1 - Factura Electrónica: 1838075 | AG20: 16812766 | AH20: 15-02-2025 0:00:00 | AJ20: 0 | AK20: WEB CONCESIONARIO | AL20: 15-02-2025 0:00:00 | AM20: CI | AN20: Peso | AP20: 111 | AQ20: 18058824 | AR20: -2773109 | AS20: -621849 | AT20: 14663866 | AU20: 16812766 | AV20: -2148900 | AW20: -14.65 % | AX20: 0 | AY20: 764231 | AZ20: 764231 | BA20: 0 | BB20: 0 % | BC20: 0 | BD20: 0 | BE20: 0 | BF20: 0 | BG20: 0 % | BH20: 0 | BI20: 0 | BJ20: 0 | BK20: 0 | BL20: 0 % | BM20: 15285715 | BN20: 15428097 | BO20: 17576997 | BP20: -2148900 | BQ20: -13.93 % | BR20: -2148900 | BS20: -13.93 % | BT20: 0 | BU20: 0 | BV20: 18214231 | BW20: 0 | BX20: 764231 | BY20: 0 | BZ20: 18214232 | CA20: 15428097 | CB20: -2148900 | CC20: -13.93 % | CE20: 0 | CG20: 0 | CH20: 0 | CI20: 0
A21: CASA MATRIZ NUEVOS | B21: JUAN PABLO GONZALEZ ACUÑA | C21: 15-01-2025 12:52:36 | D21: 5931 | E21: PILAR DEL CARMEN RODRIGUEZ PEREZ | F21: 6506064 | G21: 7 | H21: AVDA LUIS PASTEUR 5626 DEPTO 402 | I21: 982594676 | L21: VITACURA | M21: 09/01/1959 | N21: pirope@gmail.com | P21: STATION WAGON 01 | Q21: VOLKSWAGEN | R21: FAMILIA 1 | S21: NUEVO TIGUAN TSI AT COMFORTLINE 150HP | T21: BJ23N611 | U21: GRIS PLATINO | V21: AN-25-01-0010 | W21: 3VVHP65N9RM207455 | X21: 3VVHP65N9RM207455 | Z21: NUEVO Y SIN USO | AA21: 2025 | AB21: Facturada | AC21: 19883 | AD21: 17-01-2025 0:00:00 | AF21: Guía de Despacho: 1 - Factura Electrónica: 1864440 | AG21: 23804093 | AH21: 17-01-2025 0:00:00 | AJ21: 0 | AK21: SALON | AL21: 17-01-2025 0:00:00 | AM21: RETAIL | AN21: Peso | AP21: 0 | AQ21: 25789916 | AR21: -2436975 | AS21: -504202 | AT21: 22848740 | AU21: 23804093 | AV21: -955353 | AW21: -4.18 % | AX21: 0 | AY21: 1592887 | AZ21: 1592887 | BA21: 0 | BB21: 0 % | BC21: 0 | BD21: 0 | BE21: 0 | BF21: 0 | BG21: 0 % | BH21: 0 | BI21: 0 | BJ21: 0 | BK21: 0 | BL21: 0 % | BM21: 23352941 | BN21: 24441627 | BO21: 25396980 | BP21: -955353 | BQ21: -3.91 % | BR21: -955353 | BS21: -3.91 % | BT21: 0 | BU21: 0 | BV21: 28782887 | BW21: 0 | BX21: 1592887 | BY21: 0 | BZ21: 28782888 | CA21: 24441627 | CB21: -955353 | CC21: -3.91 % | CE21: 0 | CG21: 0 | CH21: 0 | CI21: 0
A22: CASA MATRIZ NUEVOS | B22: JUAN PABLO GONZALEZ ACUÑA | C22: 16-01-2025 10:16:04 | D22: 5934 | E22: LIQUI MOLY CHILE S.A | F22: 86868900 | G22: 5 | H22: ELIODORO YAÑEZ 1727 | I22: 984188185 | L22: PROVIDENCIA | M22: 01/01/1900 | N22: info@liqui-moly.cl | P22: CAMIONETA | Q22: VOLKSWAGEN | R22: FAMILIA 1 | S22: SAVEIRO 1.6 MT CABINA DOBLE 81 kW/110 CV | T22: 5UKWT413 | U22: BLANCO CANDY | V22: AN-24-06-0030 | W22: 9BWJL45U1SP003018 | X22: 9BWJL45U1SP003018 | Y22: 9BWJL45U1SP003018 | Z22: NUEVO Y SIN USO | AA22: 2025 | AB22: Parcial Facturada | AC22: 19884 | AD22: 17-01-2025 0:00:00 | AF22: Guía de Despacho: 1 - Factura Electrónica: 1791013 - Nota de Crédito Electrónica: 3060477 - Nota de Crédito Electrónica: 3060548 | AG22: 13054340 | AH22: 17-01-2025 0:00:00 | AJ22: 0 | AK22: SALON | AL22: 17-01-2025 0:00:00 | AM22: FLOTA | AN22: Peso | AP22: 0 | AQ22: 15340000 | AR22: -1450000 | AS22: -920400 | AT22: 12969600 | AU22: 11854340 | AV22: 1115260 | AW22: 8.6 % | AX22: 0 | AY22: 485138 | AZ22: 485138 | BA22: 0 | BB22: 0 % | BC22: 0 | BD22: 0 | BE22: 0 | BF22: 0 | BG22: 0 % | BH22: 0 | BI22: 0 | BJ22: 0 | BK22: 0 | BL22: 0 % | BM22: 13890000 | BN22: 13454738 | BO22: 12339478 | BP22: 1115260 | BQ22: 8.29 % | BR22: 1115260 | BS22: 8.29 % | BT22: 0 | BU22: 0 | BV22: 15918962 | BW22: 0 | BX22: 485138 | BY22: 0 | BZ22: 15918962 | CA22: 13454738 | CB22: 1115260 | CC22: 8.29 % | CE22: 0 | CG22: 0 | CH22: 1428000 | CI22: 0
A23: CASA MATRIZ NUEVOS | B23: CLAUDIO ROBLEZ GALAZ | C23: 17-01-2025 14:40:20 | D23: 5937 | E23: TERESA INES DE LA CRUZ MILLAN KLUSSE | F23: 5388894 | G23: 1 | H23: SANTA RITA 498 | I23: 3565136/091318341 | L23: LA REINA | M23: 07/04/1951 | N23: tmillan@med.uchile.cl | P23: AUTOMOVIL | Q23: VOLKSWAGEN | R23: VIRTUS | S23: VIRTUS 1.0 TSI COMFORTLINE AT | T23: BZ43D311 | U23: GRIS PLATINO | V23: AN-23-12-0036 | W23: 9BWDH6BZ4RP012042 | X23: 9BWDH6BZ4RP012042 | Y23: 9BWDH6BZ4RP012042 | Z23: NUEVO Y SIN USO | AA23: 2024 | AB23: Facturada | AC23: 19888 | AD23: 20-01-2025 0:00:00 | AF23: Guía de Despacho: 1 - Factura Electrónica: 1753763 | AG23: 14445294 | AH23: 20-01-2025 0:00:00 | AJ23: 0 | AK23: AMIGO | AL23: 20-01-2025 0:00:00 | AM23: RETAIL | AN23: Peso | AO23: CJFV96 | AP23: 414 | AQ23: 15873950 | AR23: -4117647 | AS23: -274736 | AT23: 11481566 | AU23: 14445294 | AV23: -2963728 | AW23: -25.81 % | AX23: 0 | AY23: 326936 | AZ23: 326936 | BA23: 0 | BB23: 0 % | BC23: 0 | BD23: 0 | BE23: 0 | BF23: 0 | BG23: 0 % | BH23: 0 | BI23: 0 | BJ23: 0 | BK23: 0 | BL23: 0 % | BM23: 11756303 | BN23: 11808502 | BO23: 14772230 | BP23: -2963728 | BQ23: -25.1 % | BR23: -2963728 | BS23: -25.1 % | BT23: 0 | BU23: 2200000 | BV23: 11790000 | BW23: 0 | BX23: 326936 | BY23: 0 | BZ23: 13990000 | CA23: 11808502 | CB23: -2963728 | CC23: -25.1 % | CE23: 0 | CG23: 0 | CH23: 0 | CI23: 0
A24: CASA MATRIZ NUEVOS | B24: ROBERTO LOBOS GUTIERREZ | C24: 17-01-2025 17:31:36 | D24: 5938 | E24: SOCIEDAD COMERCIAL ELECTROPOWER S.A. | F24: 76257832 | G24: 8 | H24: CARRETERA GENERAL SAN MARTIN 8250 BODEGA 29B | J24: 998185621 | L24: QUILICURA | M24: 01/01/1900 | N24: cosorio@electropower.cl | P24: CAMIONETA | Q24: VOLKSWAGEN | R24: SAVEIRO | S24: Saveiro 1.6 MT Cabina Simple Lite | T24: 5URTT412 | U24: BLANCO CANDY | V24: AN-24-10-0032 | W24: 9BWKL45U2SP015005 | X24: 9BWKL45U2SP015005 | Y24: 9BWKL45U2SP015005 | Z24: NUEVO Y SIN USO | AA24: 2025 | AB24: Parcial Facturada | AC24: 19906 | AD24: 23-01-2025 0:00:00 | AF24: Guía de Despacho: 1 - Factura Electrónica: 1839691 - Nota de Crédito Electrónica: 3061194 - Nota de Débito Electrónica: 3906658 - Nota de Crédito Electrónica: 3062483 | AG24: 11047360 | AH24: 23-01-2025 0:00:00 | AJ24: 0 | AK24: SALON | AL24: 23-01-2025 0:00:00 | AM24: CC | AN24: Peso | AP24: 98 | AQ24: 12640000 | AR24: -1250000 | AS24: -758067 | AT24: 10631933 | AU24: 11047360 | AV24: -415427 | AW24: -3.91 % | AX24: 0 | AY24: 407238 | AZ24: 407238 | BA24: 0 | BB24: 0 % | BC24: 0 | BD24: 0 | BE24: 0 | BF24: 0 | BG24: 0 % | BH24: 0 | BI24: 0 | BJ24: 0 | BK24: 0 | BL24: 0 % | BM24: 11390000 | BN24: 11039171 | BO24: 11454598 | BP24: -415427 | BQ24: -3.76 % | BR24: -415427 | BS24: -3.76 % | BT24: 0 | BU24: 0 | BV24: 13059238 | BW24: 0 | BX24: 407238 | BY24: 0 | BZ24: 13059238 | CA24: 11039171 | CB24: -415427 | CC24: -3.76 % | CE24: 0 | CG24: 0 | CH24: 0 | CI24: 0
A25: CASA MATRIZ NUEVOS | B25: JUAN PABLO GONZALEZ ACUÑA | C25: 21-01-2025 15:24:14 | D25: 5946 | E25: INTELCLIMA LIMITADA | F25: 76431332 | G25: 1 | H25: FEDERICO ERRAZURIZ 1250 DPTO 31 EDIFICIO 6 | I25: 955290099 | L25: PUDAHUEL | N25: s.ramireztorres@hotmail.com | P25: CAMIONETA | Q25: VOLKSWAGEN | R25: SAVEIRO | S25: Saveiro 1.6 MT Cabina Doble Lite | T25: 5UKWT412 | U25: BLANCO CANDY | V25: AN-24-10-0057 | W25: 9BWJL45U7SP006599 | X25: 9BWJL45U7SP006599 | Y25: 9BWJL45U7SP006599 | Z25: NUEVO Y SIN USO | AA25: 2025 | AB25: Facturada | AC25: 19943 | AD25: 30-01-2025 0:00:00 | AF25: Guía de Despacho: 1 - Factura Electrónica: 1839953 - Nota de Crédito Electrónica: 3062524 | AG25: 12096160 | AH25: 01-03-2025 0:00:00 | AJ25: 0 | AK25: SALON | AL25: 01-03-2025 0:00:00 | AM25: FLOTA | AN25: Peso | AO25: PGSY19 | AP25: 98 | AQ25: 13840000 | AR25: -2150000 | AS25: -942101 | AT25: 10747899 | AU25: 10746160 | AV25: 1739 | AW25: 0.02 % | AX25: 0 | AY25: 328487 | AZ25: 328487 | BA25: 0 | BB25: 0 % | BC25: 0 | BD25: 0 | BE25: 0 | BF25: 0 | BG25: 0 % | BH25: 0 | BI25: 0 | BJ25: 0 | BK25: 0 | BL25: 0 % | BM25: 11690000 | BN25: 11076386 | BO25: 11074647 | BP25: 1739 | BQ25: 0.02 % | BR25: 1739 | BS25: 0.02 % | BT25: 0 | BU25: 9000000 | BV25: 10709913 | BW25: -6591426 | BX25: 328487 | BY25: 0 | BZ25: 13118487 | CA25: 11076386 | CB25: 1739 | CC25: 0.02 % | CE25: 0 | CG25: 0 | CH25: 1606500 | CI25: 0
A26: CASA MATRIZ NUEVOS | B26: JUAN PABLO GONZALEZ ACUÑA | C26: 21-01-2025 15:32:21 | D26: 5947 | E26: INTELCLIMA LIMITADA | F26: 76431332 | G26: 1 | H26: FEDERICO ERRAZURIZ 1250 DPTO 31 EDIFICIO 6 | I26: 955290099 | L26: PUDAHUEL | N26: s.ramireztorres@hotmail.com | P26: CAMIONETA | Q26: VOLKSWAGEN | R26: SAVEIRO | S26: Saveiro 1.6 MT Cabina Simple Lite | T26: 5URTT412 | U26: BLANCO CANDY | V26: AN-25-01-0028 | W26: 9BWKL45U3SP047879 | X26: 9BWKL45U3SP047879 | Y26: 9BWKL45U3SP047879 | Z26: NUEVO Y SIN USO | AA26: 2025 | AB26: Facturada | AC26: 19944 | AD26: 30-01-2025 0:00:00 | AF26: Guía de Despacho: 1 - Factura Electrónica: 1864567 - Nota de Crédito Electrónica: 3063712 | AG26: 11287520 | AH26: 01-03-2025 0:00:00 | AJ26: 0 | AK26: SALON | AL26: 01-03-2025 0:00:00 | AM26: FLOTA | AN26: Peso | AP26: 8 | AQ26: 12640000 | AR26: -2050000 | AS26: -934538 | AT26: 9655462 | AU26: 11287520 | AV26: -1632058 | AW26: -16.9 % | AX26: 0 | AY26: 295713 | AZ26: 295713 | BA26: 0 | BB26: 0 % | BC26: 0 | BD26: 0 | BE26: 0 | BF26: 0 | BG26: 0 % | BH26: 0 | BI26: 0 | BJ26: 0 | BK26: 0 | BL26: 0 % | BM26: 10590000 | BN26: 9951175 | BO26: 11583233 | BP26: -1632058 | BQ26: -16.4 % | BR26: -1632058 | BS26: -16.4 % | BT26: 0 | BU26: 0 | BV26: 11785713 | BW26: 0 | BX26: 295713 | BY26: 0 | BZ26: 11785713 | CA26: 9951175 | CB26: -1632058 | CC26: -16.4 % | CE26: 0 | CG26: 0 | CH26: 0 | CI26: 0
A27: CASA MATRIZ NUEVOS | B27: JUAN PABLO GONZALEZ ACUÑA | C27: 21-01-2025 15:51:21 | D27: 5948 | E27: INTELCLIMA LIMITADA | F27: 76431332 | G27: 1 | H27: FEDERICO ERRAZURIZ 1250 DPTO 31 EDIFICIO 6 | I27: 955290099 | L27: PUDAHUEL | N27: s.ramireztorres@hotmail.com | P27: CAMIONETA | Q27: VOLKSWAGEN | R27: SAVEIRO | S27: Saveiro 1.6 MT Cabina Simple Lite | T27: 5URTT412 | U27: BLANCO CANDY | V27: AN-25-01-0026 | W27: 9BWKL45U1SP048416 | X27: 9BWKL45U1SP048416 | Y27: 9BWKL45U1SP048416 | Z27: NUEVO Y SIN USO | AA27: 2025 | AB27: Facturada | AC27: 19945 | AD27: 30-01-2025 0:00:00 | AF27: Guía de Despacho: 1 - Factura Electrónica: 1864566 - Nota de Crédito Electrónica: 3063693 | AG27: 11287520 | AH27: 01-03-2025 0:00:00 | AJ27: 0 | AK27: SALON | AL27: 01-03-2025 0:00:00 | AM27: FLOTA | AN27: Peso | AP27: 8 | AQ27: 13840000 | AR27: -2050000 | AS27: -934538 | AT27: 9655462 | AU27: 9937520 | AV27: -282058 | AW27: -2.92 % | AX27: 0 | AY27: 295713 | AZ27: 295713 | BA27: 0 | BB27: 0 % | BC27: 0 | BD27: 0 | BE27: 0 | BF27: 0 | BG27: 0 % | BH27: 0 | BI27: 0 | BJ27: 0 | BK27: 0 | BL27: 0 % | BM27: 11790000 | BN27: 9951175 | BO27: 10233233 | BP27: -282058 | BQ27: -2.83 % | BR27: -282058 | BS27: -2.83 % | BT27: 0 | BU27: 0 | BV27: 11785713 | BW27: 0 | BX27: 295713 | BY27: 0 | BZ27: 11785713 | CA27: 9951175 | CB27: -282058 | CC27: -2.83 % | CE27: 0 | CG27: 0 | CH27: 1606500 | CI27: 0
A28: CASA MATRIZ NUEVOS | B28: ROBERTO LOBOS GUTIERREZ | C28: 21-01-2025 18:00:21 | D28: 5949 | E28: RODRIGO ALFONSO HEREDIA PEÑA | F28: 10653803 | G28: 4 | H28: CAMINO LOS PEUMOS 10200 CASA 27 | I28: 979667938 | L28: LO BARNECHEA | M28: 18/01/1973 | N28: RODRIGOHEREDI@GMAIL.COM | P28: STATION WAGON | Q28: VOLKSWAGEN | R28: T CROSS | S28: T-Cross 1.0 TSI AT Comfortline - 85 kW/116 CV | T28: BF33K311 | U28: PLATA PIRITA | V28: AN-24-12-0049 | W28: 9BWBH6BF6S4053356 | X28: 9BWBH6BF6S4053356 | Y28: 9BWBH6BF6S4053356 | Z28: NUEVO Y SIN USO | AA28: 2025 | AB28: Facturada | AC28: 19925 | AD28: 27-01-2025 0:00:00 | AF28: Guía de Despacho: 1 - Factura Electrónica: 1864428 | AG28: 16848883 | AH28: 27-01-2025 0:00:00 | AJ28: 0 | AK28: SALON | AL28: 27-01-2025 0:00:00 | AM28: CC | AN28: Peso | AP28: 32 | AQ28: 18058824 | AR28: -1470588 | AS28: -1083529 | AT28: 15504706 | AU28: 16848883 | AV28: -1344177 | AW28: -8.67 % | AX28: 0 | AY28: 889892 | AZ28: 889892 | BA28: 0 | BB28: 0 % | BC28: 0 | BD28: 0 | BE28: 0 | BF28: 0 | BG28: 0 % | BH28: 0 | BI28: 0 | BJ28: 0 | BK28: 0 | BL28: 0 % | BM28: 16588236 | BN28: 16394598 | BO28: 17738775 | BP28: -1344177 | BQ28: -8.2 % | BR28: -1344177 | BS28: -8.2 % | BT28: 0 | BU28: 0 | BV28: 19340492 | BW28: 0 | BX28: 889892 | BY28: 0 | BZ28: 19340492 | CA28: 16394598 | CB28: -1344177 | CC28: -8.2 % | CE28: 0 | CG28: 0 | CH28: 0 | CI28: 0
A29: CASA MATRIZ NUEVOS | B29: ROBERTO LOBOS GUTIERREZ | C29: 21-01-2025 18:15:01 | D29: 5950 | E29: VANESSA INES MALDONADO ALARCON | F29: 17166024 | G29: 6 | H29: COLOMBIA 7800 DEPTO 704 | J29: 956003735 | L29: LA FLORIDA | M29: 01/01/1900 | N29: VANE.M.ALARCON@GMAIL.COM | P29: STATION WAGON 01 | Q29: VOLKSWAGEN | R29: NIVUS | S29: Nivus TSI MT Comfortline - 70 kW/95 CV | T29: CH13L411 | U29: GRIS PLATINO | V29: AN-25-01-0013 | W29: 9BWCH6CHXRP079584 | X29: 9BWCH6CHXRP079584 | Z29: NUEVO Y SIN USO | AA29: 2025 | AB29: Facturada | AC29: 19921 | AD29: 27-01-2025 0:00:00 | AF29: Guía de Despacho: 1 - Factura Electrónica: 1864536 | AG29: 14888798 | AH29: 27-01-2025 0:00:00 | AJ29: 0 | AK29: WEB CONCESIONARIO | AL29: 27-01-2025 0:00:00 | AM29: CC | AN29: Peso | AP29: 0 | AQ29: 15537815 | AR29: -1554622 | AS29: -718109 | AT29: 13685252 | AU29: 14888798 | AV29: -1203546 | AW29: -8.79 % | AX29: 0 | AY29: 784550 | AZ29: 784550 | BA29: 0 | BB29: 0 % | BC29: 0 | BD29: 0 | BE29: 0 | BF29: 0 | BG29: 0 % | BH29: 0 | BI29: 0 | BJ29: 0 | BK29: 0 | BL29: 0 % | BM29: 13983193 | BN29: 14469802 | BO29: 15673348 | BP29: -1203546 | BQ29: -8.32 % | BR29: -1203546 | BS29: -8.32 % | BT29: 0 | BU29: 0 | BV29: 17070000 | BW29: 0 | BX29: 784550 | BY29: 0 | BZ29: 17070000 | CA29: 14469802 | CB29: -1203546 | CC29: -8.32 % | CE29: 0 | CG29: 0 | CH29: 0 | CI29: 0
A30: CASA MATRIZ NUEVOS | B30: ROBERTO LOBOS GUTIERREZ | C30: 22-01-2025 17:41:25 | D30: 5951 | E30: JONNY KULKA FRAENKEL | F30: 4863497 | G30: 4 | H30: CAMINO OTOÑAL 1326 DPTO C2 | I30: 993300005 | L30: LAS CONDES | M30: 21/04/1945 | N30: MARCOS.KULKA@FCH.CL | P30: STATION WAGON | Q30: VOLKSWAGEN | R30: FAMILIA 1 | S30: Nivus 1.0 TSI AT Comfortline 85KW/116CV 5 p | T30: CH13K311 | U30: BLANCO CANDY | V30: AN-24-10-0040 | W30: 9BWCH6CH5RP048825 | X30: 9BWCH6CH5RP048825 | Y30: 9BWCH6CH5RP048825 | Z30: NUEVO Y SIN USO | AA30: 2025 | AB30: Facturada | AC30: 19924 | AD30: 27-01-2025 0:00:00 | AF30: Guía de Despacho: 1 - Factura Electrónica: 1839682 | AG30: 16396017 | AH30: 27-01-2025 0:00:00 | AJ30: 0 | AK30: WEB CONCESIONARIO | AL30: 27-01-2025 0:00:00 | AM30: CC | AN30: Peso | AP30: 0 | AQ30: 17134454 | AR30: -1848739 | AS30: -457563 | AT30: 14828151 | AU30: 16396017 | AV30: -1567866 | AW30: -10.57 % | AX30: 0 | AY30: 844500 | AZ30: 844500 | BA30: 0 | BB30: 0 % | BC30: 0 | BD30: 0 | BE30: 0 | BF30: 0 | BG30: 0 % | BH30: 0 | BI30: 0 | BJ30: 0 | BK30: 0 | BL30: 0 % | BM30: 15285715 | BN30: 15672651 | BO30: 17240517 | BP30: -1567866 | BQ30: -10 % | BR30: -1567866 | BS30: -10 % | BT30: 0 | BU30: 0 | BV30: 18490000 | BW30: 0 | BX30: 844500 | BY30: 0 | BZ30: 18490000 | CA30: 15672651 | CB30: -1567866 | CC30: -10 % | CE30: 0 | CG30: 0 | CH30: 0 | CI30: 0
A31: CASA MATRIZ NUEVOS | B31: ROBERTO LOBOS GUTIERREZ | C31: 23-01-2025 16:36:11 | D31: 5954 | E31: DANIEL JACK BROOKS BRAVO | F31: 19894192 | G31: 1 | H31: MONROE 6584 | J31: 969160087 | L31: LAS CONDES | M31: 01/01/1900 | N31: Djbrookssb@gmail.com | P31: STATION WAGON | Q31: VOLKSWAGEN | R31: FAMILIA 1 | S31: Nivus 1.0 TSI AT Highline 85KW/116CV 5 p | T31: CH14K311 | U31: Gris Piedra de Luna | V31: AN-25-01-0035 | W31: 9BWCH6CH8RP052805 | X31: 9BWCH6CH8RP052805 | Y31: 9BWCH6CH8RP052805 | Z31: NUEVO Y SIN USO | AA31: 2025 | AB31: Facturada | AC31: 19920 | AD31: 27-01-2025 0:00:00 | AF31: Guía de Despacho: 1 - Factura Electrónica: 1864596 | AG31: 18103335 | AH31: 26-02-2025 0:00:00 | AJ31: 0 | AK31: WEB CONCESIONARIO | AL31: 26-02-2025 0:00:00 | AM31: CI | AN31: Peso | AP31: 0 | AQ31: 19403361 | AR31: -3739496 | AS31: -537815 | AT31: 15126050 | AU31: 18103335 | AV31: -2977285 | AW31: -19.68 % | AX31: 0 | AY31: 784164 | AZ31: 784164 | BA31: 0 | BB31: 0 % | BC31: 0 | BD31: 0 | BE31: 0 | BF31: 0 | BG31: 0 % | BH31: 0 | BI31: 0 | BJ31: 0 | BK31: 0 | BL31: 0 % | BM31: 15663865 | BN31: 15910214 | BO31: 18887499 | BP31: -2977285 | BQ31: -18.71 % | BR31: -2977285 | BS31: -18.71 % | BT31: 0 | BU31: 0 | BV31: 18784164 | BW31: 0 | BX31: 784164 | BY31: 0 | BZ31: 18784164 | CA31: 15910214 | CB31: -2977285 | CC31: -18.71 % | CE31: 0 | CG31: 0 | CH31: 0 | CI31: 0
A32: CASA MATRIZ NUEVOS | B32: ROBERTO LOBOS GUTIERREZ | C32: 24-01-2025 17:04:54 | D32: 5958 | E32: BERNARDITA MARIA SOLER LEON | F32: 15313830 | G32: 3 | H32: VASCO DE GAMA 4596 DEPTO 17 | J32: 961689307 | L32: LAS CONDES | M32: 01/01/1900 | N32: bernarditasoler@gmail.com | P32: STATION WAGON | Q32: VOLKSWAGEN | R32: T CROSS | S32: T-Cross 1.0 TSI AT Highline - 85 kW/116 CV | T32: BF34K311 | U32: PLATA PIRITA | V32: AN-24-12-0036 | W32: 9BWBH6BF2S4053564 | X32: 9BWBH6BF2S4053564 | Y32: 9BWBH6BF2S4053564 | Z32: NUEVO Y SIN USO | AA32: 2025 | AB32: Parcial Facturada | AC32: 19918 | AD32: 27-01-2025 0:00:00 | AF32: Guía de Despacho: 1 - Factura Electrónica: 1841782 | AG32: 17651815 | AH32: 27-01-2025 0:00:00 | AJ32: 0 | AK32: WEB CONCESIONARIO | AL32: 27-01-2025 0:00:00 | AM32: CC | AN32: Peso | AP32: 39 | AQ32: 18899160 | AR32: -1218487 | AS32: -571429 | AT32: 17109244 | AU32: 17651815 | AV32: -542571 | AW32: -3.17 % | AX32: 0 | AY32: 977613 | AZ32: 977613 | BA32: 0 | BB32: 0 % | BC32: 55336 | BD32: 252101 | BE32: 0 | BF32: 0 | BG32: 0 % | BH32: 0 | BI32: 0 | BJ32: 0 | BK32: 0 | BL32: 0 % | BM32: 17680673 | BN32: 18338958 | BO32: 18629428 | BP32: -290470 | BQ32: -1.58 % | BR32: -290470 | BS32: -1.58 % | BT32: 0 | BU32: 0 | BV32: 21637613 | BW32: 0 | BX32: 977613 | BY32: 252101 | BZ32: 21637614 | CA32: 18338958 | CB32: -290470 | CC32: -1.58 % | CE32: 0 | CG32: 0 | CH32: 0 | CI32: 0
A33: CASA MATRIZ NUEVOS | B33: JUAN PABLO GONZALEZ ACUÑA | C33: 27-01-2025 18:15:38 | D33: 5960 | E33: FRANCESCA MARIA DE LOURDES CALVANESE HUIDOBRO | F33: 8545815 | G33: 9 | H33: HERNANDO DE MAGALLANES 1922 | I33: 996897113 | L33: LAS CONDES | M33: 06/06/1959 | N33: francescacalvanese@gmail.com | P33: STATION WAGON | Q33: VOLKSWAGEN | R33: T CROSS | S33: T-Cross 1.0 TSI MT Comfortline - 74 kW/101 CV | T33: BF33D411 | U33: AZUL NORUEGA | V33: AN-24-08-0072 | W33: 9BWBH6BF7S4004618 | X33: 9BWBH6BF7S4004618 | Y33: 9BWBH6BF7S4004618 | Z33: NUEVO Y SIN USO | AA33: 2025 | AB33: Facturada | AC33: 19926 | AD33: 28-01-2025 0:00:00 | AF33: Guía de Despacho: 1 - Factura Electrónica: 1838082 | AG33: 15795707 | AH33: 28-01-2025 0:00:00 | AJ33: 0 | AK33: SALON | AL33: 28-01-2025 0:00:00 | AM33: RETAIL | AN33: Peso | AP33: 123 | AQ33: 16966386 | AR33: -1554622 | AS33: -508992 | AT33: 14902773 | AU33: 15795707 | AV33: -892934 | AW33: -5.99 % | AX33: 0 | AY33: 860724 | AZ33: 860724 | BA33: 0 | BB33: 0 % | BC33: 0 | BD33: 0 | BE33: 0 | BF33: 0 | BG33: 0 % | BH33: 0 | BI33: 0 | BJ33: 0 | BK33: 0 | BL33: 0 % | BM33: 15411764 | BN33: 15763497 | BO33: 16656431 | BP33: -892934 | BQ33: -5.66 % | BR33: -892934 | BS33: -5.66 % | BT33: 0 | BU33: 0 | BV33: 18595024 | BW33: 0 | BX33: 860724 | BY33: 0 | BZ33: 18595024 | CA33: 15763497 | CB33: -892934 | CC33: -5.66 % | CE33: 0 | CG33: 0 | CH33: 0 | CI33: 0
A34: CASA MATRIZ NUEVOS | B34: JUAN PABLO GONZALEZ ACUÑA | C34: 29-01-2025 9:57:23 | D34: 5963 | E34: NATALIE ANDREE BORDACHAR URRUTIA | F34: 15934220 | G34: 4 | H34: VEINTITRES DE FEBRERO 8916 CASA A | I34: 998484576 | L34: LA REINA | M34: 31/07/1984 | N34: nataliebordachar@gmail.com | P34: STATION WAGON 01 | Q34: VOLKSWAGEN | R34: FAMILIA 1 | S34: Taos TSI AT Comfortline 110KW/150CV | T34: CQ16LY11 | U34: BLANCO PURO | V34: AN-24-10-0061 | W34: 8AWBJ6B26RA830005 | X34: 8AWBJ6B26RA830005 | Y34: 8AWBJ6B26RA830005 | Z34: NUEVO Y SIN USO | AA34: 2025 | AB34: Facturada | AC34: 19942 | AD34: 29-01-2025 0:00:00 | AF34: Guía de Despacho: 1 - Factura Electrónica: 1839961 | AG34: 20025176 | AH34: 28-02-2025 0:00:00 | AJ34: 0 | AK34: SALON | AL34: 28-02-2025 0:00:00 | AM34: RETAIL | AN34: Peso | AP34: 97 | AQ34: 21672269 | AR34: -3235294 | AS34: -866891 | AT34: 17570084 | AU34: 20025176 | AV34: -2455092 | AW34: -13.97 % | AX34: 0 | AY34: 1024400 | AZ34: 1024400 | BA34: 0 | BB34: 0 % | BC34: 0 | BD34: 0 | BE34: 0 | BF34: 0 | BG34: 0 % | BH34: 0 | BI34: 0 | BJ34: 0 | BK34: 0 | BL34: 0 % | BM34: 18436975 | BN34: 18594484 | BO34: 21049576 | BP34: -2455092 | BQ34: -13.2 % | BR34: -2455092 | BS34: -13.2 % | BT34: 0 | BU34: 0 | BV34: 21932800 | BW34: 0 | BX34: 1024400 | BY34: 0 | BZ34: 21932800 | CA34: 18594484 | CB34: -2455092 | CC34: -13.2 % | CE34: 0 | CG34: 0 | CH34: 0 | CI34: 0
A35: CASA MATRIZ NUEVOS | B35: ROBERTO LOBOS GUTIERREZ | C35: 30-01-2025 17:47:56 | D35: 5969 | E35: FRANCISCA ANDREA RIQUELME FENNER | F35: 18142681 | G35: 0 | H35: ALONSO DE CAMARGO 5870 DEPTO 403 | J35: 99179180 | L35: LAS CONDES | M35: 01/01/1900 | N35: NICOLAS.C¿MACCLUR@INPEN.CL | P35: STATION WAGON | Q35: VOLKSWAGEN | S35: NUEVO ATLAS 2.0 TSI AT LIMITED 4MOTION | T35: CA35PR11 | U35: GRIS PLATINO | V35: AN-24-12-0042 | W35: WVGZZZCA5RC601451 | X35: WVGZZZCA5RC601451 | Y35: WVGZZZCA5RC601451 | Z35: NUEVO Y SIN USO | AA35: 2025 | AB35: Parcial Facturada | AC35: 19949 | AD35: 31-01-2025 0:00:00 | AF35: Factura Electrónica: 1841778 | AG35: 43474588 | AH35: 31-01-2025 0:00:00 | AJ35: 0 | AK35: SALON | AL35: 31-01-2025 0:00:00 | AM35: CC | AN35: Peso | AP35: 31 | AQ35: 47050420 | AR35: -2521008 | AS35: -2521008 | AT35: 42008403 | AU35: 43474588 | AV35: -1466185 | AW35: -3.49 % | AX35: 0 | AY35: 2749605 | AZ35: 2749605 | BA35: 0 | BB35: 0 % | BC35: 110500 | BD35: 168487 | BE35: 0 | BF35: 0 | BG35: 0 % | BH35: 0 | BI35: 0 | BJ35: 0 | BK35: 0 | BL35: 0 % | BM35: 44529412 | BN35: 44926495 | BO35: 46224193 | BP35: -1297698 | BQ35: -2.89 % | BR35: -1297698 | BS35: -2.89 % | BT35: 0 | BU35: 0 | BV35: 52940105 | BW35: 0 | BX35: 2749605 | BY35: 168487 | BZ35: 52940104 | CA35: 44926495 | CB35: -1297698 | CC35: -2.89 % | CE35: 0 | CG35: 0 | CH35: 0 | CI35: 0

Sheet ANDES
A1: Sucursal | B1: Vendedor | C1: Fecha Venta | D1: Folio Venta | E1: Cliente | F1: Rut | G1: Digito | H1: Dirección | I1: Teléfono Fijo | J1: Teléfono Móvil | K1: Teléfono Comercial | L1: Comuna | M1: Fecha Nacimiento | N1: E-mail | O1: Tipo Vehículo | P1: Marca | Q1: Modelo | R1: Versión | S1: Codigo Version | T1: Color | U1: Código Interno | V1: Numero Chasis | W1: Numero VIN | X1: Numero Serie | Y1: Condición | Z1: Año | AA1: Estado Venta | AB1: Folio Facturación | AC1: Fecha Facturación | AD1: Tipo Documento | AE1: Documento | AF1: Precio Compra | AG1: Vencimiento Factura | AH1: Vendedor Cotización | AI1: Folio | AJ1: Medio Contacto | AK1: Vencimiento Documento | AL1: Tipo Venta | AM1: Moneda Venta | AN1: Patente Pago | AO1: Días Stock | AP1: Precio Lista | AQ1: Bono Lista Precio | AR1: Descuento Unidad | AS1: Unidad Venta | AT1: Unidad Costo | AU1: Unidad Margen | AV1: % | AW1: Tramites Descuento/Recargo | AX1: Tramites Venta | AY1: Tramites Costo | AZ1: Tramites Margen | BA1: %1 | BB1: Accesorios Descuento/Recargo | BC1: Accesorios Venta | BD1: Accesorios Costo | BE1: Accesorios Margen | BF1: %2 | BG1: Contratos DR ML | BH1: Contratos Sub Total ML | BI1: Contratos Costo ML | BJ1: Contratos Margen ML | BK1: Contratos Margen Pje | BL1: Total Lista Precio | BM1: SubTotal Venta | BN1: SubTotal Costo | BO1: SubTotal Margen + Crédito + Seguro | BP1: %3 | BQ1: Margen Sin Intereses | BR1: Sub Total Margen ML Sin Inter~s Pje | BS1: Total Interés | BT1: Total Retoma | BU1: Total Abono | BV1: Total Saldo | BW1: Total Venta Trámite | BX1: Total Venta Accesorios | BY1: Total Venta | BZ1: Venta Sin Creditos Y Seguros | CA1: Margen de Venta | CB1: Pje. Margen de Venta | CC1: Entidad Crédito | CD1: Margen Crédito | CE1: Entidad Seguro | CF1: Margen Seguro | CG1: Bono | CH1: Gasto | CI1: Nacionalidad
A2: ANDES MOTOR | B2: RAMON MUÑOZ FERNANDEZ | C2: 10-12-2024 16:36:57 | D2: 5810 | E2: TRIPLE C INTERNATIONAL SPA | F2: 76009782 | G2: 9 | H2: EL ALFALFAL N°471 | I2: 932399384 | J2: 957897580 | L2: LAMPA | M2: 20/07/2010 | N2: CGODOY@TRIPLECINTERNATIONAL.COM | O2: CAMIONETA | P2: MAXUS | Q2: T60 | R2: T60 4X2 DX MT E6 | S2: 21062023 | T2: BLANCO | U2: AN-24-12-0001 | V2: LSFAM11A2SA041144 | W2: LSFAM11A2SA041144 | X2: LSFAM11A2SA041144 | Y2: NUEVO Y SIN USO | Z2: 2025 | AA2: Facturada | AB2: 19896 | AC2: 22-01-2025 0:00:00 | AE2: Guía de Despacho: 1 - Factura Electrónica: 205710 | AF2: 18978600 | AG2: 21-02-2025 0:00:00 | AI2: 0 | AK2: 21-02-2025 0:00:00 | AL2: [OTRO] | AM2: Peso | AO2: 52 | AP2: 20190000 | AQ2: -2019034 | AR2: 0 | AS2: 18170966 | AT2: 17464350 | AU2: 706616 | AV2: 3.89 % | AW2: 0 | AX2: 0 | AY2: 0 | AZ2: 0 | BA2: 0 % | BB2: 0 | BC2: 0 | BD2: 0 | BE2: 0 | BF2: 0 % | BG2: 0 | BH2: 0 | BI2: 0 | BJ2: 0 | BK2: 0 % | BL2: 18170966 | BM2: 18170966 | BN2: 17699350 | BO2: 471616 | BP2: 2.6 % | BQ2: 471616 | BR2: 2.6 % | BS2: 0 | BT2: 0 | BU2: 21623450 | BV2: 0 | BW2: 0 | BX2: 0 | BY2: 21623450 | BZ2: 18170966 | CA2: 471616 | CB2: 2.6 % | CD2: 0 | CF2: 0 | CG2: 1801958 | CH2: 235000
A3: ANDES MOTOR | B3: Manuel Rodrigo Hurtado Melo | C3: 02-01-2025 17:00:38 | D3: 5885 | E3: HERWIN ROLANDO BAHAMONDES HENRIQUEZ | F3: 13161261 | G3: 3 | H3: PASAJE LA GROSSAL 02340 | J3: 993401676 | L3: SAN BERNARDO | M3: 07/06/1977 | N3: HEREBAHAM@HOTMAIL.COM | O3: STATION WAGON | P3: JETOUR | Q3: X70 | R3: X70 1.5T MT LUX | S3: 03082023 | T3: ROJO | U3: AN-23-08-0059 | V3: LVUDB11B8PF018233 | W3: LVUDB11B8PF018233 | X3: LVUDB11B8PF018233 | Y3: NUEVO Y SIN USO | Z3: 2024 | AA3: Parcial Facturada | AB3: 19886 | AC3: 17-01-2025 0:00:00 | AE3: Guía de Despacho: 1 - Factura Electrónica: 145309 | AF3: 12748571 | AG3: 16-02-2025 0:00:00 | AI3: 0 | AJ3: SITIO WEB | AK3: 16-02-2025 0:00:00 | AL3: CC | AM3: Peso | AN3: HLRT60 | AO3: 506 | AP3: 14697479 | AQ3: -2521008 | AR3: -1680672 | AS3: 10495798 | AT3: 12748571 | AU3: -2252773 | AV3: -21.46 % | AW3: 0 | AX3: 699835 | AY3: 699835 | AZ3: 0 | BA3: 0 % | BB3: 0 | BC3: 0 | BD3: 0 | BE3: 0 | BF3: 0 % | BG3: 0 | BH3: 0 | BI3: 0 | BJ3: 0 | BK3: 0 % | BL3: 12176471 | BM3: 11195633 | BN3: 13448406 | BO3: -2252773 | BP3: -20.12 % | BQ3: -2252773 | BR3: -20.12 % | BS3: 0 | BT3: 3500000 | BU3: 9738652 | BV3: -48817 | BW3: 699835 | BX3: 0 | BY3: 13189835 | BZ3: 11195633 | CA3: -2252773 | CB3: -20.12 % | CD3: 0 | CF3: 0 | CG3: 0 | CH3: 0
A4: ANDES MOTOR | B4: Marcos Ignacio Campos Zavala | C4: 07-01-2025 13:16:04 | D4: 5897 | E4: GLOBAL GROUP INGENIERIA SPA | F4: 76235534 | G4: 5 | H4: BAQUEDANO 239 OF 414 | I4: 6-919.3266 | J4: 926281759 | L4: ANTOFAGASTA | N4: GERENCIA@GGINGENIERIA.CL | O4: CAMIONETA | P4: MAXUS | Q4: C35 L | R4: C35 L CARROCERÍA PLANA | S4: C35 L CARROCERÍA PLANA | T4: BLANCO | U4: AN-24-12-0004 | V4: LSH14B4C6PD900042 | W4: LSH14B4C6PD900042 | X4: LSH14B4C6PD900042 | Y4: NUEVO Y SIN USO | Z4: 2023 | AA4: Parcial Facturada | AB4: 19844 | AC4: 10-01-2025 0:00:00 | AE4: Guía de Despacho: 1 - Factura Electrónica: 284604 | AF4: 15190500 | AG4: 10-01-2025 0:00:00 | AI4: 0 | AJ4: WEB CONCESIONARIO | AK4: 10-01-2025 0:00:00 | AL4: RETAIL | AM4: Peso | AO4: 15 | AP4: 20990000 | AQ4: 0 | AR4: -4443782 | AS4: 16546218 | AT4: 15190500 | AU4: 1355718 | AV4: 8.19 % | AW4: 0 | AX4: 573980 | AY4: 573980 | AZ4: 0 | BA4: 0 % | BB4: 0 | BC4: 0 | BD4: 0 | BE4: 0 | BF4: 0 % | BG4: 0 | BH4: 0 | BI4: 0 | BJ4: 0 | BK4: 0 % | BL4: 20990000 | BM4: 17120198 | BN4: 15764480 | BO4: 1355718 | BP4: 7.92 % | BQ4: 1355718 | BR4: 7.92 % | BS4: 0 | BT4: 0 | BU4: 20263980 | BV4: 0 | BW4: 573980 | BX4: 0 | BY4: 20263979 | BZ4: 17120198 | CA4: 1355718 | CB4: 7.92 % | CD4: 0 | CF4: 0 | CG4: 0 | CH4: 0
A5: ANDES MOTOR | B5: Matias Larrain Larrain | C5: 08-01-2025 17:53:51 | D5: 5901 | E5: SOCIEDAD DE PROFESIONALES ASESORIAS GARREAUD FERNANDEZ LIMITADA | F5: 77722252 | G5: K | H5: LO FONTECILLA 101 OFI 903 LC | J5: +56 9 8428 0282 | L5: LAS CONDES | M5: 03/03/2023 | N5: fgarreaud@pkgabogados.cl | O5: CAMIONETA | P5: MAXUS | Q5: T60 | R5: T60 4X2 GL AT E6 | S5: 2592023 | T5: PLATA | U5: AN-25-01-0007 | V5: LSFAM11A6SA041342 | W5: LSFAM11A6SA041342 | X5: LSFAM11A6SA041342 | Y5: NUEVO Y SIN USO | Z5: 2025 | AA5: Parcial Facturada | AB5: 19891 | AC5: 21-01-2025 0:00:00 | AE5: Guía de Despacho: 1 - Factura Electrónica: 206075 | AF5: 19862800 | AG5: 20-02-2025 0:00:00 | AI5: 0 | AJ5: SITIO WEB | AK5: 20-02-2025 0:00:00 | AL5: CC | AM5: Peso | AO5: 16 | AP5: 21290000 | AQ5: -500000 | AR5: -863600 | AS5: 20226400 | AT5: 19862800 | AU5: 363600 | AV5: 1.8 % | AW5: 0 | AX5: 633536 | AY5: 633536 | AZ5: 0 | BA5: 0 % | BB5: 0 | BC5: 0 | BD5: 0 | BE5: 0 | BF5: 0 % | BG5: 0 | BH5: 0 | BI5: 0 | BJ5: 0 | BK5: 0 % | BL5: 20790000 | BM5: 20859936 | BN5: 20496336 | BO5: 363600 | BP5: 1.74 % | BQ5: 363600 | BR5: 1.74 % | BS5: 0 | BT5: 0 | BU5: 24702952 | BV5: 0 | BW5: 633536 | BX5: 0 | BY5: 24702952 | BZ5: 20859936 | CA5: 363600 | CB5: 1.74 % | CD5: 0 | CF5: 0 | CG5: 0 | CH5: 0
A6: ANDES MOTOR | B6: Manuel Rodrigo Hurtado Melo | C6: 10-01-2025 15:37:20 | D6: 5911 | E6: ASCANIO OSORIO AVENDAÑO SER.ING.MEC.MOT.ASES.PINT.IND.Y GRALES .EIRL | F6: 76692680 | G6: 0 | H6: PETRONILA 149 50 | J6: 985433201 | L6: ANTOFAGASTA | M6: 01/01/2022 | N6: ascanio.osorioc@gmail.com | O6: CAMIONETA | P6: MAXUS | Q6: T60 | R6: T60 4X2 GL MT E6 | S6: T60 4X2 GL MT E6 | T6: GRIS | U6: AN-24-08-0083 | V6: LSFAM11A4RA077914 | W6: LSFAM11A4RA077914 | X6: LSFAM11A4RA077914 | Y6: NUEVO Y SIN USO | Z6: 2025 | AA6: Parcial Facturada | AB6: 19862 | AC6: 14-01-2025 0:00:00 | AE6: Guía de Despacho: 1 - Factura Electrónica: 186708 | AF6: 19586800 | AG6: 14-01-2025 0:00:00 | AI6: 0 | AJ6: SITIO WEB | AK6: 14-01-2025 0:00:00 | AL6: FLOTA | AM6: Peso | AO6: 109 | AP6: 21290000 | AQ6: -2767700 | AR6: -50000 | AS6: 18472300 | AT6: 19586800 | AU6: -1114500 | AV6: -6.03 % | AW6: 0 | AX6: 658602 | AY6: 658602 | AZ6: 0 | BA6: 0 % | BB6: 0 | BC6: 0 | BD6: 0 | BE6: 0 | BF6: 0 % | BG6: 0 | BH6: 0 | BI6: 0 | BJ6: 0 | BK6: 0 % | BL6: 18522300 | BM6: 19130902 | BN6: 20245402 | BO6: -1114500 | BP6: -5.83 % | BQ6: -1114500 | BR6: -5.83 % | BS6: 0 | BT6: 0 | BU6: 22640639 | BV6: 0 | BW6: 658602 | BX6: 0 | BY6: 22640639 | BZ6: 19130902 | CA6: -1114500 | CB6: -5.83 % | CD6: 0 | CF6: 0 | CG6: 0 | CH6: 0
A7: ANDES MOTOR | B7: Matias Larrain Larrain | C7: 10-01-2025 15:45:47 | D7: 5912 | E7: RUCO SPA | F7: 77423111 | G7: 0 | H7: RAFAEL CASANOVA 213, 309 | J7: 953274041 | L7: SANTA CRUZ | M7: 25/07/2022 | N7: AGUSTIN@RUCOCONSULTING.CL | O7: CAMIONETA | P7: MAXUS | Q7: T60 | R7: T60 BLACK EDITION 4X4 GLX AT E6 | S7: 2710 | T7: PLATA | U7: AN-25-01-0009 | V7: LSFAM11A3PA075696 | W7: LSFAM11A3PA075696 | X7: LSFAM11A3PA075696 | Y7: NUEVO Y SIN USO | Z7: 2024 | AA7: Parcial Facturada | AB7: 19889 | AC7: 20-01-2025 0:00:00 | AE7: Guía de Despacho: 1 - Factura Electrónica: 206024 | AF7: 21298620 | AG7: 19-02-2025 0:00:00 | AI7: 0 | AJ7: AMIGO | AK7: 19-02-2025 0:00:00 | AL7: CC | AM7: Peso | AN7: FRTD28 | AO7: 6 | AP7: 26690000 | AQ7: -4270400 | AR7: 0 | AS7: 22419600 | AT7: 21298620 | AU7: 1120980 | AV7: 5 % | AW7: 0 | AX7: 721264 | AY7: 721264 | AZ7: 0 | BA7: 0 % | BB7: 0 | BC7: 0 | BD7: 0 | BE7: 0 | BF7: 0 % | BG7: 0 | BH7: 0 | BI7: 0 | BJ7: 0 | BK7: 0 % | BL7: 22419600 | BM7: 23140864 | BN7: 22019884 | BO7: 1120980 | BP7: 4.84 % | BQ7: 1120980 | BR7: 4.84 % | BS7: 0 | BT7: 2000000 | BU7: 25400588 | BV7: 0 | BW7: 721264 | BX7: 0 | BY7: 27400588 | BZ7: 23140864 | CA7: 1120980 | CB7: 4.84 % | CD7: 0 | CF7: 0 | CG7: 0 | CH7: 0
A8: ANDES MOTOR | B8: Marcos Ignacio Campos Zavala | C8: 11-01-2025 12:06:24 | D8: 5915 | E8: DIEGO ALEJANDRO JIMENEZ SILVA | F8: 16802706 | G8: 0 | H8: EJERCITO LIBERTADOR 2120 CASA 297 | J8: 985658267 | L8: PUENTE ALTO | M8: 22/09/1987 | N8: COMERCIALA07SPA@GMAIL.COM | O8: AUTOMOVIL | P8: KAIYI | Q8: KYE5 | R8: KYE5 1.5T MT LUX | S8: 632024 | T8: GRIS | U8: AN-24-03-0009 | V8: LUYJA1G22RA003056 | W8: LUYJA1G22RA003056 | X8: LUYJA1G22RA003056 | Y8: NUEVO Y SIN USO | Z8: 2025 | AA8: Parcial Facturada | AB8: 19872 | AC8: 15-01-2025 0:00:00 | AE8: Guía de Despacho Electrónica: 1 - Factura Electrónica: 168809 | AF8: 11588907 | AG8: 14-02-2025 0:00:00 | AI8: 0 | AJ8: WEB CONCESIONARIO | AK8: 14-02-2025 0:00:00 | AL8: RETAIL | AM8: Peso | AO8: 0 | AP8: 12596639 | AQ8: -1848739 | AR8: -429916 | AS8: 10317983 | AT8: 11588907 | AU8: -1270924 | AV8: -12.32 % | AW8: 0 | AX8: 669467 | AY8: 669467 | AZ8: 0 | BA8: 0 % | BB8: 0 | BC8: 0 | BD8: 0 | BE8: 0 | BF8: 0 % | BG8: 0 | BH8: 0 | BI8: 0 | BJ8: 0 | BK8: 0 % | BL8: 10747900 | BM8: 10987450 | BN8: 12258374 | BO8: -1270924 | BP8: -11.57 % | BQ8: -1270924 | BR8: -11.57 % | BS8: 0 | BT8: 0 | BU8: 12947867 | BV8: 0 | BW8: 669467 | BX8: 0 | BY8: 12947867 | BZ8: 10987450 | CA8: -1270924 | CB8: -11.57 % | CD8: 0 | CF8: 0 | CG8: 0 | CH8: 0
A9: ANDES MOTOR | B9: Matias Larrain Larrain | C9: 15-01-2025 10:53:16 | D9: 5929 | E9: GERARDO ACHA ZUÑIGA | F9: 7697564 | G9: 7 | H9: LOS JORNALEROS 1718 | J9: 982342462 | L9: ÑUÑOA | M9: 06/03/1961 | N9: GERARDOACHA@GMAIL.COM | O9: STATION WAGON | P9: JETOUR | Q9: X70 | R9: X70 1.5T MT STD | S9: 02082023 | T9: BLANCO | U9: AN-24-07-0010 | V9: LVUDB11B4PF009299 | W9: LVUDB11B4PF009299 | X9: LVUDB11B4PF009299 | Y9: NUEVO Y SIN USO | Z9: 2024 | AA9: Facturada | AB9: 19887 | AC9: 20-01-2025 0:00:00 | AE9: Guía de Despacho: 1 - Factura Electrónica: 176302 | AF9: 12362017 | AG9: 19-02-2025 0:00:00 | AI9: 0 | AJ9: SITIO WEB | AK9: 19-02-2025 0:00:00 | AL9: CI | AM9: Peso | AO9: 202 | AP9: 13436975 | AQ9: -2394958 | AR9: -462185 | AS9: 10579832 | AT9: 12362017 | AU9: -1782185 | AV9: -16.85 % | AW9: -622830 | AX9: 0 | AY9: 622830 | AZ9: -622830 | BA9: -100 % | BB9: 0 | BC9: 0 | BD9: 0 | BE9: 0 | BF9: 0 % | BG9: 0 | BH9: 0 | BI9: 0 | BJ9: 0 | BK9: 0 % | BL9: 11042017 | BM9: 10579832 | BN9: 12984847 | BO9: -2405015 | BP9: -22.73 % | BQ9: -2405015 | BR9: -22.73 % | BS9: 0 | BT9: 0 | BU9: 12672230 | BV9: -82230 | BW9: 0 | BX9: 0 | BY9: 12590000 | BZ9: 10579832 | CA9: -2405015 | CB9: -22.73 % | CD9: 0 | CF9: 0 | CG9: 0 | CH9: 0
A10: ANDES MOTOR | B10: SERGIO POBLETE CAMPOS | C10: 21-01-2025 11:03:39 | D10: 5943 | E10: ENNIO MAURICIO GRBAC NUÑEZ | F10: 7131041 | G10: 8 | H10: TONGOY 1157 | I10: 67275763 | J10: +569 67275763 | L10: LAS CONDES | M10: 20/12/1964 | N10: enniogrbac@grbac.cl | O10: STATION WAGON | P10: MAXUS | Q10: D60 | R10: D60 4X2 LUX AT 7P | S10: 10112023 | T10: PLATA | U10: AN-24-09-0044 | V10: LSKG4BC13SD040453 | W10: LSKG4BC13SD040453 | X10: LSKG4BC13SD040453 | Y10: NUEVO Y SIN USO | Z10: 2025 | AA10: Parcial Facturada | AB10: 19907 | AC10: 23-01-2025 0:00:00 | AE10: Guía de Despacho: 1 - Factura Electrónica: 205322 | AF10: 17773781 | AG10: 22-02-2025 0:00:00 | AI10: 0 | AJ10: SALON | AK10: 22-02-2025 0:00:00 | AL10: CC | AM10: Peso | AN10: KBBL13 | AO10: 115 | AP10: 19319328 | AQ10: -1680672 | AR10: -840336 | AS10: 16798319 | AT10: 17773781 | AU10: -975462 | AV10: -5.81 % | AW10: 0 | AX10: 1000000 | AY10: 1000000 | AZ10: 0 | BA10: 0 % | BB10: 0 | BC10: 0 | BD10: 0 | BE10: 0 | BF10: 0 % | BG10: 0 | BH10: 0 | BI10: 0 | BJ10: 0 | BK10: 0 % | BL10: 17638656 | BM10: 17798319 | BN10: 18773781 | BO10: -975462 | BP10: -5.48 % | BQ10: -975462 | BR10: -5.48 % | BS10: 0 | BT10: 6300000 | BU10: 14690000 | BV10: 0 | BW10: 1000000 | BX10: 0 | BY10: 20990000 | BZ10: 17798319 | CA10: -975462 | CB10: -5.48 % | CD10: 0 | CF10: 0 | CG10: 0 | CH10: 0
A11: ANDES MOTOR | B11: Marcos Ignacio Campos Zavala | C11: 21-01-2025 14:49:46 | D11: 5945 | E11: MANUELA SOLEDAD SALAS CAMPOS | F11: 17958247 | G11: 3 | H11: JUAN DE DIOS VIAL CORREA 4220 DPTO 401 B | I11: 95975802 | J11: 951975802 | L11: PEÑALOLEN | M11: 10/06/1991 | N11: manu_salas1991@hotmail.com | O11: STATION WAGON | P11: JETOUR | Q11: T2 | R11: T2 2.0T GDI AWD 7DCT LIMITED | S11: 240813 | T11: GRIS ARENA | U11: AN-24-08-0067 | V11: HJRPBGJBXSB200369 | W11: HJRPBGJBXSB200369 | X11: HJRPBGJBXSB200369 | Y11: NUEVO Y SIN USO | Z11: 2025 | AA11: Parcial Facturada | AB11: 19957 | AC11: 31-01-2025 0:00:00 | AE11: Guía de Despacho: 1 - Factura Electrónica: 187112 | AF11: 23185546 | AG11: 02-03-2025 0:00:00 | AI11: 0 | AJ11: WEB CONCESIONARIO | AK11: 02-03-2025 0:00:00 | AL11: RETAIL | AM11: Peso | AN11: SFXJ73 | AO11: 158 | AP11: 25201681 | AQ11: -1176471 | AR11: -961008 | AS11: 23064202 | AT11: 23185546 | AU11: -121344 | AV11: -0.53 % | AW11: 0 | AX11: 1572888 | AY11: 1572888 | AZ11: 0 | BA11: 0 % | BB11: 0 | BC11: 0 | BD11: 0 | BE11: 0 | BF11: 0 % | BG11: 0 | BH11: 0 | BI11: 0 | BJ11: 0 | BK11: 0 % | BL11: 24025210 | BM11: 24637090 | BN11: 24758434 | BO11: -121344 | BP11: -0.49 % | BQ11: -121344 | BR11: -0.49 % | BS11: 0 | BT11: 6700000 | BU11: 24798063 | BV11: -2478775 | BW11: 1572888 | BX11: 0 | BY11: 29019288 | BZ11: 24637090 | CA11: -121344 | CB11: -0.49 % | CD11: 0 | CF11: 0 | CG11: 0 | CH11: 0
A12: ANDES MOTOR | B12: Manuel Rodrigo Hurtado Melo | C12: 23-01-2025 11:04:10 | D12: 5952 | E12: PATAGONIA BIOTECNICNOLOGIA SPA | F12: 76321115 | G12: 0 | H12: RUTA V-065 KM 5 0 RIO CHICO | J12: 994341528 | L12: PUERTO MONTT | M12: 28/05/2024 | N12: TJOQUE@PATBIO.COM | O12: CAMIONETA | P12: MAXUS | Q12: T60 | R12: T60 4X4 GLX AT E6 | S12: T60 4X4 GLX AT E6 | T12: GRIS | U12: AN-24-11-0035 | V12: LSFAM11A5SA041445 | W12: LSFAM11A5SA041445 | X12: LSFAM11A5SA041445 | Y12: NUEVO Y SIN USO | Z12: 2025 | AA12: Parcial Facturada | AB12: 19913 | AC12: 24-01-2025 0:00:00 | AE12: Guía de Despacho: 1 - Factura Electrónica: 206185 | AF12: 24554800 | AG12: 24-01-2025 0:00:00 | AI12: 0 | AJ12: SITIO WEB | AK12: 24-01-2025 0:00:00 | AL12: RETAIL | AM12: Peso | AO12: 0 | AP12: 26690000 | AQ12: -1500000 | AR12: -500000 | AS12: 24690000 | AT12: 24554800 | AU12: 135200 | AV12: 0.55 % | AW12: 0 | AX12: 929310 | AY12: 929310 | AZ12: 0 | BA12: 0 % | BB12: 0 | BC12: 0 | BD12: 0 | BE12: 0 | BF12: 0 % | BG12: 0 | BH12: 0 | BI12: 0 | BJ12: 0 | BK12: 0 % | BL12: 25190000 | BM12: 25619310 | BN12: 25484110 | BO12: 135200 | BP12: 0.53 % | BQ12: 135200 | BR12: 0.53 % | BS12: 0 | BT12: 0 | BU12: 30310410 | BV12: 0 | BW12: 929310 | BX12: 0 | BY12: 30310410 | BZ12: 25619310 | CA12: 135200 | CB12: 0.53 % | CD12: 0 | CF12: 0 | CG12: 0 | CH12: 0
A13: ANDES MOTOR | B13: Marcos Ignacio Campos Zavala | C13: 24-01-2025 10:01:06 | D13: 5956 | E13: LION OPERATIONS SPA | F13: 78060017 | G13: 9 | H13: SEMINARIO 372 | J13: 985290198 | L13: PUERTO MONTT | N13: gabriel.oberreuter@opciones.cl | O13: CAMIONETA | P13: KARRY | Q13: Q22 | R13: Q22 C.B. Cargo Box 1.5cc | S13: 3242023 | T13: BLANCO | U13: AN-25-01-0036 | V13: LVM1A1A14NF048727 | W13: LVM1A1A14NF048727 | X13: LVM1A1A14NF048727 | Y13: NUEVO Y SIN USO | Z13: 2023 | AA13: Parcial Facturada | AB13: 19950 | AC13: 31-01-2025 0:00:00 | AE13: Guía de Despacho: 1 - Factura Electrónica: 293476 | AF13: 9380600 | AG13: 31-01-2025 0:00:00 | AI13: 0 | AJ13: WEB CONCESIONARIO | AK13: 31-01-2025 0:00:00 | AL13: FLOTA | AM13: Peso | AO13: -6 | AP13: 10540000 | AQ13: -2250000 | AR13: -735378 | AS13: 7554622 | AT13: 9380600 | AU13: -1825978 | AV13: -24.17 % | AW13: 0 | AX13: 336980 | AY13: 336980 | AZ13: 0 | BA13: 0 % | BB13: 0 | BC13: 0 | BD13: 0 | BE13: 0 | BF13: 0 % | BG13: 0 | BH13: 0 | BI13: 0 | BJ13: 0 | BK13: 0 % | BL13: 8290000 | BM13: 7891602 | BN13: 9717580 | BO13: -1825978 | BP13: -23.14 % | BQ13: -1825978 | BR13: -23.14 % | BS13: 0 | BT13: 0 | BU13: 9326980 | BV13: 0 | BW13: 336980 | BX13: 0 | BY13: 9326980 | BZ13: 7891602 | CA13: -1825978 | CB13: -23.14 % | CD13: 0 | CF13: 0 | CG13: 0 | CH13: 0
A14: ANDES MOTOR | B14: Marcos Ignacio Campos Zavala | C14: 31-01-2025 10:48:39 | D14: 5970 | E14: MATIAS AGLIATI GARRIDO | F14: 15959880 | G14: 2 | H14: LO CABAÑA 80 DPTO 804 | I14: 93433346 | J14: 993433346 | L14: LAS CONDES | M14: 27/11/1984 | N14: MATIASAGLIATI@GMAIL.COM | O14: STATION WAGON | P14: JETOUR | Q14: T2 | R14: T2 2.0T GDI AWD 7DCT LIMITED | S14: 240813 | T14: GRIS ARENA | U14: AN-25-01-0033 | V14: HJRPBGJB1SB203855 | W14: HJRPBGJB1SB203855 | X14: HJRPBGJB1SB203855 | Y14: NUEVO Y SIN USO | Z14: 2025 | AA14: Parcial Facturada | AB14: 19958 | AC14: 31-01-2025 0:00:00 | AE14: Guía de Despacho: 1 - Factura Electrónica: 206373 | AF14: 23185546 | AG14: 02-03-2025 0:00:00 | AI14: 0 | AJ14: WEB CONCESIONARIO | AK14: 02-03-2025 0:00:00 | AL14: RETAIL | AM14: Peso | AN14: KZHK49 | AO14: 9 | AP14: 25201681 | AQ14: -2016807 | AR14: -927395 | AS14: 22257479 | AT14: 23185546 | AU14: -928067 | AV14: -4.17 % | AW14: 0 | AX14: 1460222 | AY14: 1460222 | AZ14: 0 | BA14: 0 % | BB14: 0 | BC14: 0 | BD14: 0 | BE14: 0 | BF14: 0 % | BG14: 0 | BH14: 0 | BI14: 0 | BJ14: 0 | BK14: 0 % | BL14: 23184874 | BM14: 23717701 | BN14: 24645768 | BO14: -928067 | BP14: -3.91 % | BQ14: -928067 | BR14: -3.91 % | BS14: 0 | BT14: 22500000 | BU14: 13268630 | BV14: -7822008 | BW14: 1460222 | BX14: 0 | BY14: 27946622 | BZ14: 23717701 | CA14: -928067 | CB14: -3.91 % | CD14: 0 | CF14: 0 | CG14: 0 | CH14: 0

Sheet USADOS
A1: Marca | B1: Versión | C1: Código Interno | D1: Año | E1: Numero Chasis | F1: Cliente | G1: Margen de Venta | I1: Sucursal | J1: Vendedor | K1: Fecha Venta | L1: Folio Venta | M1: Rut | N1: Digito | O1: Dirección | P1: Teléfono Fijo | Q1: Teléfono Móvil | R1: Teléfono Comercial | S1: Comuna | T1: Fecha Nacimiento | U1: E-mail | V1: Placa Patente | W1: Tipo Vehículo | X1: Modelo | Y1: Codigo Version | Z1: Color | AA1: Numero VIN | AB1: Numero Serie | AC1: Condición | AD1: Estado Venta | AE1: Folio Facturación | AF1: Fecha Facturación | AG1: Tipo Documento | AH1: Documento | AI1: Precio Compra | AJ1: Vencimiento Factura | AK1: Vendedor Cotización | AL1: Folio | AM1: Medio Contacto | AN1: Vencimiento Documento | AO1: Tipo Venta | AP1: Moneda Venta | AQ1: Patente Pago | AR1: Días Stock | AS1: Precio Lista | AT1: Bono Lista Precio | AU1: Descuento Unidad | AV1: Unidad Venta | AW1: Unidad Costo | AX1: Unidad Margen | AY1: % | AZ1: Tramites Descuento/Recargo | BA1: Tramites Venta | BB1: Tramites Costo | BC1: Tramites Margen | BD1: %1 | BE1: Accesorios Descuento/Recargo | BF1: Accesorios Venta | BG1: Accesorios Costo | BH1: Accesorios Margen | BI1: %2 | BJ1: Contratos DR ML | BK1: Contratos Sub Total ML | BL1: Contratos Costo ML | BM1: Contratos Margen ML | BN1: Contratos Margen Pje | BO1: Total Lista Precio | BP1: SubTotal Venta | BQ1: SubTotal Costo | BR1: SubTotal Margen + Crédito + Seguro | BS1: %3 | BT1: Margen Sin Intereses | BU1: Sub Total Margen ML Sin Inter~s Pje | BV1: Total Interés | BW1: Total Retoma | BX1: Total Abono | BY1: Total Saldo | BZ1: Total Venta Trámite | CA1: Total Venta Accesorios | CB1: Total Venta | CC1: Venta Sin Creditos Y Seguros | CD1: Margen de Venta | CE1: Pje. Margen de Venta | CF1: Entidad Crédito | CG1: Margen Crédito | CH1: Entidad Seguro | CI1: Margen Seguro | CJ1: Bono | CK1: Gasto | CL1: Nacionalidad
A2: CHEVROLET | B2: 1.5 T PREMIER | C2: AU-24-10-0032 | D2: 2023 | E2: LZWADAGA9PF003559 | F2: JAIME CHRISTIAN GRANTT CACERES | G2: 535650 | H2: =G2*100/CC2 -> 4.6497477 | I2: USADOS | J2: JUAN PABLO GONZALEZ ACUÑA | K2: 04-01-2025 10:48:36 | L2: 5890 | M2: 11631020 | N2: 1 | O2: VALENZUELA PUELMA 9709 CASA 22 | P2: 995153000 | Q2: 995153000 | S2: LA REINA | T2: 11/06/1970 | U2: jaimegrantt@gmail.com | V2: SVKC32 | W2: STATION WAGON | X2: GROOVE | Y2: 1.5 T PREMIER | Z2: NEGRO | AA2: LZWADAGA9PF003559 | AB2: LZWADAGA9PF003559 | AC2: CONSIGNACION USADO (Propio) | AD2: Facturada | AE2: 50798 | AF2: 24-01-2025 0:00:00 | AH2: Contrato: 132 | AI2: 10500000 | AJ2: 24-01-2025 0:00:00 | AL2: 0 | AM2: SALON | AN2: 24-01-2025 0:00:00 | AO2: RETAIL | AP2: Peso | AR2: 88 | AS2: 0 | AT2: 0 | AU2: -490000 | AV2: 11100000 | AW2: 10500000 | AX2: 600000 | AY2: 5.41 % | AZ2: 0 | BA2: 419980 | BB2: 419980 | BC2: 0 | BD2: 0 % | BE2: 0 | BF2: 0 | BG2: 0 | BH2: 0 | BI2: 0 % | BJ2: 0 | BK2: 0 | BL2: 0 | BM2: 0 | BN2: 0 % | BO2: 0 | BP2: 11519980 | BQ2: 10984330 | BR2: 535650 | BS2: 4.65 % | BT2: 535650 | BU2: 4.65 % | BV2: 0 | BW2: 0 | BX2: 11519980 | BY2: 0 | BZ2: 419980 | CA2: 0 | CB2: 12183980 | CC2: 11519980 | CD2: 535650 | CE2: 4.65 % | CG2: 0 | CI2: 0 | CJ2: 0 | CK2: 64350
A3: VOLKSWAGEN | B3: GOL G5 TRENDLINE 1.6 | C3: AU-24-12-0024 | D3: 2022 | E3: 9BWAB45U9NT088282 | F3: CRISTIAN ALEJANDRO PARDO SOTO | G3: 1073000 | H3: =G3*100/CC3 -> 13.66879 | I3: USADOS | J3: SERGIO POBLETE CAMPOS | K3: 08-01-2025 17:57:54 | L3: 5902 | M3: 15030471 | N3: 7 | O3: CAMINO EL PARQUE 100 DPTO 603 EDIFICIO LINGUE | Q3: +56948014356 | S3: VITACURA | T3: 09/07/1982 | U3: CRISTIANPARDOS@LIVE.COM | V3: RWPL70 | W3: AUTOMOVIL | X3: GOL | Y3: 10--RHGOL | Z3: BLANCO | AA3: 9BWAB45U9NT088282 | AB3: 9BWAB45U9NT088282 | AC3: CONSIGNACION USADO (Propio) | AD3: Facturada | AE3: 50799 | AF3: 24-01-2025 0:00:00 | AH3: Contrato: 143 | AI3: 6500000 | AJ3: 24-01-2025 0:00:00 | AL3: 0 | AM3: SITIO WEB | AN3: 24-01-2025 0:00:00 | AO3: CC | AP3: Peso | AR3: 29 | AS3: 0 | AT3: 0 | AU3: -417000 | AV3: 7573000 | AW3: 6500000 | AX3: 1073000 | AY3: 14.17 % | AZ3: 0 | BA3: 277000 | BB3: 277000 | BC3: 0 | BD3: 0 % | BE3: 0 | BF3: 0 | BG3: 0 | BH3: 0 | BI3: 0 % | BJ3: 0 | BK3: 0 | BL3: 0 | BM3: 0 | BN3: 0 % | BO3: 0 | BP3: 7850000 | BQ3: 6777000 | BR3: 1073000 | BS3: 13.67 % | BT3: 1073000 | BU3: 13.67 % | BV3: 0 | BW3: 0 | BX3: 7850000 | BY3: 0 | BZ3: 277000 | CA3: 0 | CB3: 7885000 | CC3: 7850000 | CD3: 1073000 | CE3: 13.67 % | CG3: 0 | CI3: 0 | CJ3: 0 | CK3: 0
A4: MAZDA | B4: 2.0 R AT | C4: AU-25-01-0010 | D4: 2013 | E4: JM8KE2W77D0141729 | F4: ORTUZAR SPA | G4: -300000 | H4: =G4*100/CC4 -> -6.3829787 | I4: USADOS | J4: RODRIGO MONTANER CABEZON | K4: 09-01-2025 13:07:01 | L4: 5903 | M4: 76981608 | N4: 9 | O4: FRANCISCO BILBAO N° 4740 | Q4: 985775766 | S4: LAS CONDES | U4: francisco.ortuzar@mail.udp.cl | V4: FSPS74 | W4: STATION WAGON | X4: CX-5 | Y4: 2.0 R AT | Z4: GRIS OSCURO | AA4: JM8KE2W77D0141729 | AB4: JM8KE2W77D0141729 | AC4: CONSIGNACION USADO (Propio) | AD4: Facturada | AE4: 50808 | AF4: 30-01-2025 0:00:00 | AH4: Contrato: 141 | AI4: 5000000 | AJ4: 30-01-2025 0:00:00 | AL4: 0 | AM4: SALON | AN4: 30-01-2025 0:00:00 | AO4: RETAIL | AP4: Peso | AR4: 21 | AS4: 0 | AT4: 0 | AU4: 0 | AV4: 4700000 | AW4: 5000000 | AX4: -300000 | AY4: -6.38 % | AZ4: 0 | BA4: 0 | BB4: 0 | BC4: 0 | BD4: 0 % | BE4: 0 | BF4: 0 | BG4: 0 | BH4: 0 | BI4: 0 % | BJ4: 0 | BK4: 0 | BL4: 0 | BM4: 0 | BN4: 0 % | BO4: 0 | BP4: 4700000 | BQ4: 5000000 | BR4: -300000 | BS4: -6.38 % | BT4: -300000 | BU4: -6.38 % | BV4: 0 | BW4: 0 | BX4: 5700000 | BY4: -1000000 | BZ4: 0 | CA4: 0 | CB4: 4700000 | CC4: 4700000 | CD4: -300000 | CE4: -6.38 % | CG4: 0 | CI4: 0 | CJ4: 0 | CK4: 0
A5: SUZUKI | B5: HB 1.4 AT | C5: AU-24-12-0009 | D5: 2022 | E5: MBHWB52S4PG840374 | F5: RICHARD ANTONY SEBASTIAN SOTO SANDOVAL | G5: 1390000 | H5: =G5*100/CC5 -> 16.019657 | I5: USADOS | J5: SERGIO POBLETE CAMPOS | K5: 09-01-2025 15:22:18 | L5: 5904 | M5: 18098948 | N5: K | O5: AV JOSE MIGUEL INFANTE 5886 | Q5: +56964395385 | S5: RENCA | T5: 11/09/1992 | U5: RICHARDSOTOSANDOVAL@GMAIL.COM | V5: RZHZ40 | W5: AUTOMOVIL | X5: BALENO | Y5: HB 1.4 AT | Z5: GRIS | AA5: MBHWB52S4PG840374 | AC5: CONSIGNACION USADO (Propio) | AD5: Facturada | AE5: 50794 | AF5: 24-01-2025 0:00:00 | AH5: Contrato: 144 | AI5: 7000000 | AJ5: 24-01-2025 0:00:00 | AL5: 0 | AM5: SITIO WEB | AN5: 24-01-2025 0:00:00 | AO5: CC | AP5: Peso | AR5: 51 | AS5: 0 | AT5: 0 | AU5: 0 | AV5: 8390000 | AW5: 7000000 | AX5: 1390000 | AY5: 16.57 % | AZ5: 0 | BA5: 286840 | BB5: 286840 | BC5: 0 | BD5: 0 % | BE5: 0 | BF5: 0 | BG5: 0 | BH5: 0 | BI5: 0 % | BJ5: 0 | BK5: 0 | BL5: 0 | BM5: 0 | BN5: 0 % | BO5: 0 | BP5: 8676840 | BQ5: 7286840 | BR5: 1390000 | BS5: 16.02 % | BT5: 1390000 | BU5: 16.02 % | BV5: 0 | BW5: 0 | BX5: 8676840 | BY5: 0 | BZ5: 286840 | CA5: 0 | CB5: 8676840 | CC5: 8676840 | CD5: 1390000 | CE5: 16.02 % | CG5: 0 | CI5: 0 | CJ5: 0 | CK5: 0
A6: VOLKSWAGEN | B6: NUEVO TIGUAN TSI AT HIGHLINE 150HP | C6: AU-24-12-0018 | D6: 2023 | E6: 3VVTP65N7NM109254 | F6: MARIA AIDA GONZALEZ PIMENTEL | G6: 1250000 | H6: =G6*100/CC6 -> 5.0471933 | I6: USADOS | J6: Matias Larrain Larrain | K6: 10-01-2025 12:04:28 | L6: 5908 | M6: 16573460 | N6: 2 | O6: VIRGO 1802 | Q6: 993213212 | S6: VITACURA | T6: 03/12/1986 | U6: MARI_GONZALEZ6@HOTMAIL.COM | V6: SVVK61 | W6: STATION WAGON 01 | X6: FAMILIA 1 | Y6: BJ24N611 | Z6: BLANCO PURO | AA6: 3VVTP65N7NM109254 | AB6: 3VVTP65N7NM109254 | AC6: CONSIGNACION USADO (Propio) | AD6: Facturada | AE6: 50815 | AF6: 31-01-2025 0:00:00 | AH6: Contrato: 132 | AI6: 23000000 | AJ6: 31-01-2025 0:00:00 | AL6: 0 | AM6: CHILEAUTOS | AN6: 31-01-2025 0:00:00 | AO6: CC | AP6: Peso | AR6: 49 | AS6: 0 | AT6: 0 | AU6: -1240000 | AV6: 24250000 | AW6: 23000000 | AX6: 1250000 | AY6: 5.15 % | AZ6: 0 | BA6: 516240 | BB6: 516240 | BC6: 0 | BD6: 0 % | BE6: 0 | BF6: 0 | BG6: 0 | BH6: 0 | BI6: 0 % | BJ6: 0 | BK6: 0 | BL6: 0 | BM6: 0 | BN6: 0 % | BO6: 0 | BP6: 24766240 | BQ6: 23516240 | BR6: 1250000 | BS6: 5.05 % | BT6: 1250000 | BU6: 5.05 % | BV6: 0 | BW6: 0 | BX6: 24766240 | BY6: 0 | BZ6: 516240 | CA6: 0 | CB6: 24766240 | CC6: 24766240 | CD6: 1250000 | CE6: 5.05 % | CG6: 0 | CI6: 0 | CJ6: 0 | CK6: 0
A7: VOLKSWAGEN | B7: SAVEIRO 1.6 MT CABINA SIMPLE | C7: AU-24-11-0006 | D7: 2021 | E7: 9BWKB45U6MP038244 | F7: JACQUES WALDEMAR DE HEECKEREN GILDEMEISTER | G7: 713510 | H7: =G7*100/CC7 -> 8.7119658 | I7: USADOS | J7: CLAUDIO ROBLEZ GALAZ | K7: 10-01-2025 13:01:35 | L7: 5910 | M7: 17700661 | N7: 0 | O7: Camino Chabelun Calle Calelo casa 3 ZAPALLAR | P7: 976485003 | Q7: 976485003 | S7: PUCHUNCAVI | T7: 15/03/1991 | U7: Jacquesdhg@gmail.com | V7: PSHT25 | W7: CAMIONETA | X7: SAVEIRO | Y7: 5URTT411 | Z7: BLANCO | AA7: 9BWKB45U6MP038244 | AB7: 9BWKB45U6MP038244 | AC7: CONSIGNACION USADO (Propio) | AD7: Facturada | AE7: 50795 | AF7: 24-01-2025 0:00:00 | AH7: Contrato: 141 | AI7: 7200000 | AJ7: 24-01-2025 0:00:00 | AL7: 0 | AM7: AMIGO | AN7: 24-01-2025 0:00:00 | AO7: FLOTA | AP7: Peso | AR7: 71 | AS7: 0 | AT7: 0 | AU7: -446490 | AV7: 7943510 | AW7: 7200000 | AX7: 743510 | AY7: 9.36 % | AZ7: 0 | BA7: 246490 | BB7: 246490 | BC7: 0 | BD7: 0 % | BE7: 0 | BF7: 0 | BG7: 0 | BH7: 0 | BI7: 0 % | BJ7: 0 | BK7: 0 | BL7: 0 | BM7: 0 | BN7: 0 % | BO7: 0 | BP7: 8190000 | BQ7: 7476490 | BR7: 713510 | BS7: 8.71 % | BT7: 713510 | BU7: 8.71 % | BV7: 0 | BW7: 0 | BX7: 8190000 | BY7: 0 | BZ7: 246490 | CA7: 0 | CB7: 8190000 | CC7: 8190000 | CD7: 713510 | CE7: 8.71 % | CG7: 0 | CI7: 0 | CJ7: 0 | CK7: 30000
A8: VOLKSWAGEN | B8: NIVUS 1.0 TSI AT HIGHLINE HERO | C8: AU-24-12-0025 | D8: 2022 | E8: 9BWCH6CH0NP005357 | F8: ALEJANDRO EDUARDO DONOSO TORRES | G8: 1566505 | H8: =G8*100/CC8 -> 10.113008 | I8: USADOS | J8: CLAUDIO ROBLEZ GALAZ | K8: 13-01-2025 13:35:56 | L8: 5921 | M8: 12486707 | N8: k | O8: ITATA 4425 DEPTO 507 | P8: 995491107 | Q8: 995491107 | S8: ÑUÑOA | T8: 08/03/1973 | U8: ALEJADO@GMAIL.COM | V8: RXTT68 | W8: STATION WAGON | X8: NIVUS | Y8: CH14K315 | Z8: Gris Piedra de Luna | AA8: 9BWCH6CH0NP005357 | AB8: 9BWCH6CH0NP005357 | AC8: CONSIGNACION USADO (Propio) | AD8: Facturada | AE8: 50805 | AF8: 24-01-2025 0:00:00 | AH8: Contrato: 141 | AI8: 13569155 | AJ8: 24-01-2025 0:00:00 | AL8: 0 | AM8: AMIGO | AN8: 24-01-2025 0:00:00 | AO8: RETAIL | AP8: Peso | AR8: 29 | AS8: 0 | AT8: 0 | AU8: -354340 | AV8: 15135660 | AW8: 13569155 | AX8: 1566505 | AY8: 10.35 % | AZ8: 0 | BA8: 354340 | BB8: 354340 | BC8: 0 | BD8: 0 % | BE8: 0 | BF8: 0 | BG8: 0 | BH8: 0 | BI8: 0 % | BJ8: 0 | BK8: 0 | BL8: 0 | BM8: 0 | BN8: 0 % | BO8: 0 | BP8: 15490000 | BQ8: 13923495 | BR8: 1566505 | BS8: 10.11 % | BT8: 1566505 | BU8: 10.11 % | BV8: 0 | BW8: 0 | BX8: 15490000 | BY8: 0 | BZ8: 354340 | CA8: 0 | CB8: 15490000 | CC8: 15490000 | CD8: 1566505 | CE8: 10.11 % | CG8: 0 | CI8: 0 | CJ8: 0 | CK8: 0
A9: VOLKSWAGEN | B9: Nivus 1.0 TSI AT Comfortline 85KW/116CV 5 p | C9: AU-25-01-0008 | D9: 2023 | E9: 9BWCH6CH5PP005986 | F9: MARIA JOSE MONTECINOS ESPINOZA | G9: 3934630 | H9: =G9*100/CC9 -> 26.248366 | I9: USADOS | J9: CLAUDIO ROBLEZ GALAZ | K9: 13-01-2025 18:14:39 | L9: 5923 | M9: 19083401 | N9: 8 | O9: HANNOVER 5331 DEPTO D 307 | P9: 992790275 | Q9: 992790275 | S9: ÑUÑOA | T9: 18/11/1993 | U9: MARIA.MONTECINOSE@GMAIL.COM | V9: TJVT76 | W9: STATION WAGON | X9: FAMILIA 1 | Y9: CH13K311 | Z9: GRIS PLATINO | AA9: 9BWCH6CH5PP005986 | AB9: 9BWCH6CH5PP005986 | AC9: CONSIGNACION USADO (Propio) | AD9: Facturada | AE9: 50806 | AF9: 24-01-2025 0:00:00 | AH9: Contrato: 144 | AI9: 10708530 | AJ9: 24-01-2025 0:00:00 | AL9: 0 | AM9: AMIGO | AN9: 24-01-2025 0:00:00 | AO9: RETAIL | AP9: Peso | AR9: 17 | AS9: 0 | AT9: 0 | AU9: -346840 | AV9: 14643160 | AW9: 10708530 | AX9: 3934630 | AY9: 26.87 % | AZ9: 0 | BA9: 346840 | BB9: 346840 | BC9: 0 | BD9: 0 % | BE9: 0 | BF9: 0 | BG9: 0 | BH9: 0 | BI9: 0 % | BJ9: 0 | BK9: 0 | BL9: 0 | BM9: 0 | BN9: 0 % | BO9: 0 | BP9: 14990000 | BQ9: 11055370 | BR9: 3934630 | BS9: 26.25 % | BT9: 3934630 | BU9: 26.25 % | BV9: 0 | BW9: 0 | BX9: 14990000 | BY9: 0 | BZ9: 346840 | CA9: 0 | CB9: 15188625 | CC9: 14990000 | CD9: 3934630 | CE9: 26.25 % | CG9: 0 | CI9: 0 | CJ9: 0 | CK9: 0
A10: VOLKSWAGEN | B10: Nivus 1.0 TSI AT Highline 85KW/116CV 5 p | C10: AU-24-12-0027 | D10: 2022 | E10: 9BWCH6CH0NP005231 | F10: PATRICIA ANDREA CANCINO MORENO | G10: 1408000 | H10: =G10*100/CC10 -> 9.5199459 | I10: USADOS | J10: SERGIO POBLETE CAMPOS | K10: 14-01-2025 12:06:13 | L10: 5924 | M10: 10614054 | N10: 5 | O10: ATAHUALPA 235 DTO/402 -D | P10: 977673383 | S10: LA FLORIDA | T10: 14/11/1974 | U10: patriacancino14@gmail.com | V10: RWZT72 | W10: STATION WAGON | X10: FAMILIA 1 | Y10: CH14K311 | Z10: Gris Piedra de Luna | AA10: 9BWCH6CH0NP005231 | AB10: 9BWCH6CH0NP005231 | AC10: CONSIGNACION USADO (Propio) | AD10: Facturada | AE10: 50803 | AF10: 24-01-2025 0:00:00 | AH10: Contrato: 105 | AI10: 13000000 | AJ10: 23-02-2025 0:00:00 | AL10: 0 | AM10: SALON | AN10: 23-02-2025 0:00:00 | AO10: CC | AP10: Peso | AR10: 24 | AS10: 0 | AT10: 0 | AU10: -382000 | AV10: 14408000 | AW10: 13000000 | AX10: 1408000 | AY10: 9.77 % | AZ10: 0 | BA10: 382000 | BB10: 382000 | BC10: 0 | BD10: 0 % | BE10: 0 | BF10: 0 | BG10: 0 | BH10: 0 | BI10: 0 % | BJ10: 0 | BK10: 0 | BL10: 0 | BM10: 0 | BN10: 0 % | BO10: 0 | BP10: 14790000 | BQ10: 13382000 | BR10: 1408000 | BS10: 9.52 % | BT10: 1408000 | BU10: 9.52 % | BV10: 0 | BW10: 0 | BX10: 14790000 | BY10: 0 | BZ10: 382000 | CA10: 0 | CB10: 14825000 | CC10: 14790000 | CD10: 1408000 | CE10: 9.52 % | CG10: 0 | CI10: 0 | CJ10: 0 | CK10: 0
A11: MITSUBISHI | B11: CROSS RX 1.5T AT | C11: AU-24-11-0002 | D11: 2020 | E11: JMYXTGK1WKZ000444 | F11: NATALIA ELIZABETH PAREDES FLORES | G11: 1794160 | H11: =G11*100/CC11 -> 14.183083 | I11: USADOS | J11: Matias Larrain Larrain | K11: 14-01-2025 18:38:37 | L11: 5928 | M11: 17768585 | N11: 2 | O11: PADRE TADEO 5017 | Q11: 973385973 | S11: QUINTA NORMAL | T11: 27/02/1991 | U11: NAATALIAP.FLORES@GMAIL.COM | V11: LSKW61 | W11: STATION WAGON | X11: ECLIPSE | Y11: CROSS RX 1.5T AT | Z11: ROJO | AA11: JMYXTGK1WKZ000444 | AB11: JMYXTGK1WKZ000444 | AC11: CONSIGNACION USADO (Propio) | AD11: Facturada | AE11: 50797 | AF11: 24-01-2025 0:00:00 | AH11: Contrato: 132 | AI11: 10500000 | AJ11: 24-01-2025 0:00:00 | AL11: 0 | AM11: CHILEAUTOS | AN11: 24-01-2025 0:00:00 | AO11: CC | AP11: Peso | AR11: 79 | AS11: 0 | AT11: 0 | AU11: -695840 | AV11: 12294160 | AW11: 10500000 | AX11: 1794160 | AY11: 14.59 % | AZ11: 0 | BA11: 355840 | BB11: 355840 | BC11: 0 | BD11: 0 % | BE11: 0 | BF11: 0 | BG11: 0 | BH11: 0 | BI11: 0 % | BJ11: 0 | BK11: 0 | BL11: 0 | BM11: 0 | BN11: 0 % | BO11: 0 | BP11: 12650000 | BQ11: 10855840 | BR11: 1794160 | BS11: 14.18 % | BT11: 1794160 | BU11: 14.18 % | BV11: 0 | BW11: 0 | BX11: 12650000 | BY11: 0 | BZ11: 355840 | CA11: 0 | CB11: 12650000 | CC11: 12650000 | CD11: 1794160 | CE11: 14.18 % | CG11: 0 | CI11: 0 | CJ11: 0 | CK11: 0
A12: SUZUKI | B12: SWIFT GLX HB 1.2 | C12: AU-24-12-0028 | D12: 2022 | E12: JS2ZC13S5N6400051 | F12: MAX DOLLMANN DEL SANTE | G12: 1416010 | H12: =G12*100/CC12 -> 13.111204 | I12: USADOS | J12: CLAUDIO ROBLEZ GALAZ | K12: 15-01-2025 11:25:59 | L12: 5930 | M12: 22040901 | N12: 5 | O12: CAMINO EL ATAJO 10444 | P12: 942143668 | Q12: 942143668 | S12: LO BARNECHEA | T12: 01/08/2006 | U12: MAXDOLLMANN7@GMAIL.COM | V12: RHZL77 | W12: AUTOMOVIL | X12: SUZUKI | Y12: 25--86342 | Z12: AZUL | AA12: JS2ZC13S5N6400051 | AB12: JS2ZC13S5N6400051 | AC12: CONSIGNACION USADO (Propio) | AD12: Facturada | AE12: 50796 | AF12: 24-01-2025 0:00:00 | AH12: Contrato: 132 | AI12: 9100000 | AJ12: 24-01-2025 0:00:00 | AL12: 0 | AM12: AMIGO | AN12: 24-01-2025 0:00:00 | AO12: RETAIL | AP12: Peso | AR12: 24 | AS12: 0 | AT12: 0 | AU12: -473990 | AV12: 10516010 | AW12: 9100000 | AX12: 1416010 | AY12: 13.47 % | AZ12: 0 | BA12: 283990 | BB12: 283990 | BC12: 0 | BD12: 0 % | BE12: 0 | BF12: 0 | BG12: 0 | BH12: 0 | BI12: 0 % | BJ12: 0 | BK12: 0 | BL12: 0 | BM12: 0 | BN12: 0 % | BO12: 0 | BP12: 10800000 | BQ12: 9383990 | BR12: 1416010 | BS12: 13.11 % | BT12: 1416010 | BU12: 13.11 % | BV12: 0 | BW12: 0 | BX12: 10800000 | BY12: 0 | BZ12: 283990 | CA12: 0 | CB12: 10800000 | CC12: 10800000 | CD12: 1416010 | CE12: 13.11 % | CG12: 0 | CI12: 0 | CJ12: 0 | CK12: 0
A13: VOLKSWAGEN | B13: Nivus 1.0 TSI AT Comfortline 85KW/116CV 5 p | C13: AU-24-10-0041 | D13: 2023 | E13: 9BWCH6CHXNP033859 | F13: MARIA AMELIA ROBLES VIVANCO | G13: 817183 | H13: =G13*100/CC13 -> 5.3410654 | I13: USADOS | J13: Marcos Ignacio Campos Zavala | K13: 15-01-2025 17:10:16 | L13: 5932 | M13: 12721422 | N13: 0 | O13: REY GUSTAVO ADOLFO 4620 DPTO 62 | Q13: 962067354 | S13: LAS CONDES | T13: 27/05/1975 | U13: MARIAMELIA.ROBLES@GMAIL.COM | V13: TBFD95 | W13: STATION WAGON | X13: FAMILIA 1 | Y13: CH13K316 | Z13: GRIS | AA13: 9BWCH6CHXNP033859 | AB13: 9BWCH6CHXNP033859 | AC13: CONSIGNACION USADO (Propio) | AD13: Facturada | AE13: 50809 | AF13: 30-01-2025 0:00:00 | AH13: Contrato: 141 | AI13: 14092337 | AJ13: 30-01-2025 0:00:00 | AL13: 0 | AM13: WEB CONCESIONARIO | AN13: 30-01-2025 0:00:00 | AO13: RETAIL | AP13: Peso | AR13: 86 | AS13: 0 | AT13: 0 | AU13: -580480 | AV13: 14909520 | AW13: 14092337 | AX13: 817183 | AY13: 5.48 % | AZ13: 0 | BA13: 390480 | BB13: 390480 | BC13: 0 | BD13: 0 % | BE13: 0 | BF13: 0 | BG13: 0 | BH13: 0 | BI13: 0 % | BJ13: 0 | BK13: 0 | BL13: 0 | BM13: 0 | BN13: 0 % | BO13: 0 | BP13: 15300000 | BQ13: 14482817 | BR13: 817183 | BS13: 5.34 % | BT13: 817183 | BU13: 5.34 % | BV13: 0 | BW13: 0 | BX13: 15300000 | BY13: 0 | BZ13: 390480 | CA13: 0 | CB13: 15680428 | CC13: 15300000 | CD13: 817183 | CE13: 5.34 % | CG13: 0 | CI13: 0 | CJ13: 0 | CK13: 0
A14: VOLKSWAGEN | B14: NUEVO JETTA 2.0 TSI AT GLI | C14: AU-24-10-0018 | D14: 2025 | E14: 3VW2E6BU7RM073645 | F14: SEBASTIAN FRANCISCO PLAZA SALAS | G14: 3146285 | H14: =G14*100/CC14 -> 11.509619 | I14: USADOS | J14: JUAN PABLO GONZALEZ ACUÑA | K14: 16-01-2025 18:06:43 | L14: 5935 | M14: 15469672 | N14: 5 | O14: SERRANO 62 DPTO 612 | P14: 956295315 | S14: SANTIAGO | T14: 28/05/1982 | U14: plaza.sebastian@gmail.com | V14: TTRR50 | W14: AUTOMOVIL | X14: FAMILIA 1 | Y14: BU49UZ11 | Z14: GRIS PURO | AA14: 3VW2E6BU7RM073645 | AB14: 3VW2E6BU7RM073645 | AC14: CONSIGNACION USADO (Propio) | AD14: Parcial Facturada | AE14: 50793 | AF14: 21-01-2025 0:00:00 | AH14: Contrato: 132 | AI14: 23359950 | AJ14: 21-01-2025 0:00:00 | AL14: 0 | AM14: SALON | AN14: 21-01-2025 0:00:00 | AO14: RETAIL | AP14: Peso | AQ14: TKWX97 | AR14: 94 | AS14: 0 | AT14: -260420 | AU14: 0 | AV14: 26180100 | AW14: 23359950 | AX14: 2820150 | AY14: 10.77 % | AZ14: 0 | BA14: 819900 | BB14: 819900 | BC14: 0 | BD14: 0 % | BE14: 240000 | BF14: 336135 | BG14: 0 | BH14: 0 | BI14: 0 % | BJ14: 0 | BK14: 0 | BL14: 0 | BM14: 0 | BN14: 0 % | BO14: -260420 | BP14: 27336135 | BQ14: 24189850 | BR14: 3146285 | BS14: 11.51 % | BT14: 3146285 | BU14: 11.51 % | BV14: 0 | BW14: 8500000 | BX14: 18900000 | BY14: 0 | BZ14: 819900 | CA14: 336134 | CB14: 27160000 | CC14: 27336135 | CD14: 3146285 | CE14: 11.51 % | CG14: 0 | CI14: 0 | CJ14: 0 | CK14: 10000
A15: VOLKSWAGEN | B15: ATLAS COMFORTLINE 3.6 V6 4 MOTION | C15: AU-24-10-0034 | D15: 2020 | E15: IV2LR2CA4KC512881 | F15: SEBASTIAN BROWNE URREJOLA | G15: 2290738 | H15: =G15*100/CC15 -> 9.7615331 | I15: USADOS | J15: CLAUDIO ROBLEZ GALAZ | K15: 17-01-2025 12:39:25 | L15: 5936 | M15: 16100242 | N15: 9 | O15: CAMINO VILLARRICA - PUCON KM5 CONDOMINIO PARQUE DEL LAGO CASA 48 | P15: 999694006 | Q15: 999694006 | S15: VILLARRICA | T15: 06/12/1985 | U15: sbrowneru@gmail.com | V15: PGKT34 | W15: STATION WAGON 01 | X15: FAMILIA 1 | Y15: 10--98635 | Z15: BLANCO | AA15: IV2LR2CA4KC512881 | AB15: IV2LR2CA4KC512881 | AC15: CONSIGNACION USADO (Propio) | AD15: Facturada | AE15: 50801 | AF15: 24-01-2025 0:00:00 | AH15: Contrato: 144 | AI15: 20000000 | AJ15: 24-01-2025 0:00:00 | AL15: 0 | AM15: AMIGO | AN15: 24-01-2025 0:00:00 | AO15: RETAIL | AP15: Peso | AR15: 88 | AS15: 0 | AT15: 0 | AU15: -475000 | AV15: 23015000 | AW15: 20000000 | AX15: 3015000 | AY15: 13.1 % | AZ15: 0 | BA15: 451990 | BB15: 451990 | BC15: 0 | BD15: 0 % | BE15: 0 | BF15: 0 | BG15: 0 | BH15: 0 | BI15: 0 % | BJ15: 0 | BK15: 0 | BL15: 0 | BM15: 0 | BN15: 0 % | BO15: 0 | BP15: 23466990 | BQ15: 21176252 | BR15: 2290738 | BS15: 9.76 % | BT15: 2290738 | BU15: 9.76 % | BV15: 0 | BW15: 0 | BX15: 23466990 | BY15: 0 | BZ15: 451990 | CA15: 0 | CB15: 23466990 | CC15: 23466990 | CD15: 2290738 | CE15: 9.76 % | CG15: 0 | CI15: 0 | CJ15: 0 | CK15: 724262
A16: MAZDA | B16: MAZDA CX9 AT | C16: AU-24-11-0009 | D16: 2017 | E16: JM7TC4WLAH0108006 | F16: INMOBILIARIA NUEVA VIDA SPA | G16: 1643283 | H16: =G16*100/CC16 -> 10.270519 | I16: USADOS | J16: CLAUDIO ROBLEZ GALAZ | K16: 20-01-2025 16:39:54 | L16: 5941 | M16: 77604756 | N16: 2 | O16: Cerro Las Arañas 12201 | P16: 956086362 | Q16: 956086362 | S16: LO BARNECHEA | T16: 01/01/1900 | U16: IVOLANTE@AURYN.CL | V16: JWCP95 | W16: STATION WAGON 01 | X16: MAZDA 3 | Y16: 15--CXO9 | Z16: BLANCO | AA16: JM7TC4WLAH0108006 | AB16: JM7TC4WLAH0108006 | AC16: CONSIGNACION USADO (Propio) | AD16: Facturada | AE16: 50804 | AF16: 24-01-2025 0:00:00 | AH16: Contrato: 132 | AI16: 13500000 | AJ16: 24-01-2025 0:00:00 | AL16: 0 | AM16: AMIGO | AN16: 24-01-2025 0:00:00 | AO16: FLOTA | AP16: Peso | AR16: 71 | AS16: 0 | AT16: 0 | AU16: -951990 | AV16: 15638010 | AW16: 13500000 | AX16: 2138010 | AY16: 13.67 % | AZ16: 0 | BA16: 361990 | BB16: 361990 | BC16: 0 | BD16: 0 % | BE16: 0 | BF16: 0 | BG16: 0 | BH16: 0 | BI16: 0 % | BJ16: 0 | BK16: 0 | BL16: 0 | BM16: 0 | BN16: 0 % | BO16: 0 | BP16: 16000000 | BQ16: 14356717 | BR16: 1643283 | BS16: 10.27 % | BT16: 1643283 | BU16: 10.27 % | BV16: 0 | BW16: 0 | BX16: 16000000 | BY16: 0 | BZ16: 361990 | CA16: 0 | CB16: 16000000 | CC16: 16000000 | CD16: 1643283 | CE16: 10.27 % | CG16: 0 | CI16: 0 | CJ16: 0 | CK16: 494727
A17: VOLKSWAGEN | B17: GOL GP HB TRENDLINE 1.6 | C17: AU-24-10-0016 | D17: 2021 | E17: 9BWAB45UOMT112292 | F17: NICOLAS BUSTAMANTE OLMEDO | G17: 537920 | H17: =G17*100/CC17 -> 7.6955651 | I17: USADOS | J17: Marcos Ignacio Campos Zavala | K17: 21-01-2025 13:39:46 | L17: 5944 | M17: 20445310 | N17: 1 | O17: VITACURA 10108 DPTO 40 | Q17: 982591707 | S17: VITACURA | T17: 21/12/2000 | U17: NBUSTAMANTEOLMEDO@GMAIL.COM | V17: PCWF83 | W17: AUTOMOVIL | X17: GOL | Y17: 10--GOLGP | Z17: BLANCO CANDY | AA17: 9BWAB45UOMT112292 | AB17: 9BWAB45UOMT112292 | AC17: CONSIGNACION USADO (Propio) | AD17: Facturada | AE17: 50807 | AF17: 30-01-2025 0:00:00 | AH17: Contrato: 105 | AI17: 6186080 | AJ17: 01-03-2025 0:00:00 | AL17: 0 | AM17: WEB CONCESIONARIO | AN17: 01-03-2025 0:00:00 | AO17: RETAIL | AP17: Peso | AR17: 104 | AS17: 0 | AT17: 0 | AU17: -266000 | AV17: 6724000 | AW17: 6186080 | AX17: 537920 | AY17: 8 % | AZ17: 0 | BA17: 266000 | BB17: 266000 | BC17: 0 | BD17: 0 % | BE17: 0 | BF17: 0 | BG17: 0 | BH17: 0 | BI17: 0 % | BJ17: 0 | BK17: 0 | BL17: 0 | BM17: 0 | BN17: 0 % | BO17: 0 | BP17: 6990000 | BQ17: 6452080 | BR17: 537920 | BS17: 7.7 % | BT17: 537920 | BU17: 7.7 % | BV17: 0 | BW17: 0 | BX17: 6990000 | BY17: 0 | BZ17: 266000 | CA17: 0 | CB17: 6990000 | CC17: 6990000 | CD17: 537920 | CE17: 7.7 % | CG17: 0 | CI17: 0 | CJ17: 0 | CK17: 0
A18: VOLKSWAGEN | B18: Nuevo T-Cross TSI MT Comfortline - 70 kW/95 CV | C18: AU-25-01-0005 | D18: 2021 | E18: 9BWBL6BF6L4060467 | F18: MARISOL PATRICIA GALLEGUILLOS BERINDOAGUE | G18: 1250000 | H18: =G18*100/CC18 -> 12.122999 | I18: USADOS | J18: Manuel Rodrigo Hurtado Melo | K18: 23-01-2025 13:07:11 | L18: 5953 | M18: 16406388 | N18: 7 | O18: BELPASSO 1018 | Q18: 962551445 | S18: SAN BERNARDO | T18: 16/04/1986 | U18: MAGABERIN@GMAIL.COM | V18: PHXZ46 | W18: STATION WAGON | X18: FAMILIA 1 | Y18: 08032022 | Z18: GRIS PLATINO | AA18: 9BWBL6BF6L4060467 | AB18: 9BWBL6BF6L4060467 | AC18: CONSIGNACION USADO (Propio) | AD18: Facturada | AE18: 50810 | AF18: 30-01-2025 0:00:00 | AH18: Contrato: 143 | AI18: 8750000 | AJ18: 30-01-2025 0:00:00 | AL18: 0 | AM18: SITIO WEB | AN18: 30-01-2025 0:00:00 | AO18: RETAIL | AP18: Peso | AR18: 17 | AS18: 0 | AT18: 0 | AU18: -590000 | AV18: 10000000 | AW18: 8750000 | AX18: 1250000 | AY18: 12.5 % | AZ18: 0 | BA18: 310980 | BB18: 310980 | BC18: 0 | BD18: 0 % | BE18: 0 | BF18: 0 | BG18: 0 | BH18: 0 | BI18: 0 % | BJ18: 0 | BK18: 0 | BL18: 0 | BM18: 0 | BN18: 0 % | BO18: 0 | BP18: 10310980 | BQ18: 9060980 | BR18: 1250000 | BS18: 12.12 % | BT18: 1250000 | BU18: 12.12 % | BV18: 0 | BW18: 0 | BX18: 10310980 | BY18: 0 | BZ18: 310980 | CA18: 0 | CB18: 10310980 | CC18: 10310980 | CD18: 1250000 | CE18: 12.12 % | CG18: 0 | CI18: 0 | CJ18: 0 | CK18: 0
A19: VOLKSWAGEN | B19: NUEVO T-CROSS COMFORTLINE 1.6L MT 110HP | C19: AU-24-12-0010 | D19: 2021 | E19: 9BWBL6BF4L4057115 | F19: JUAN SEBASTIAN GALLARDO MARDONES | G19: 755088 | H19: =G19*100/CC19 -> 6.6668668 | I19: USADOS | J19: Manuel Rodrigo Hurtado Melo | K19: 23-01-2025 19:14:54 | L19: 5955 | M19: 16074803 | N19: 6 | O19: AVENIDA MEXICO 2227 CASA 100 | Q19: 950972864 | S19: PUENTE ALTO | T19: 17/02/1986 | U19: SEBA.GMARDONES@GMAIL.COM | V19: PCZX75 | W19: STATION WAGON | X19: FAMILIA 1 | Y19: BF13T412 | Z19: GRAFITO OSCURO | AA19: 9BWBL6BF4L4057115 | AB19: 9BWBL6BF4L4057115 | AC19: CONSIGNACION USADO (Propio) | AD19: Facturada | AE19: 50818 | AF19: 31-01-2025 0:00:00 | AH19: Contrato: 132 | AI19: 10000000 | AJ19: 31-01-2025 0:00:00 | AL19: 0 | AM19: SITIO WEB | AN19: 31-01-2025 0:00:00 | AO19: RETAIL | AP19: Peso | AR19: 58 | AS19: 0 | AT19: 0 | AU19: -690000 | AV19: 11000000 | AW19: 10000000 | AX19: 1000000 | AY19: 9.09 % | AZ19: 0 | BA19: 325980 | BB19: 325980 | BC19: 0 | BD19: 0 % | BE19: 0 | BF19: 0 | BG19: 0 | BH19: 0 | BI19: 0 % | BJ19: 0 | BK19: 0 | BL19: 0 | BM19: 0 | BN19: 0 % | BO19: 0 | BP19: 11325980 | BQ19: 10570892 | BR19: 755088 | BS19: 6.67 % | BT19: 755088 | BU19: 6.67 % | BV19: 0 | BW19: 0 | BX19: 11335980 | BY19: -10000 | BZ19: 325980 | CA19: 0 | CB19: 11325980 | CC19: 11325980 | CD19: 755088 | CE19: 6.67 % | CG19: 0 | CI19: 0 | CJ19: 0 | CK19: 244912
A20: VOLKSWAGEN | B20: NUEVO JETTA 1.4 TSI AT COMFORTLINE SKY | C20: AU-24-10-0021 | D20: 2025 | E20: 3VWLP6BU3RM101844 | F20: Rodrigo Andres Valenzuela Acevedo | G20: =1740518+150000 -> 1890518 | H20: =G20*100/CC20 -> 9.0786539 | I20: USADOS | J20: SERGIO POBLETE CAMPOS | K20: 24-01-2025 11:03:13 | L20: 5957 | M20: 13682729 | N20: 4 | O20: Jorge Valdes Perez 3139 | P20: 952162022 | S20: BUIN | T20: 14/03/1979 | U20: rodrigoctv@gmail.com | V20: TTRR73 | W20: AUTOMOVIL | X20: FAMILIA 1 | Y20: 10--BU43LY11 | Z20: GRIS PLATINO | AA20: 3VWLP6BU3RM101844 | AB20: 3VWLP6BU3RM101844 | AC20: CONSIGNACION USADO (Propio) | AD20: Facturada | AE20: 50800 | AF20: 27-01-2025 0:00:00 | AH20: Contrato: 143 | AI20: 18555482 | AJ20: 26-02-2025 0:00:00 | AL20: 0 | AM20: SALON | AN20: 26-02-2025 0:00:00 | AO20: CC | AP20: Peso | AQ20: PCYS71 | AR20: 100 | AS20: 0 | AT20: 0 | AU20: -684000 | AV20: 20306000 | AW20: 18555482 | AX20: 1750518 | AY20: 8.62 % | AZ20: 0 | BA20: 517770 | BB20: 517770 | BC20: 0 | BD20: 0 % | BE20: 0 | BF20: 0 | BG20: 0 | BH20: 0 | BI20: 0 % | BJ20: 0 | BK20: 0 | BL20: 0 | BM20: 0 | BN20: 0 % | BO20: 0 | BP20: 20823770 | BQ20: 19083252 | BR20: 1740518 | BS20: 8.36 % | BT20: 1740518 | BU20: 8.36 % | BV20: 0 | BW20: 8431850 | BX20: 18782230 | BY20: -6390310 | BZ20: 517770 | CA20: 0 | CB20: 20823770 | CC20: 20823770 | CD20: 1740518 | CE20: 8.36 % | CG20: 0 | CI20: 0 | CJ20: 0 | CK20: 10000
A21: TOYOTA | B21: XLI 1.3 | C21: AU-25-01-0017 | D21: 2013 | E21: JTDJW9D35DD531768 | F21: BENJAMIN FLOREZ LABRA | G21: 0 | H21: =G21*100/CC21 -> 0 | I21: USADOS | J21: RODRIGO MONTANER CABEZON | K21: 27-01-2025 10:38:49 | L21: 5959 | M21: 5713005 | N21: 9 | O21: AV. OSSA 953 | P21: 992309752 | S21: LA REINA | T21: 03/10/1951 | U21: bb@bjk.cl | V21: FRTD28 | W21: AUTOMOVIL | X21: YARIS | Y21: XLI 1.3 | Z21: GRIS OSCURO | AA21: JTDJW9D35DD531768 | AC21: CONSIGNACION USADO (Propio) | AD21: Facturada | AE21: 50802 | AF21: 24-01-2025 0:00:00 | AH21: Contrato: 141 | AI21: 2000000 | AJ21: 24-01-2025 0:00:00 | AL21: 0 | AM21: SALON | AN21: 24-01-2025 0:00:00 | AO21: RETAIL | AP21: Peso | AR21: 3 | AS21: 0 | AT21: 0 | AU21: 0 | AV21: 2000000 | AW21: 2000000 | AX21: 0 | AY21: 0 % | AZ21: 0 | BA21: 0 | BB21: 0 | BC21: 0 | BD21: 0 % | BE21: 0 | BF21: 0 | BG21: 0 | BH21: 0 | BI21: 0 % | BJ21: 0 | BK21: 0 | BL21: 0 | BM21: 0 | BN21: 0 % | BO21: 0 | BP21: 2000000 | BQ21: 2000000 | BR21: 0 | BS21: 0 % | BT21: 0 | BU21: 0 % | BV21: 0 | BW21: 0 | BX21: 2000000 | BY21: 0 | BZ21: 0 | CA21: 0 | CB21: 2000000 | CC21: 2000000 | CD21: 0 | CE21: 0 % | CG21: 0 | CI21: 0 | CJ21: 0 | CK21: 0
A22: FORD | B22: ESCAPE SE 2.0L ECOBOOST 4X2 AT | C22: AU-24-12-0026 | D22: 2015 | E22: WF0AXXWPMAFC58745 | F22: JOSE MIGUEL DROGUET FREDES | G22: 1686670 | H22: =G22*100/CC22 -> 22.518959 | I22: USADOS | J22: Manuel Rodrigo Hurtado Melo | K22: 28-01-2025 16:56:15 | L22: 5961 | M22: 18496649 | N22: 2 | O22: GENERAL CAROL URZUA 6950 DEPTO 502 | Q22: 997223454 | S22: LAS CONDES | T22: 30/04/1993 | U22: JOSE.DROGUET.F@GMAIL.COM | V22: HHVT31 | W22: STATION WAGON 01 | X22: FORD | Y22: 8--53623 | Z22: NEGRO | AA22: WF0AXXWPMAFC58745 | AB22: WF0AXXWPMAFC58745 | AC22: CONSIGNACION USADO (Propio) | AD22: Facturada | AE22: 50811 | AF22: 31-01-2025 0:00:00 | AH22: Contrato: 132 | AI22: 5500000 | AJ22: 31-01-2025 0:00:00 | AL22: 0 | AM22: SITIO WEB | AN22: 31-01-2025 0:00:00 | AO22: RETAIL | AP22: Peso | AQ22: FZXD | AR22: 32 | AS22: 0 | AT22: 0 | AU22: -303330 | AV22: 7186670 | AW22: 5500000 | AX22: 1686670 | AY22: 23.47 % | AZ22: 0 | BA22: 303330 | BB22: 303330 | BC22: 0 | BD22: 0 % | BE22: 0 | BF22: 0 | BG22: 0 | BH22: 0 | BI22: 0 % | BJ22: 0 | BK22: 0 | BL22: 0 | BM22: 0 | BN22: 0 % | BO22: 0 | BP22: 7490000 | BQ22: 5803330 | BR22: 1686670 | BS22: 22.52 % | BT22: 1686670 | BU22: 22.52 % | BV22: 0 | BW22: 5600000 | BX22: 1890000 | BY22: 0 | BZ22: 303330 | CA22: 0 | CB22: 7525000 | CC22: 7490000 | CD22: 1686670 | CE22: 22.52 % | CG22: 0 | CI22: 0 | CJ22: 0 | CK22: 0
A23: VOLKSWAGEN | B23: SAVEIRO POWER PLUS 1.6 | C23: AU-24-11-0021 | D23: 2018 | E23: 9BWKB45U7JP088596 | F23: MIGUEL ANGEL QUEZADA OLIVARES | G23: 891068 | H23: =G23*100/CC23 -> 14.875927 | I23: USADOS | J23: SERGIO POBLETE CAMPOS | K23: 29-01-2025 17:38:56 | L23: 5965 | M23: 12214885 | N23: 8 | O23: OFICINA LINA 235 CONDOMINIO PATAGUAL | Q23: 961112997 | S23: ANTOFAGASTA | T23: 01/01/1980 | U23: mquezada72@gmail.com | V23: KHTB67 | W23: CAMIONETA | X23: PICK UP | Y23: 10--saveipow | Z23: GRIS PLATINO | AA23: 9BWKB45U7JP088596 | AB23: 9BWKB45U7JP088596 | AC23: CONSIGNACION USADO (Propio) | AD23: Facturada | AE23: 50820 | AF23: 31-01-2025 0:00:00 | AH23: Contrato: 105 | AI23: 4500000 | AJ23: 02-03-2025 0:00:00 | AL23: 0 | AM23: SALON | AN23: 02-03-2025 0:00:00 | AO23: CC | AP23: Peso | AR23: 58 | AS23: 0 | AT23: 0 | AU23: -284000 | AV23: 5706000 | AW23: 4500000 | AX23: 1206000 | AY23: 21.14 % | AZ23: 0 | BA23: 284000 | BB23: 284000 | BC23: 0 | BD23: 0 % | BE23: 0 | BF23: 0 | BG23: 0 | BH23: 0 | BI23: 0 % | BJ23: 0 | BK23: 0 | BL23: 0 | BM23: 0 | BN23: 0 % | BO23: 0 | BP23: 5990000 | BQ23: 5098932 | BR23: 891068 | BS23: 14.88 % | BT23: 891068 | BU23: 14.88 % | BV23: 0 | BW23: 0 | BX23: 5990000 | BY23: 0 | BZ23: 284000 | CA23: 0 | CB23: 5990000 | CC23: 5990000 | CD23: 891068 | CE23: 14.88 % | CG23: 0 | CI23: 0 | CJ23: 0 | CK23: 314932
A24: HYUNDAI | B24: I 10 | C24: AU-25-01-0013 | D24: 2024 | E24: MALB251CARM531718 | F24: ERICK MATIAS LIZANA CALDERON | G24: 500000 | H24: =G24*100/CC24 -> 5.3590683 | I24: USADOS | J24: Manuel Rodrigo Hurtado Melo | K24: 29-01-2025 19:01:39 | L24: 5966 | M24: 18761500 | N24: 3 | O24: EYZAGUIIRRE 295 | Q24: 972979764 | S24: PUENTE ALTO | T24: 20/01/1995 | U24: erick_lizana@hotmail.com | V24: TKWX97 | W24: AUTOMOVIL 01 | X24: ATOS | Y24: 2--025 | Z24: BLANCO | AA24: MALB251CARM531718 | AB24: MALB251CARM531718 | AC24: CONSIGNACION USADO (Propio) | AD24: Facturada | AE24: 50821 | AF24: 31-01-2025 0:00:00 | AH24: Contrato: 141 | AI24: 8500000 | AJ24: 31-01-2025 0:00:00 | AL24: 0 | AM24: SITIO WEB | AN24: 31-01-2025 0:00:00 | AO24: RETAIL | AP24: Peso | AR24: 11 | AS24: 0 | AT24: 0 | AU24: -590000 | AV24: 9000000 | AW24: 8500000 | AX24: 500000 | AY24: 5.56 % | AZ24: 0 | BA24: 329980 | BB24: 329980 | BC24: 0 | BD24: 0 % | BE24: 0 | BF24: 0 | BG24: 0 | BH24: 0 | BI24: 0 % | BJ24: 0 | BK24: 0 | BL24: 0 | BM24: 0 | BN24: 0 % | BO24: 0 | BP24: 9329980 | BQ24: 8829980 | BR24: 500000 | BS24: 5.36 % | BT24: 500000 | BU24: 5.36 % | BV24: 0 | BW24: 0 | BX24: 9329980 | BY24: 0 | BZ24: 329980 | CA24: 0 | CB24: 9329980 | CC24: 9329980 | CD24: 500000 | CE24: 5.36 % | CG24: 0 | CI24: 0 | CJ24: 0 | CK24: 0
A25: VOLKSWAGEN | B25: BORA | C25: AU-25-01-0015 | D25: 2011 | E25: 3VWYV49M5AM044685 | F25: ORTUZAR SPA | G25: 400000 | H25: =G25*100/CC25 -> 15.384615 | I25: USADOS | J25: RODRIGO MONTANER CABEZON | K25: 30-01-2025 16:58:59 | L25: 5967 | M25: 76981608 | N25: 9 | O25: FRANCISCO BILBAO N° 4740 | Q25: 985775766 | S25: LAS CONDES | U25: francisco.ortuzar@mail.udp.cl | V25: CJFV96 | W25: AUTOMOVIL 01 | X25: BORA | Y25: 10--BORA | Z25: BLANCO LASER | AA25: 3VWYV49M5AM044685 | AB25: 3VWYV49M5AM044685 | AC25: CONSIGNACION USADO (Propio) | AD25: Facturada | AE25: 50813 | AF25: 31-01-2025 0:00:00 | AH25: Contrato: 132 | AI25: 2200000 | AJ25: 31-01-2025 0:00:00 | AL25: 0 | AM25: SALON | AN25: 31-01-2025 0:00:00 | AO25: RETAIL | AP25: Peso | AR25: 10 | AS25: 0 | AT25: 0 | AU25: 0 | AV25: 2600000 | AW25: 2200000 | AX25: 400000 | AY25: 15.38 % | AZ25: 0 | BA25: 0 | BB25: 0 | BC25: 0 | BD25: 0 % | BE25: 0 | BF25: 0 | BG25: 0 | BH25: 0 | BI25: 0 % | BJ25: 0 | BK25: 0 | BL25: 0 | BM25: 0 | BN25: 0 % | BO25: 0 | BP25: 2600000 | BQ25: 2200000 | BR25: 400000 | BS25: 15.38 % | BT25: 400000 | BU25: 15.38 % | BV25: 0 | BW25: 0 | BX25: 2600000 | BY25: 0 | BZ25: 0 | CA25: 0 | CB25: 2600000 | CC25: 2600000 | CD25: 400000 | CE25: 15.38 % | CG25: 0 | CI25: 0 | CJ25: 0 | CK25: 0
A26: CHANGAN | B26: LUXURY | C26: AU-25-01-0012 | D26: 2015 | E26: LS5A3DBE3FA955810 | F26: ORTUZAR SPA | G26: 300000 | H26: =G26*100/CC26 -> 7.8947368 | I26: USADOS | J26: RODRIGO MONTANER CABEZON | K26: 30-01-2025 17:01:36 | L26: 5968 | M26: 76981608 | N26: 9 | O26: FRANCISCO BILBAO N° 4740 | Q26: 985775766 | S26: LAS CONDES | U26: francisco.ortuzar@mail.udp.cl | V26: HLRT60 | W26: AUTOMOVIL | X26: CS 35 1.6 | Y26: 3658 | Z26: BEIGE ARENA | AA26: LS5A3DBE3FA955810 | AB26: LS5A3DBE3FA955810 | AC26: CONSIGNACION USADO (Propio) | AD26: Facturada | AE26: 50812 | AF26: 31-01-2025 0:00:00 | AH26: Contrato: 105 | AI26: 3500000 | AJ26: 31-01-2025 0:00:00 | AL26: 0 | AM26: SALON | AN26: 31-01-2025 0:00:00 | AO26: RETAIL | AP26: Peso | AR26: 10 | AS26: 0 | AT26: 0 | AU26: 0 | AV26: 3800000 | AW26: 3500000 | AX26: 300000 | AY26: 7.89 % | AZ26: 0 | BA26: 0 | BB26: 0 | BC26: 0 | BD26: 0 % | BE26: 0 | BF26: 0 | BG26: 0 | BH26: 0 | BI26: 0 % | BJ26: 0 | BK26: 0 | BL26: 0 | BM26: 0 | BN26: 0 % | BO26: 0 | BP26: 3800000 | BQ26: 3500000 | BR26: 300000 | BS26: 7.89 % | BT26: 300000 | BU26: 7.89 % | BV26: 0 | BW26: 0 | BX26: 3800000 | BY26: 0 | BZ26: 0 | CA26: 0 | CB26: 3800000 | CC26: 3800000 | CD26: 300000 | CE26: 7.89 % | CG26: 0 | CI26: 0 | CJ26: 0 | CK26: 0
A27: VOLKSWAGEN | B27: SAVEIRO 1.6 MT CABINA SIMPLE | C27: AU-24-12-0021 | D27: 2019 | E27: 9BWKB45U5JP102012 | F27: LUDWING CESAR GUTIERREZ SUAREZ | G27: 1060111 | H27: =G27*100/CC27 -> 15.612828 | I27: USADOS | J27: JUAN PABLO GONZALEZ ACUÑA | K27: 31-01-2025 12:18:43 | L27: 5971 | M27: 6025802 | N27: 3 | O27: SAN PABLO 1295 DPTO 1116 | P27: 957177616 | S27: SANTIAGO | T27: 20/07/1953 | U27: sgcl3691@gmail.com | V27: KVKD41 | W27: CAMIONETA | X27: SAVEIRO | Y27: 5URTT411 | Z27: BLANCO | AA27: 9BWKB45U5JP102012 | AB27: 9BWKB45U5JP102012 | AC27: CONSIGNACION USADO (Propio) | AD27: Facturada | AE27: 50816 | AF27: 31-01-2025 0:00:00 | AH27: Contrato: 105 | AI27: 5400000 | AJ27: 31-01-2025 0:00:00 | AL27: 0 | AM27: SALON | AN27: 31-01-2025 0:00:00 | AO27: RETAIL | AP27: Peso | AR27: 36 | AS27: 0 | AT27: 0 | AU27: -296830 | AV27: 6493170 | AW27: 5400000 | AX27: 1093170 | AY27: 16.84 % | AZ27: 0 | BA27: 296830 | BB27: 296830 | BC27: 0 | BD27: 0 % | BE27: 0 | BF27: 0 | BG27: 0 | BH27: 0 | BI27: 0 % | BJ27: 0 | BK27: 0 | BL27: 0 | BM27: 0 | BN27: 0 % | BO27: 0 | BP27: 6790000 | BQ27: 5729889 | BR27: 1060111 | BS27: 15.61 % | BT27: 1060111 | BU27: 15.61 % | BV27: 0 | BW27: 0 | BX27: 6790000 | BY27: 0 | BZ27: 296830 | CA27: 0 | CB27: 6790000 | CC27: 6790000 | CD27: 1060111 | CE27: 15.61 % | CG27: 0 | CI27: 0 | CJ27: 0 | CK27: 33059
A28: SUBARU | B28: XV LTD AWD 2.0I AUT | C28: AU-25-01-0023 | D28: 2014 | E28: JF1GP7LC5DG075025 | F28: ORTUZAR SPA | G28: 750000 | H28: =G28*100/CC28 -> 11.811024 | I28: USADOS | J28: RODRIGO MONTANER CABEZON | K28: 31-01-2025 13:38:45 | L28: 5972 | M28: 76981608 | N28: 9 | O28: FRANCISCO BILBAO N° 4740 | Q28: 985775766 | S28: LAS CONDES | U28: francisco.ortuzar@mail.udp.cl | V28: FZXD90 | W28: STATION WAGON 01 | X28: SUBARU | Y28: 24--42365 | Z28: GRAFITO OSCURO | AA28: JF1GP7LC5DG075025 | AB28: JF1GP7LC5DG075025 | AC28: CONSIGNACION USADO (Propio) | AD28: Facturada | AE28: 50814 | AF28: 31-01-2025 0:00:00 | AH28: Contrato: 132 | AI28: 5600000 | AJ28: 31-01-2025 0:00:00 | AL28: 0 | AM28: SALON | AN28: 31-01-2025 0:00:00 | AO28: RETAIL | AP28: Peso | AR28: 0 | AS28: 0 | AT28: 0 | AU28: 0 | AV28: 6350000 | AW28: 5600000 | AX28: 750000 | AY28: 11.81 % | AZ28: 0 | BA28: 0 | BB28: 0 | BC28: 0 | BD28: 0 % | BE28: 0 | BF28: 0 | BG28: 0 | BH28: 0 | BI28: 0 % | BJ28: 0 | BK28: 0 | BL28: 0 | BM28: 0 | BN28: 0 % | BO28: 0 | BP28: 6350000 | BQ28: 5600000 | BR28: 750000 | BS28: 11.81 % | BT28: 750000 | BU28: 11.81 % | BV28: 0 | BW28: 0 | BX28: 6350000 | BY28: 0 | BZ28: 0 | CA28: 0 | CB28: 6350000 | CC28: 6350000 | CD28: 750000 | CE28: 11.81 % | CG28: 0 | CI28: 0 | CJ28: 0 | CK28: 0
A29: MG | B29: ZS 1.5 | C29: AU-25-01-0004 | D29: 2022 | E29: LSJW74U99NZ022666 | F29: CARLOS FEDERICO ROMERO JARA | G29: 900000 | H29: =G29*100/CC29 -> 10.309278 | I29: USADOS | J29: SERGIO POBLETE CAMPOS | K29: 03-02-2025 12:12:27 | L29: 5976 | M29: 9978475 | N29: K | O29: SIMON GONZALEZ 7452 | Q29: 988398566 | S29: LA REINA | T29: 01/06/1979 | U29: CARLOS@ROMERO.PRO | V29: RCJT79 | W29: STATION WAGON 01 | X29: AUTOMOVIL | Y29: 001--ZZ | Z29: NEGRO | AA29: LSJW74U99NZ022666 | AB29: LSJW74U99NZ022666 | AC29: CONSIGNACION USADO (Propio) | AD29: Facturada | AE29: 50819 | AF29: 31-01-2025 0:00:00 | AH29: Contrato: 144 | AI29: 7500000 | AJ29: 31-01-2025 0:00:00 | AL29: 0 | AM29: SALON | AN29: 31-01-2025 0:00:00 | AO29: CC | AP29: Peso | AR29: 18 | AS29: 0 | AT29: 0 | AU29: -590000 | AV29: 8400000 | AW29: 7500000 | AX29: 900000 | AY29: 10.71 % | AZ29: 0 | BA29: 330000 | BB29: 330000 | BC29: 0 | BD29: 0 % | BE29: 0 | BF29: 0 | BG29: 0 | BH29: 0 | BI29: 0 % | BJ29: 0 | BK29: 0 | BL29: 0 | BM29: 0 | BN29: 0 % | BO29: 0 | BP29: 8730000 | BQ29: 7830000 | BR29: 900000 | BS29: 10.31 % | BT29: 900000 | BU29: 10.31 % | BV29: 0 | BW29: 0 | BX29: 8730000 | BY29: 0 | BZ29: 330000 | CA29: 0 | CB29: 8730000 | CC29: 8730000 | CD29: 900000 | CE29: 10.31 % | CG29: 0 | CI29: 0 | CJ29: 0 | CK29: 0
A30: VOLKSWAGEN | B30: TOUAREG 4.2 V8 AUT | C30: AU-25-01-0011 | D30: 2017 | E30: WVGZZZ7PZGD024021 | F30: JAVIER ERNESTO FLORES HAAARDT | G30: 1500000 | H30: =G30*100/CC30 -> 4.606103 | I30: USADOS | J30: SERGIO POBLETE CAMPOS | K30: 05-02-2025 12:09:59 | L30: 5980 | M30: 17087666 | N30: 0 | O30: LO BELTRAN 2488 | Q30: +56981993181 | S30: VITACURA | T30: 11/05/1989 | U30: FLORESM.JAVIER@GMAIL.COM | V30: JBPP80 | W30: JEEP | X30: TOUAREG | Y30: 10--3251 | Z30: GRIS | AA30: WVGZZZ7PZGD024021 | AB30: WVGZZZ7PZGD024021 | AC30: CONSIGNACION USADO (Propio) | AD30: Facturada | AE30: 50817 | AF30: 31-01-2025 0:00:00 | AH30: Contrato: 141 | AI30: 29000000 | AJ30: 02-03-2025 0:00:00 | AL30: 0 | AM30: SALON | AN30: 02-03-2025 0:00:00 | AO30: CC | AP30: Peso | AR30: 10 | AS30: 0 | AT30: 0 | AU30: -2990000 | AV30: 32000000 | AW30: 29000000 | AX30: 3000000 | AY30: 9.38 % | AZ30: 0 | BA30: 565490 | BB30: 565490 | BC30: 0 | BD30: 0 % | BE30: 0 | BF30: 0 | BG30: 0 | BH30: 0 | BI30: 0 % | BJ30: 0 | BK30: 0 | BL30: 0 | BM30: 0 | BN30: 0 % | BO30: 0 | BP30: 32565490 | BQ30: 29565490 | BR30: 3000000 | BS30: 9.21 % | BT30: 3000000 | BU30: 9.21 % | BV30: 0 | BW30: 0 | BX30: 32565490 | BY30: 0 | BZ30: 565490 | CA30: 0 | CB30: 32565490 | CC30: 32565490 | CD30: 3000000 | CE30: 9.21 % | CG30: 0 | CI30: 0 | CJ30: 0 | CK30: 0
A31: VOLKSWAGEN | B31: NUEVO GOL HIGHLINE 1.6 | C31: AU-24-12-0023 | D31: 2022 | E31: 9BWAB45U3NT095747 | F31: CAROLINA ALEJANDRA DEL CARMEN PINTO VACKFLORES | G31: 728670 | H31: =G31*100/CC31 -> 8.2897611 | I31: USADOS | J31: ROBERTO LOBOS GUTIERREZ | K31: 13-01-2025 11:54:42 | L31: 5918 | M31: 18928528 | N31: 0 | O31: DUBLE ALMEYDA 2776 | P31: 999055263 | Q31: 999055263 | S31: ÑUÑOA | T31: 01/01/1900 | U31: caropintov@gmail.com | V31: RWJK91 | W31: AUTOMOVIL | X31: GOL | Y31: 5U7HF411 | Z31: ROJO | AA31: 9BWAB45U3NT095747 | AB31: 9BWAB45U3NT095747 | AC31: CONSIGNACION USADO (Propio) | AD31: Facturada | AE31: 88 | AF31: 24-01-2025 0:00:00 | AH31: Contrato: 142 | AI31: 7750000 | AJ31: 24-01-2025 0:00:00 | AL31: 0 | AM31: SALON | AN31: 24-01-2025 0:00:00 | AO31: CC | AP31: Peso | AQ31: JLRY79 | AR31: 29 | AS31: 0 | AT31: 0 | AU31: -311330 | AV31: 8478670 | AW31: 7750000 | AX31: 728670 | AY31: 8.59 % | AZ31: 0 | BA31: 311330 | BB31: 311330 | BC31: 0 | BD31: 0 % | BE31: 0 | BF31: 0 | BG31: 0 | BH31: 0 | BI31: 0 % | BJ31: 0 | BK31: 0 | BL31: 0 | BM31: 0 | BN31: 0 % | BO31: 0 | BP31: 8790000 | BQ31: 8061330 | BR31: 728670 | BS31: 8.29 % | BT31: 728670 | BU31: 8.29 % | BV31: 0 | BW31: 4000000 | BX31: 4790000 | BY31: 0 | BZ31: 311330 | CA31: 0 | CB31: 8790000 | CC31: 8790000 | CD31: 728670 | CE31: 8.29 % | CG31: 0 | CI31: 0 | CJ31: 0 | CK31: 0
A32: VOLKSWAGEN | B32: GOLF HB SPORT 1.4 AT | C32: AU-24-11-0017 | D32: 2021 | E32: 3VW7B6AU4LM016875 | F32: FRANCISCO IGNACIO CONTRERAS VALENCIA | G32: 477118 | H32: =G32*100/CC32 -> 2.8186802 | I32: USADOS | J32: ROBERTO LOBOS GUTIERREZ | K32: 13-01-2025 12:49:30 | L32: 5919 | M32: 6391594 | N32: 7 | O32: PJE BARTOLOME MURILLO 141 | P32: 988067175 | Q32: 988067175 | S32: ESTACION CENTRAL | T32: 01/07/1954 | U32: FCONTRERAS@ENVACESCARRILLO.CL | V32: PDSP73 | W32: AUTOMOVIL | X32: GOLF | Y32: 10--HBSPORT | Z32: GRIS PLATINO | AA32: 3VW7B6AU4LM016875 | AB32: 3VW7B6AU4LM016875 | AC32: CONSIGNACION USADO (Propio) | AD32: Facturada | AE32: 89 | AF32: 31-01-2025 0:00:00 | AH32: Contrato: 141 | AI32: 16022882 | AJ32: 31-01-2025 0:00:00 | AL32: 0 | AM32: SALON | AN32: 31-01-2025 0:00:00 | AO32: CC | AP32: Peso | AR32: 73 | AS32: 0 | AT32: 0 | AU32: -490000 | AV32: 16500000 | AW32: 16022882 | AX32: 477118 | AY32: 2.89 % | AZ32: 0 | BA32: 427000 | BB32: 427000 | BC32: 0 | BD32: 0 % | BE32: 0 | BF32: 0 | BG32: 0 | BH32: 0 | BI32: 0 % | BJ32: 0 | BK32: 0 | BL32: 0 | BM32: 0 | BN32: 0 % | BO32: 0 | BP32: 16927000 | BQ32: 16449882 | BR32: 477118 | BS32: 2.82 % | BT32: 477118 | BU32: 2.82 % | BV32: 0 | BW32: 0 | BX32: 16927000 | BY32: 0 | BZ32: 427000 | CA32: 0 | CB32: 16927000 | CC32: 16927000 | CD32: 477118 | CE32: 2.82 % | CG32: 0 | CI32: 0 | CJ32: 0 | CK32: 0
F34: Suma total | G34: =SUM(G2:G32) -> 36306117 | H34: =AVERAGE(H2:H32) -> 9.8973478
F35: Promedio | G35: =AVERAGE(G2:G32) -> 1171165.1
F36: Cantidad | G36: =COUNTA(G2:G32) -> 31

Sheet Archivo con Bonos Ingresados 
